Workbook
Name _Hlk106371315: #REF!
Name _Hlk106708335: #REF!
Name _Hlk106708400: #REF!
Name _Hlk106710563: #REF!

Sheet Regression_ Test_Summary (2)
A1: Regression Test Summary
A3: Objective: | B3: 1 | C3: Verify Policy workflow, Transactions creation and Integrations are working as expected on identified Scenarios
A4: Environment: STG2
A5: Data: | B5: 1 | C5: Date:
B6: 2 | C6: Environment URL = https://dragonstg2.aws.purehnw.online
B7: 3 | C7: Login = Okta tile
A9: Status: | B9: N | C9: = Not executed by QA
B10: P | C10: = Passed by QA
B11: F | C11: = Failed by QA
B12: T | C12: = Testing in progress
B13: R | C13: = Rejected / Existing issue
B14: B | C14: = Blocked by QA
A16: Test | B16: SC# | C16: Regression Suites | D16: QA Assigned | E16: Area | F16: LOB | G16: States | H16: Number of Test Cases | I16: Aprox. Execution Time (hrs) | J16: Environment | K16: Number of TC Passed | L16: % of TC Passed | M16: Number od TC Failed | N16: % TC Failed | O16: Number of TC blocked | P16: % of TC Blocked | Q16: Number of TC in Progress | R16: % of TC in Progress | S16: Number of Rejected / Existing issues | T16: % of Rejected / Existing issues | U16: Number of TC Executed | V16: % Executed | W16: Scenario Priority | X16: Automated Y/P/N | Y16: Status | Z16: Comments
A17: Functional | B17: 1 | C17: Browser testing | D17: Done | E17: Underwriting | F17: ALL | G17: Not State Specific | H17: 15 | I17: 5 | J17: ALL | K17: =COUNTIF('Browser testing'!$E23:$E1501,"P") -> 0 | L17: =K17/$H17 -> 0 | M17: =COUNTIF('Browser testing'!$E23:$E1501,"F") -> 0 | N17: =M17/$H17 -> 0 | O17: =COUNTIF('Browser testing'!$E23:$E1501,"B") -> 0 | P17: =O17/H17 -> 0 | Q17: =COUNTIF('Browser testing'!$E23:$E1501,"T") -> 0 | R17: =Q17/$H17 -> 0 | S17: =COUNTIF('Browser testing'!$E23:$E1501,"R") -> 0 | T17: =S17/$H17 -> 0 | U17: =K17+M17+O17+S17 -> 0 | V17: =U17/$H17 -> 0 | W17: High | X17: =IF(D5="A","Automated",IF(D5="M","Manual")) -> FALSE | Y17: N
A18: Functional | B18: 2 | C18: BSE Broker Self Service Endorsement | D18: Few items to be checked | E18: Underwriting | F18: ALL | H18: 30 | I18: 15 | J18: ALL | K18: =COUNTIF(BSE!$E23:$E258,"P") -> 0 | L18: =K18/$H18 -> 0 | M18: =COUNTIF(BSE!$E23:$E258,"F") -> 0 | N18: =M18/$H18 -> 0 | O18: =COUNTIF(BSE!$E23:$E258,"B") -> 0 | P18: =O18/H18 -> 0 | Q18: =COUNTIF(BSE!$E23:$E258,"T") -> 0 | R18: =Q18/$H18 -> 0 | S18: =COUNTIF(BSE!$E23:$E258,"R") -> 0 | T18: =S18/$H18 -> 0 | U18: =K18+M18+O18+S18 -> 0 | V18: =U18/$H18 -> 0 | W18: High | X18: Y | Y18: N
A19: Functional | B19: 3 | C19: TASKS | D19: Done | E19: Underwriting | F19: ALL | H19: 6 | I19: 4 | J19: ALL | K19: =COUNTIF('Tasks & Emails'!$E23:$E1503,"P") -> 0 | L19: =K19/$H19 -> 0 | M19: =COUNTIF('Tasks & Emails'!$E23:$E1503,"F") -> 0 | N19: =M19/$H19 -> 0 | O19: =COUNTIF('Tasks & Emails'!$E23:$E1503,"B") -> 0 | P19: =O19/H19 -> 0 | Q19: =COUNTIF('Tasks & Emails'!$E23:$E1503,"T") -> 0 | R19: =Q19/$H19 -> 0 | S19: =COUNTIF('Tasks & Emails'!$E23:$E1503,"R") -> 0 | T19: =S19/$H19 -> 0 | U19: =K19+M19+O19+S19 -> 0 | V19: =U19/$H19 -> 0 | X19: P | Y19: N
A20: Functional | B20: 4 | C20: BOR | D20: Done | E20: Underwriting | F20: ALL | H20: 13 | I20: 5 | J20: ALL | K20: =COUNTIF(BOR!$E$23:$E1478,"P") -> 0 | L20: =K20/$H20 -> 0 | M20: =COUNTIF(BOR!$E$23:$E1478,"F") -> 0 | N20: =M20/$H20 -> 0 | O20: =COUNTIF(BOR!$E$23:$E1478,"B") -> 0 | P20: =O20/H20 -> 0 | Q20: =COUNTIF(BOR!$E$23:$E1478,"T") -> 0 | R20: =Q20/$H20 -> 0 | S20: =COUNTIF(BOR!$E$23:$E1478,"R") -> 0 | T20: =S20/$H20 -> 0 | U20: =K20+M20+O20+S20 -> 0 | V20: =U20/$H20 -> 0 | W20: Critical | X20: P | Y20: N
A21: Integration | B21: 5 | C21: OFAC | D21: Done | E21: Integration | F21: ALL | G21: Not State Specific | H21: 6 | I21: 3 | J21: ALL | K21: =COUNTIF(OFAC!$E$23:$E1664,"P") -> 0 | L21: =K21/$H21 -> 0 | M21: =COUNTIF(OFAC!$E$23:$E1664,"F") -> 0 | N21: =M21/$H21 -> 0 | O21: =COUNTIF(OFAC!$E$23:$E1664,"B") -> 0 | P21: =O21/H21 -> 0 | Q21: =COUNTIF(OFAC!$E$23:$E1664,"T") -> 0 | R21: =Q21/$H21 -> 0 | S21: =COUNTIF(OFAC!$E$23:$E1664,"R") -> 0 | T21: =S21/$H21 -> 0 | U21: =K21+M21+O21+S21 -> 0 | V21: =U21/$H21 -> 0 | W21: High | X21: Y | Y21: N
A22: Functional | B22: 6 | C22: Carrier Partners HS | D22: Done | E22: Underwriting | F22: HS, ES | H22: 5 | I22: 3 | J22: ALL | K22: =COUNTIF('Carrier Partners HS'!$E$23:$E1458,"P") -> 0 | L22: =K22/$H22 -> 0 | M22: =COUNTIF('Carrier Partners HS'!$E$23:$E1458,"F") -> 0 | N22: =M22/$H22 -> 0 | O22: =COUNTIF('Carrier Partners HS'!$E$23:$E1458,"B") -> 0 | P22: =O22/H22 -> 0 | Q22: =COUNTIF('Carrier Partners HS'!$E$23:$E1458,"T") -> 0 | R22: =Q22/$H22 -> 0 | S22: =COUNTIF('Carrier Partners HS'!$E$23:$E1458,"R") -> 0 | T22: =S22/$H22 -> 0 | U22: =K22+M22+O22+S22 -> 0 | V22: =U22/$H22 -> 0 | W22: Medium | X22: Y | Y22: N
A23: Functional | B23: 7 | C23: Carrier Partners ES | D23: Done | E23: Underwriting | F23: ES | H23: 3 | I23: 1 | J23: ALL | K23: =COUNTIF('Carrier Partners ES'!$E$23:$E1509,"P") -> 0 | L23: =K23/$H23 -> 0 | M23: =COUNTIF('Carrier Partners ES'!$E$23:$E1509,"F") -> 0 | N23: =M23/$H23 -> 0 | O23: =COUNTIF('Carrier Partners ES'!$E$23:$E1509,"B") -> 0 | P23: =O23/H23 -> 0 | Q23: =COUNTIF('Carrier Partners ES'!$E$23:$E1509,"T") -> 0 | R23: =Q23/$H23 -> 0 | S23: =COUNTIF('Carrier Partners ES'!$E$23:$E1509,"R") -> 0 | T23: =S23/$H23 -> 0 | U23: =K23+M23+O23+S23 -> 0 | V23: =U23/$H23 -> 0 | W23: Medium | X23: Y | Y23: N
A24: Functional | B24: 8 | C24: Aggregation zone HS | D24: Done | E24: Underwriting | F24: HS | H24: 2 | I24: 1 | J24: ALL | K24: =COUNTIF('Aggregation zone HS'!$E$23:$E1510,"P") -> 0 | L24: =K24/$H24 -> 0 | M24: =COUNTIF('Aggregation zone HS'!$E$23:$E1510,"F") -> 0 | N24: =M24/$H24 -> 0 | O24: =COUNTIF('Aggregation zone HS'!$E$23:$E1510,"B") -> 0 | P24: =O24/H24 -> 0 | Q24: =COUNTIF('Aggregation zone HS'!$E$23:$E1510,"T") -> 0 | R24: =Q24/$H24 -> 0 | S24: =COUNTIF('Aggregation zone HS'!$E$23:$E1510,"R") -> 0 | T24: =S24/$H24 -> 0 | U24: =K24+M24+O24+S24 -> 0 | V24: =U24/$H24 -> 0 | W24: Medium | X24: N/A | Y24: N
A25: Functional | B25: 9 | C25: TIV HS | D25: Done | E25: Underwriting | F25: HS | H25: 2 | I25: 1 | J25: ALL | K25: =COUNTIF('TIV HS'!$E$23:$E1511,"P") -> 0 | L25: =K25/$H25 -> 0 | M25: =COUNTIF('TIV HS'!$E$23:$E1511,"F") -> 0 | N25: =M25/$H25 -> 0 | O25: =COUNTIF('TIV HS'!$E$23:$E1511,"B") -> 0 | P25: =O25/H25 -> 0 | Q25: =COUNTIF('TIV HS'!$E$23:$E1511,"T") -> 0 | R25: =Q25/$H25 -> 0 | S25: =COUNTIF('TIV HS'!$E$23:$E1511,"R") -> 0 | T25: =S25/$H25 -> 0 | U25: =K25+M25+O25+S25 -> 0 | V25: =U25/$H25 -> 0 | W25: High | X25: Y | Y25: N
A26: Integration | B26: 10 | C26: AIR HS FL | D26: Done | E26: Integration | F26: HS | G26: ALL | H26: 2 | I26: 1.5 | J26: ALL | K26: =COUNTIF('AIR HS FL'!$E$23:$E1545,"P") -> 0 | L26: =K26/$H26 -> 0 | M26: =COUNTIF('AIR HS FL'!$E$23:$E1545,"F") -> 0 | N26: =M26/$H26 -> 0 | O26: =COUNTIF('AIR HS FL'!$E$23:$E1545,"B") -> 0 | P26: =O26/H26 -> 0 | Q26: =COUNTIF('AIR HS FL'!$E$23:$E1545,"T") -> 0 | R26: =Q26/$H26 -> 0 | S26: =COUNTIF('AIR HS FL'!$E$23:$E1545,"R") -> 0 | T26: =S26/$H26 -> 0 | U26: =K26+M26+O26+S26 -> 0 | V26: =U26/$H26 -> 0 | W26: Critical | X26: Y | Y26: N
A27: Integration | B27: 11 | C27: RMS HS FL | D27: Done | E27: Integration | F27: HS | G27: CA, WA, OR | H27: 2 | I27: 1 | J27: ALL | K27: =COUNTIF('RMS HS TX'!$E$23:$E1561,"P") -> 0 | L27: =K27/$H27 -> 0 | M27: =COUNTIF('RMS HS TX'!$E$23:$E1561,"F") -> 0 | N27: =M27/$H27 -> 0 | O27: =COUNTIF('RMS HS TX'!$E$23:$E1561,"B") -> 0 | P27: =O27/H27 -> 0 | Q27: =COUNTIF('RMS HS TX'!$E$23:$E1561,"T") -> 0 | R27: =Q27/$H27 -> 0 | S27: =COUNTIF('RMS HS TX'!$E$23:$E1561,"R") -> 0 | T27: =S27/$H27 -> 0 | U27: =K27+M27+O27+S27 -> 0 | V27: =U27/$H27 -> 0 | W27: High | X27: Y | Y27: N
A28: Integration | B28: 12 | C28: Elevation Certificate | D28: Done | E28: Integration | F28: HO | H28: 8 | I28: 3 | J28: ALL | K28: =COUNTIF('Elevation Certificate '!$E$23:$E1528,"P") -> 0 | L28: =K28/$H28 -> 0 | M28: =COUNTIF('Elevation Certificate '!$E$23:$E1528,"F") -> 0 | N28: =M28/$H28 -> 0 | O28: =COUNTIF('Elevation Certificate '!$E$23:$E1528,"B") -> 0 | P28: =O28/H28 -> 0 | Q28: =COUNTIF('Elevation Certificate '!$E$23:$E1528,"T") -> 0 | R28: =Q28/$H28 -> 0 | S28: =COUNTIF('Elevation Certificate '!$E$23:$E1528,"R") -> 0 | T28: =S28/$H28 -> 0 | U28: =K28+M28+O28+S28 -> 0 | V28: =U28/$H28 -> 0 | W28: High | X28: Y | Y28: N
A29: Integration | B29: 13 | C29: Earthquake report | D29: Done | E29: Integration | F29: HO | H29: 9 | I29: 5 | J29: ALL | K29: =COUNTIF('Earthquake report'!$E$23:$E1602,"P") -> 0 | L29: =K29/$H29 -> 0 | M29: =COUNTIF('Earthquake report'!$E$23:$E1602,"F") -> 0 | N29: =M29/$H29 -> 0 | O29: =COUNTIF('Earthquake report'!$E$23:$E1602,"B") -> 0 | P29: =O29/H29 -> 0 | Q29: =COUNTIF('Earthquake report'!$E$23:$E1602,"T") -> 0 | R29: =Q29/$H29 -> 0 | S29: =COUNTIF('Earthquake report'!$E$23:$E1602,"R") -> 0 | T29: =S29/$H29 -> 0 | U29: =K29+M29+O29+S29 -> 0 | V29: =U29/$H29 -> 0 | W29: High | X29: Y | Y29: N
A30: Integration | B30: 14 | C30: Wildfire Hazard reports | D30: Done | E30: Integration | F30: HO | H30: 8 | I30: 5 | J30: ALL | K30: =COUNTIF('Wildfire Hazard reports'!$E$23:$E1455,"P") -> 0 | L30: =K30/$H30 -> 0 | M30: =COUNTIF('Wildfire Hazard reports'!$E$23:$E1455,"F") -> 0 | N30: =M30/$H30 -> 0 | O30: =COUNTIF('Wildfire Hazard reports'!$E$23:$E1455,"B") -> 0 | P30: =O30/H30 -> 0 | Q30: =COUNTIF('Wildfire Hazard reports'!$E$23:$E1455,"T") -> 0 | R30: =Q30/$H30 -> 0 | S30: =COUNTIF('Wildfire Hazard reports'!$E$23:$E1455,"R") -> 0 | T30: =S30/$H30 -> 0 | U30: =K30+M30+O30+S30 -> 0 | V30: =U30/$H30 -> 0 | W30: High | X30: Y | Y30: N
A31: Functional | B31: 15 | C31: Moratorium | D31: Few items to be checked | E31: Underwriting | F31: ALL | H31: 18 | I31: 7 | J31: ALL | K31: =COUNTIF(Moratorium!$E$23:$E1518,"P") -> 0 | L31: =K31/$H31 -> 0 | M31: =COUNTIF(Moratorium!$E$23:$E1518,"F") -> 0 | N31: =M31/$H31 -> 0 | O31: =COUNTIF(Moratorium!$E$23:$E1518,"B") -> 0 | P31: =O31/H31 -> 0 | Q31: =COUNTIF(Moratorium!$E$23:$E1518,"T") -> 0 | R31: =Q31/$H31 -> 0 | S31: =COUNTIF(Moratorium!$E$23:$E1518,"R") -> 0 | T31: =S31/$H31 -> 0 | U31: =K31+M31+O31+S31 -> 0 | V31: =U31/$H31 -> 0 | W31: High | X31: N | Y31: N
A32: Integration | B32: 16 | C32: Docusign | D32: Few items to be checked | E32: Integration | F32: ALL | G32: Not State Specific | H32: 22 | I32: 5 | J32: ALL | K32: =COUNTIF('Dragon-DocuSign'!$E$23:$E1519,"P") -> 0 | L32: =K32/$H32 -> 0 | M32: =COUNTIF('Dragon-DocuSign'!$E$23:$E1519,"F") -> 0 | N32: =M32/$H32 -> 0 | O32: =COUNTIF('Dragon-DocuSign'!$E$23:$E1519,"B") -> 0 | P32: =O32/H32 -> 0 | Q32: =COUNTIF('Dragon-DocuSign'!$E$23:$E1519,"T") -> 0 | R32: =Q32/$H32 -> 0 | S32: =COUNTIF('Dragon-DocuSign'!$E$23:$E1519,"R") -> 0 | T32: =S32/$H32 -> 0 | U32: =K32+M32+O32+S32 -> 0 | V32: =U32/$H32 -> 0 | W32: High | X32: P | Y32: N
A33: Functional | B33: 17 | C33: ITNR | D33: Done | E33: Underwriting | F33: ALL | H33: 10 | I33: 2 | J33: ALL | K33: =COUNTIF(ITNR!$E$23:$E1520,"P") -> 0 | L33: =K33/$H33 -> 0 | M33: =COUNTIF(ITNR!$E$23:$E1520,"F") -> 0 | N33: =M33/$H33 -> 0 | O33: =COUNTIF(ITNR!$E$23:$E1520,"B") -> 0 | P33: =O33/H33 -> 0 | Q33: =COUNTIF(ITNR!$E$23:$E1520,"T") -> 0 | R33: =Q33/$H33 -> 0 | S33: =COUNTIF(ITNR!$E$23:$E1520,"R") -> 0 | T33: =S33/$H33 -> 0 | U33: =K33+M33+O33+S33 -> 0 | V33: =U33/$H33 -> 0 | W33: Medium | X33: P | Y33: N
A34: Functional | B34: 18 | C34: Agent Resource | D34: Done | E34: Underwriting | F34: NA | G34: ALL | H34: 8 | I34: 1 | J34: ALL | K34: =COUNTIF('Agent Resource'!$E$23:$E1521,"P") -> 0 | L34: =K34/$H34 -> 0 | M34: =COUNTIF('Agent Resource'!$E$23:$E1521,"F") -> 0 | N34: =M34/$H34 -> 0 | O34: =COUNTIF('Agent Resource'!$E$23:$E1521,"B") -> 0 | P34: =O34/H34 -> 0 | Q34: =COUNTIF('Agent Resource'!$E$23:$E1521,"T") -> 0 | R34: =Q34/$H34 -> 0 | S34: =COUNTIF('Agent Resource'!$E$23:$E1521,"R") -> 0 | T34: =S34/$H34 -> 0 | U34: =K34+M34+O34+S34 -> 0 | V34: =U34/$H34 -> 0 | W34: Low | X34: N/A | Y34: N
A35: Integration | B35: 19 | C35: Predictive analytics - Home model | D35: Done | E35: Integration | F35: HO | H35: 2 | I35: 2 | J35: ALL | K35: =COUNTIF('Predictive analytics-Home model'!$E$23:$E1789,"P") -> 0 | L35: =K35/$H35 -> 0 | M35: =COUNTIF('Predictive analytics-Home model'!$E$23:$E1789,"F") -> 0 | N35: =M35/$H35 -> 0 | O35: =COUNTIF('Predictive analytics-Home model'!$E$23:$E1789,"B") -> 0 | P35: =O35/H35 -> 0 | Q35: =COUNTIF('Predictive analytics-Home model'!$E$23:$E1789,"T") -> 0 | R35: =Q35/$H35 -> 0 | S35: =COUNTIF('Predictive analytics-Home model'!$E$23:$E1789,"R") -> 0 | T35: =S35/$H35 -> 0 | U35: =K35+M35+O35+S35 -> 0 | V35: =U35/$H35 -> 0 | W35: High | X35: Y | Y35: N
A36: Integration | B36: 20 | C36: Predictive analytics - Auto model | D36: Done | E36: Integration | F36: PA | H36: 2 | I36: 2 | J36: ALL | K36: =COUNTIF('Predictive analytics-Auto model'!$E$23:$E1556,"P") -> 0 | L36: =K36/$H36 -> 0 | M36: =COUNTIF('Predictive analytics-Auto model'!$E$23:$E1556,"F") -> 0 | N36: =M36/$H36 -> 0 | O36: =COUNTIF('Predictive analytics-Auto model'!$E$23:$E1556,"B") -> 0 | P36: =O36/H36 -> 0 | Q36: =COUNTIF('Predictive analytics-Auto model'!$E$23:$E1556,"T") -> 0 | R36: =Q36/$H36 -> 0 | S36: =COUNTIF('Predictive analytics-Auto model'!$E$23:$E1556,"R") -> 0 | T36: =S36/$H36 -> 0 | U36: =K36+M36+O36+S36 -> 0 | V36: =U36/$H36 -> 0 | W36: High | X36: Y | Y36: N
A37: Integration | B37: 21 | C37: Predictive analytics - Excess model | D37: Done | E37: Integration | F37: EX | H37: 4 | I37: 2 | J37: ALL | K37: =COUNTIF('Predictive analytics-Excess mod'!$E$23:$E1554,"P") -> 0 | L37: =K37/$H37 -> 0 | M37: =COUNTIF('Predictive analytics-Excess mod'!$E$23:$E1554,"F") -> 0 | N37: =M37/$H37 -> 0 | O37: =COUNTIF('Predictive analytics-Excess mod'!$E$23:$E1554,"B") -> 0 | P37: =O37/H37 -> 0 | Q37: =COUNTIF('Predictive analytics-Excess mod'!$E$23:$E1554,"T") -> 0 | R37: =Q37/$H37 -> 0 | S37: =COUNTIF('Predictive analytics-Excess mod'!$E$23:$E1554,"R") -> 0 | T37: =S37/$H37 -> 0 | U37: =K37+M37+O37+S37 -> 0 | V37: =U37/$H37 -> 0 | W37: High | X37: Y | Y37: N
A38: Functional | B38: 22 | C38: Account Grade Summary | D38: Done | E38: Underwriting | F38: ALL | H38: 2 | I38: 1 | J38: ALL | K38: =COUNTIF('Account Grade Summary'!$E$23:$E1525,"P") -> 0 | L38: =K38/$H38 -> 0 | M38: =COUNTIF('Account Grade Summary'!$E$23:$E1525,"F") -> 0 | N38: =M38/$H38 -> 0 | O38: =COUNTIF('Account Grade Summary'!$E$23:$E1525,"B") -> 0 | P38: =O38/H38 -> 0 | Q38: =COUNTIF('Account Grade Summary'!$E$23:$E1525,"T") -> 0 | R38: =Q38/$H38 -> 0 | S38: =COUNTIF('Account Grade Summary'!$E$23:$E1525,"R") -> 0 | T38: =S38/$H38 -> 0 | U38: =K38+M38+O38+S38 -> 0 | V38: =U38/$H38 -> 0 | W38: High | X38: Y | Y38: N
A39: Functional | B39: 23 | C39: Roles/Authority - Sub Roles | E39: Underwriting | F39: ALL | H39: 94 | I39: 35 | J39: ALL | K39: =COUNTIF('Roles Authority - Sub Roles'!$E$23:$E1525,"P") -> 0 | L39: =K39/$H39 -> 0 | M39: =COUNTIF('Roles Authority - Sub Roles'!$E$23:$E1525,"F") -> 0 | N39: =M39/$H39 -> 0 | O39: =COUNTIF('Roles Authority - Sub Roles'!$E$23:$E1525,"B") -> 0 | P39: =O39/H39 -> 0 | Q39: =COUNTIF('Roles Authority - Sub Roles'!$E$23:$E1525,"T") -> 0 | R39: =Q39/$H39 -> 0 | S39: =COUNTIF('Roles Authority - Sub Roles'!$E$23:$E1525,"R") -> 0 | T39: =S39/$H39 -> 0 | U39: =K39+M39+O39+S39 -> 0 | V39: =U39/$H39 -> 0 | W39: High | X39: N | Y39: N
A40: Integration | B40: 24 | C40: Home CLUE | E40: Integration | F40: HO | H40: 17 | I40: 4 | J40: ALL | K40: =COUNTIF('Dragon-LexisNexis HO CLUE'!$E$23:$E1561,"P") -> 0 | L40: =K40/$H40 -> 0 | M40: =COUNTIF('Dragon-LexisNexis HO CLUE'!$E$23:$E1561,"F") -> 0 | N40: =M40/$H40 -> 0 | O40: =COUNTIF('Dragon-LexisNexis HO CLUE'!$E$23:$E1561,"B") -> 0 | P40: =O40/H40 -> 0 | Q40: =COUNTIF('Dragon-LexisNexis HO CLUE'!$E$23:$E1561,"T") -> 0 | R40: =Q40/$H40 -> 0 | S40: =COUNTIF('Dragon-LexisNexis HO CLUE'!$E$23:$E1561,"R") -> 0 | T40: =S40/$H40 -> 0 | U40: =K40+M40+O40+S40 -> 0 | V40: =U40/$H40 -> 0 | W40: High | X40: N | Y40: N
A41: Integration | B41: 25 | C41: Auto CLUE | E41: Integration | F41: PA | H41: 16 | I41: 4 | J41: ALL | K41: =COUNTIF('Dragon-LexisNexis PA CLUE'!$E$23:$E1605,"P") -> 0 | L41: =K41/$H41 -> 0 | M41: =COUNTIF('Dragon-LexisNexis PA CLUE'!$E$23:$E1605,"F") -> 0 | N41: =M41/$H41 -> 0 | O41: =COUNTIF('Dragon-LexisNexis PA CLUE'!$E$23:$E1605,"B") -> 0 | P41: =O41/H41 -> 0 | Q41: =COUNTIF('Dragon-LexisNexis PA CLUE'!$E$23:$E1605,"T") -> 0 | R41: =Q41/$H41 -> 0 | S41: =COUNTIF('Dragon-LexisNexis PA CLUE'!$E$23:$E1605,"R") -> 0 | T41: =S41/$H41 -> 0 | U41: =K41+M41+O41+S41 -> 0 | V41: =U41/$H41 -> 0 | W41: High | X41: N | Y41: N
A42: Integration | B42: 26 | C42: Auto MVR | E42: Integration | F42: PA | G42: ALL | H42: 13 | I42: 4 | J42: ALL | K42: =COUNTIF('Dragon-LexisNexis PA MVR'!$E$23:$E1593,"P") -> 0 | L42: =K42/$H42 -> 0 | M42: =COUNTIF('Dragon-LexisNexis PA MVR'!$E$23:$E1593,"F") -> 0 | N42: =M42/$H42 -> 0 | O42: =COUNTIF('Dragon-LexisNexis PA MVR'!$E$23:$E1593,"B") -> 0 | P42: =O42/H42 -> 0 | Q42: =COUNTIF('Dragon-LexisNexis PA MVR'!$E$23:$E1593,"T") -> 0 | R42: =Q42/$H42 -> 0 | S42: =COUNTIF('Dragon-LexisNexis PA MVR'!$E$23:$E1593,"R") -> 0 | T42: =S42/$H42 -> 0 | U42: =K42+M42+O42+S42 -> 0 | V42: =U42/$H42 -> 0 | W42: High | X42: N | Y42: N
A43: Integration | B43: 27 | C43: Excess CLUE | E43: Integration | F43: EX | H43: 14 | I43: 3 | J43: ALL | K43: =COUNTIF('Dragon-LexisNexis EX CLUE'!$E$24:$E1666,"P") -> 0 | L43: =K43/$H43 -> 0 | M43: =COUNTIF('Dragon-LexisNexis EX CLUE'!$E$24:$E1666,"F") -> 0 | N43: =M43/$H43 -> 0 | O43: =COUNTIF('Dragon-LexisNexis EX CLUE'!$E$24:$E1666,"B") -> 0 | P43: =O43/H43 -> 0 | Q43: =COUNTIF('Dragon-LexisNexis EX CLUE'!$E$24:$E1666,"T") -> 0 | R43: =Q43/$H43 -> 0 | S43: =COUNTIF('Dragon-LexisNexis EX CLUE'!$E$24:$E1666,"R") -> 0 | T43: =S43/$H43 -> 0 | U43: =K43+M43+O43+S43 -> 0 | V43: =U43/$H43 -> 0 | W43: High | X43: N | Y43: N
A44: Integration | B44: 28 | C44: Excess MVR | E44: Integration | F44: EX | H44: 8 | I44: 1 | J44: ALL | K44: =COUNTIF(#REF!,"P") -> #REF! | L44: =K44/$H44 -> #REF! | M44: =COUNTIF(#REF!,"F") -> #REF! | N44: =M44/$H44 -> #REF! | O44: =COUNTIF(#REF!,"B") -> #REF! | P44: =O44/H44 -> #REF! | Q44: =COUNTIF(#REF!,"T") -> #REF! | R44: =Q44/$H44 -> #REF! | S44: =COUNTIF(#REF!,"R") -> #REF! | T44: =S44/$H44 -> #REF! | U44: =K44+M44+O44+S44 -> #REF! | V44: =U44/$H44 -> #REF! | W44: High | X44: N | Y44: N
A45: Integration | B45: 29 | C45: Home prefill | E45: Integration | F45: HO | H45: 19 | I45: 3 | J45: ALL | K45: =COUNTIF('Dragon-LexisNexis HO prefill'!$E$23:$E1731,"P") -> 0 | L45: =K45/$H45 -> 0 | M45: =COUNTIF('Dragon-LexisNexis HO prefill'!$E$23:$E1731,"F") -> 0 | N45: =M45/$H45 -> 0 | O45: =COUNTIF('Dragon-LexisNexis HO prefill'!$E$23:$E1731,"B") -> 0 | P45: =O45/H45 -> 0 | Q45: =COUNTIF('Dragon-LexisNexis HO prefill'!$E$23:$E1731,"T") -> 0 | R45: =Q45/$H45 -> 0 | S45: =COUNTIF('Dragon-LexisNexis HO prefill'!$E$23:$E1731,"R") -> 0 | T45: =S45/$H45 -> 0 | U45: =K45+M45+O45+S45 -> 0 | V45: =U45/$H45 -> 0 | W45: High | X45: N | Y45: N
A46: Integration | B46: 30 | C46: Auto prefill | E46: Integration | F46: PA | H46: 6 | I46: 1.5 | J46: ALL | K46: =COUNTIF('Dragon-LexisNexis PA prefill'!$E$23:$E1513,"P") -> 0 | L46: =K46/$H46 -> 0 | M46: =COUNTIF('Dragon-LexisNexis PA prefill'!$E$23:$E1513,"F") -> 0 | N46: =M46/$H46 -> 0 | O46: =COUNTIF('Dragon-LexisNexis PA prefill'!$E$23:$E1513,"B") -> 0 | P46: =O46/H46 -> 0 | Q46: =COUNTIF('Dragon-LexisNexis PA prefill'!$E$23:$E1513,"T") -> 0 | R46: =Q46/$H46 -> 0 | S46: =COUNTIF('Dragon-LexisNexis PA prefill'!$E$23:$E1513,"R") -> 0 | T46: =S46/$H46 -> 0 | U46: =K46+M46+O46+S46 -> 0 | V46: =U46/$H46 -> 0 | W46: High | X46: N | Y46: N
A47: Integration | B47: 31 | C47: Auto NADA (Coll Symbol, OTC, PIP) | E47: Integration | F47: PA | H47: 6 | I47: 2 | J47: ALL | K47: =COUNTIF('Auto NADA(Coll Symbol,OTC,PIP)'!$E$23:$E1541,"P") -> 0 | L47: =K47/$H47 -> 0 | M47: =COUNTIF('Auto NADA(Coll Symbol,OTC,PIP)'!$E$23:$E1541,"F") -> 0 | N47: =M47/$H47 -> 0 | O47: =COUNTIF('Auto NADA(Coll Symbol,OTC,PIP)'!$E$23:$E1541,"B") -> 0 | P47: =O47/H47 -> 0 | Q47: =COUNTIF('Auto NADA(Coll Symbol,OTC,PIP)'!$E$23:$E1541,"T") -> 0 | R47: =Q47/$H47 -> 0 | S47: =COUNTIF('Auto NADA(Coll Symbol,OTC,PIP)'!$E$23:$E1541,"R") -> 0 | T47: =S47/$H47 -> 0 | U47: =K47+M47+O47+S47 -> 0 | V47: =U47/$H47 -> 0 | W47: High | X47: P | Y47: N
A48: Integration | B48: 32 | C48: PW NADA | E48: Integration | F48: PW | H48: 10 | I48: 2 | J48: ALL | K48: =COUNTIF('PW NADA'!$E$23:$E1542,"P") -> 0 | L48: =K48/$H48 -> 0 | M48: =COUNTIF('PW NADA'!$E$23:$E1542,"F") -> 0 | N48: =M48/$H48 -> 0 | O48: =COUNTIF('PW NADA'!$E$23:$E1542,"B") -> 0 | P48: =O48/H48 -> 0 | Q48: =COUNTIF('PW NADA'!$E$23:$E1542,"T") -> 0 | R48: =Q48/$H48 -> 0 | S48: =COUNTIF('PW NADA'!$E$23:$E1542,"R") -> 0 | T48: =S48/$H48 -> 0 | U48: =K48+M48+O48+S48 -> 0 | V48: =U48/$H48 -> 0 | W48: High | X48: N | Y48: N
A49: Integration | B49: 33 | C49: Carfax | E49: Integration | F49: PA | H49: 8 | I49: 6 | J49: ALL | K49: =COUNTIF(Carfax!$E$23:$E1531,"P") -> 0 | L49: =K49/$H49 -> 0 | M49: =COUNTIF(Carfax!$E$23:$E1531,"F") -> 0 | N49: =M49/$H49 -> 0 | O49: =COUNTIF(Carfax!$E$23:$E1531,"B") -> 0 | P49: =O49/H49 -> 0 | Q49: =COUNTIF(Carfax!$E$23:$E1531,"T") -> 0 | R49: =Q49/$H49 -> 0 | S49: =COUNTIF(Carfax!$E$23:$E1531,"R") -> 0 | T49: =S49/$H49 -> 0 | U49: =K49+M49+O49+S49 -> 0 | V49: =U49/$H49 -> 0 | W49: High | X49: N | Y49: N
A50: Functional | B50: 34 | C50: PURE Claims (Add template) | E50: Functional | F50: ALL | H50: 5 | I50: 3 | J50: ALL | K50: =COUNTIF('PURE Claims '!$E$23:$E1538,"P") -> 0 | L50: =K50/$H50 -> 0 | M50: =COUNTIF('PURE Claims '!$E$23:$E1538,"F") -> 0 | N50: =M50/$H50 -> 0 | O50: =COUNTIF('PURE Claims '!$E$23:$E1538,"B") -> 0 | P50: =O50/H50 -> 0 | Q50: =COUNTIF('PURE Claims '!$E$23:$E1538,"T") -> 0 | R50: =Q50/$H50 -> 0 | S50: =COUNTIF('PURE Claims '!$E$23:$E1538,"R") -> 0 | T50: =S50/$H50 -> 0 | U50: =K50+M50+O50+S50 -> 0 | V50: =U50/$H50 -> 0 | W50: High | Y50: N
A51: Functional | B51: 35 | C51: End submission | E51: Underwriting | F51: ALL | G51: ALL | H51: 20 | I51: 5 | J51: ALL | K51: =COUNTIF('End submission'!$E$23:$E1544,"P") -> 0 | L51: =K51/$H51 -> 0 | M51: =COUNTIF('End submission'!$E$23:$E1544,"F") -> 0 | N51: =M51/$H51 -> 0 | O51: =COUNTIF('End submission'!$E$23:$E1544,"B") -> 0 | P51: =O51/H51 -> 0 | Q51: =COUNTIF('End submission'!$E$23:$E1544,"T") -> 0 | R51: =Q51/$H51 -> 0 | S51: =COUNTIF('End submission'!$E$23:$E1544,"R") -> 0 | T51: =S51/$H51 -> 0 | U51: =K51+M51+O51+S51 -> 0 | V51: =U51/$H51 -> 0 | W51: Medium | X51: N | Y51: N
A52: Functional | B52: 36 | C52: Round Robbin | E52: Underwriting | F52: ALL | H52: 18 | I52: 4 | J52: ALL | K52: =COUNTIF('Round Robin'!$E$23:$E1548,"P") -> 0 | L52: =K52/$H52 -> 0 | M52: =COUNTIF('Round Robin'!$E$23:$E1548,"F") -> 0 | N52: =M52/$H52 -> 0 | O52: =COUNTIF('Round Robin'!$E$23:$E1548,"B") -> 0 | P52: =O52/H52 -> 0 | Q52: =COUNTIF('Round Robin'!$E$23:$E1548,"T") -> 0 | R52: =Q52/$H52 -> 0 | S52: =COUNTIF('Round Robin'!$E$23:$E1548,"R") -> 0 | T52: =S52/$H52 -> 0 | U52: =K52+M52+O52+S52 -> 0 | V52: =U52/$H52 -> 0 | W52: Medium | X52: N | Y52: N
A53: Integration | B53: 37 | C53: Insurance score | E53: Integration | F53: ALL | G53: ALL | H53: 25 | I53: 25 | J53: ALL | K53: =COUNTIF('Insurance score'!$E$23:$E1505,"P") -> 0 | L53: =K53/$H53 -> 0 | M53: =COUNTIF('Insurance score'!$E$23:$E1505,"F") -> 0 | N53: =M53/$H53 -> 0 | O53: =COUNTIF('Insurance score'!$E$23:$E1505,"B") -> 0 | P53: =O53/H53 -> 0 | Q53: =COUNTIF('Insurance score'!$E$23:$E1505,"T") -> 0 | R53: =Q53/$H53 -> 0 | S53: =COUNTIF('Insurance score'!$E$23:$E1505,"R") -> 0 | T53: =S53/$H53 -> 0 | U53: =K53+M53+O53+S53 -> 0 | V53: =U53/$H53 -> 0 | W53: Critical | X53: N | Y53: N
A54: Integration | B54: 38 | C54: ISO, PPC & BCEG | E54: Integration | F54: HO | H54: 5 | I54: 3 | J54: ALL | K54: =COUNTIF('ISO, PPC & BCEG'!$E$23:$E1547,"P") -> 0 | L54: =K54/$H54 -> 0 | M54: =COUNTIF('ISO, PPC & BCEG'!$E$23:$E1547,"F") -> 0 | N54: =M54/$H54 -> 0 | O54: =COUNTIF('ISO, PPC & BCEG'!$E$23:$E1547,"B") -> 0 | P54: =O54/H54 -> 0 | Q54: =COUNTIF('ISO, PPC & BCEG'!$E$23:$E1547,"T") -> 0 | R54: =Q54/$H54 -> 0 | S54: =COUNTIF('ISO, PPC & BCEG'!$E$23:$E1547,"R") -> 0 | T54: =S54/$H54 -> 0 | U54: =K54+M54+O54+S54 -> 0 | V54: =U54/$H54 -> 0 | W54: High | X54: N | Y54: N
A55: Integration | B55: 39 | C55: Weather analytics | D55: Done | E55: Integration | F55: HO | H55: 2 | I55: 0.5 | J55: ALL | K55: =COUNTIF('Weather analytics'!$E$23:$E1629,"P") -> 0 | L55: =K55/$H55 -> 0 | M55: =COUNTIF('Weather analytics'!$E$23:$E1629,"F") -> 0 | N55: =M55/$H55 -> 0 | O55: =COUNTIF('Weather analytics'!$E$23:$E1629,"B") -> 0 | P55: =O55/H55 -> 0 | Q55: =COUNTIF('Weather analytics'!$E$23:$E1629,"T") -> 0 | R55: =Q55/$H55 -> 0 | S55: =COUNTIF('Weather analytics'!$E$23:$E1629,"R") -> 0 | T55: =S55/$H55 -> 0 | U55: =K55+M55+O55+S55 -> 0 | V55: =U55/$H55 -> 0 | W55: High | X55: N | Y55: N
A56: Integration | B56: 40 | C56: Verisk | D56: Done | E56: Integration | F56: HO | G56: Not State Specific | H56: 3 | I56: 7 | J56: ALL | K56: =COUNTIF(Verisk!$E$23:$E1549,"P") -> 0 | L56: =K56/$H56 -> 0 | M56: =COUNTIF(Verisk!$E$23:$E1549,"F") -> 0 | N56: =M56/$H56 -> 0 | O56: =COUNTIF(Verisk!$E$23:$E1549,"B") -> 0 | P56: =O56/H56 -> 0 | Q56: =COUNTIF(Verisk!$E$23:$E1549,"T") -> 0 | R56: =Q56/$H56 -> 0 | S56: =COUNTIF(Verisk!$E$23:$E1549,"R") -> 0 | T56: =S56/$H56 -> 0 | U56: =K56+M56+O56+S56 -> 0 | V56: =U56/$H56 -> 0 | W56: High | X56: N | Y56: N
A57: Functional | B57: 42 | C57: Quote Not Taken up | E57: Underwriting | F57: ALL | G57: FL | H57: 8 | I57: 1 | J57: ALL | K57: =COUNTIF('Quote Not Taken up'!$E$23:$E1553,"P") -> 0 | L57: =K57/$H57 -> 0 | M57: =COUNTIF('Quote Not Taken up'!$E$23:$E1553,"F") -> 0 | N57: =M57/$H57 -> 0 | O57: =COUNTIF('Quote Not Taken up'!$E$23:$E1553,"B") -> 0 | P57: =O57/H57 -> 0 | Q57: =COUNTIF('Quote Not Taken up'!$E$23:$E1553,"T") -> 0 | R57: =Q57/$H57 -> 0 | S57: =COUNTIF('Quote Not Taken up'!$E$23:$E1553,"R") -> 0 | T57: =S57/$H57 -> 0 | U57: =K57+M57+O57+S57 -> 0 | V57: =U57/$H57 -> 0 | W57: Medium | X57: N | Y57: N
A58: Functional | B58: 43 | C58: Forms | E58: Forms | F58: ALL | G58: ALL | H58: 15 | I58: 8 | J58: ALL | K58: =COUNTIF(Forms!$E$23:$E1528,"P") -> 0 | L58: =K58/$H58 -> 0 | M58: =COUNTIF(Forms!$E$23:$E1528,"F") -> 0 | N58: =M58/$H58 -> 0 | O58: =COUNTIF(Forms!$E$23:$E1528,"B") -> 0 | P58: =O58/H58 -> 0 | Q58: =COUNTIF(Forms!$E$23:$E1528,"T") -> 0 | R58: =Q58/$H58 -> 0 | S58: =COUNTIF(Forms!$E$23:$E1528,"R") -> 0 | T58: =S58/$H58 -> 0 | U58: =K58+M58+O58+S58 -> 0 | V58: =U58/$H58 -> 0 | W58: Medium | X58: P | Y58: N
A59: Functional | B59: 44 | C59: Quote Proposals | E59: Forms | F59: ALL | H59: 6 | I59: 1 | J59: ALL | K59: =COUNTIF('Quote Proposals'!$E$23:$E1574,"P") -> 0 | L59: =K59/$H59 -> 0 | M59: =COUNTIF('Quote Proposals'!$E$23:$E1574,"F") -> 0 | N59: =M59/$H59 -> 0 | O59: =COUNTIF('Quote Proposals'!$E$23:$E1574,"B") -> 0 | P59: =O59/H59 -> 0 | Q59: =COUNTIF('Quote Proposals'!$E$23:$E1574,"T") -> 0 | R59: =Q59/$H59 -> 0 | S59: =COUNTIF('Quote Proposals'!$E$23:$E1574,"R") -> 0 | T59: =S59/$H59 -> 0 | U59: =K59+M59+O59+S59 -> 0 | V59: =U59/$H59 -> 0 | W59: High | X59: N | Y59: N
A60: Functional | B60: 45 | C60: Pre Bind Forms | E60: Forms | F60: ALL | H60: 74 | I60: 25 | J60: ALL | K60: =COUNTIF('Pre Bind Forms'!$E$23:$E1549,"P") -> 0 | L60: =K60/$H60 -> 0 | M60: =COUNTIF('Pre Bind Forms'!$E$23:$E1549,"F") -> 0 | N60: =M60/$H60 -> 0 | O60: =COUNTIF('Pre Bind Forms'!$E$23:$E1549,"B") -> 0 | P60: =O60/H60 -> 0 | Q60: =COUNTIF('Pre Bind Forms'!$E$23:$E1549,"T") -> 0 | R60: =Q60/$H60 -> 0 | S60: =COUNTIF('Pre Bind Forms'!$E$23:$E1549,"R") -> 0 | T60: =S60/$H60 -> 0 | U60: =K60+M60+O60+S60 -> 0 | V60: =U60/$H60 -> 0 | W60: Medium | X60: N | Y60: N
A61: Functional | B61: 46 | C61: Forms - Additional Packages | E61: Forms | F61: ALL | G61: ALL | H61: 48 | I61: 5 | J61: ALL | K61: =COUNTIF('Forms - Additional Packages'!$E$23:$E1482,"P") -> 0 | L61: =K61/$H61 -> 0 | M61: =COUNTIF('Forms - Additional Packages'!$E$23:$E1482,"F") -> 0 | N61: =M61/$H61 -> 0 | O61: =COUNTIF('Forms - Additional Packages'!$E$23:$E1482,"B") -> 0 | P61: =O61/H61 -> 0 | Q61: =COUNTIF('Forms - Additional Packages'!$E$23:$E1482,"T") -> 0 | R61: =Q61/$H61 -> 0 | S61: =COUNTIF('Forms - Additional Packages'!$E$23:$E1482,"R") -> 0 | T61: =S61/$H61 -> 0 | U61: =K61+M61+O61+S61 -> 0 | V61: =U61/$H61 -> 0 | W61: Medium | X61: N | Y61: N
A62: Integration | B62: 47 | C62: KY Municipality Taxes | E62: Integration | F62: ALL | H62: 6 | I62: 3 | J62: ALL | K62: =COUNTIF('KY Municipality Taxes'!$E$23:$E1520,"P") -> 0 | L62: =K62/$H62 -> 0 | M62: =COUNTIF('KY Municipality Taxes'!$E$23:$E1520,"F") -> 0 | N62: =M62/$H62 -> 0 | O62: =COUNTIF('KY Municipality Taxes'!$E$23:$E1520,"B") -> 0 | P62: =O62/H62 -> 0 | Q62: =COUNTIF('KY Municipality Taxes'!$E$23:$E1520,"T") -> 0 | R62: =Q62/$H62 -> 0 | S62: =COUNTIF('KY Municipality Taxes'!$E$23:$E1520,"R") -> 0 | T62: =S62/$H62 -> 0 | U62: =K62+M62+O62+S62 -> 0 | V62: =U62/$H62 -> 0 | W62: High | Y62: N
A63: Integration | B63: 48 | C63: Census Tract | E63: Integration | F63: PA | H63: 6 | I63: 2 | J63: ALL | K63: =COUNTIF('Census Tract'!$E$23:$E1569,"P") -> 0 | L63: =K63/$H63 -> 0 | M63: =COUNTIF('Census Tract'!$E$23:$E1569,"F") -> 0 | N63: =M63/$H63 -> 0 | O63: =COUNTIF('Census Tract'!$E$23:$E1569,"B") -> 0 | P63: =O63/H63 -> 0 | Q63: =COUNTIF('Census Tract'!$E$23:$E1569,"T") -> 0 | R63: =Q63/$H63 -> 0 | S63: =COUNTIF('Census Tract'!$E$23:$E1569,"R") -> 0 | T63: =S63/$H63 -> 0 | U63: =K63+M63+O63+S63 -> 0 | V63: =U63/$H63 -> 0 | W63: High | X63: N | Y63: N
A64: Integration | B64: 41 | C64: Billing | E64: Integration | F64: ALL | H64: 8 | I64: 10 | J64: ALL | K64: =COUNTIF(Billing!$E$23:$E1551,"P") -> 0 | L64: =K64/$H64 -> 0 | M64: =COUNTIF(Billing!$E$23:$E1551,"F") -> 0 | N64: =M64/$H64 -> 0 | O64: =COUNTIF(Billing!$E$23:$E1551,"B") -> 0 | P64: =O64/H64 -> 0 | Q64: =COUNTIF(Billing!$E$23:$E1551,"T") -> 0 | R64: =Q64/$H64 -> 0 | S64: =COUNTIF(Billing!$E$23:$E1551,"R") -> 0 | T64: =S64/$H64 -> 0 | U64: =K64+M64+O64+S64 -> 0 | V64: =U64/$H64 -> 0 | W64: Medium | X64: N | Y64: N
A65: Functional | B65: 49 | C65: LA and UHNW indicators | E65: Underwriting | F65: Admitted | G65: Not State Specific | H65: 7 | I65: 2 | J65: ALL | K65: =COUNTIF('LA and UHNW indicators'!$E$23:$E1560,"P") -> 0 | L65: =K65/$H65 -> 0 | M65: =COUNTIF('LA and UHNW indicators'!$E$23:$E1560,"F") -> 0 | N65: =M65/$H65 -> 0 | O65: =COUNTIF('LA and UHNW indicators'!$E$23:$E1560,"B") -> 0 | P65: =O65/H65 -> 0 | Q65: =COUNTIF('LA and UHNW indicators'!$E$23:$E1560,"T") -> 0 | R65: =Q65/$H65 -> 0 | S65: =COUNTIF('LA and UHNW indicators'!$E$23:$E1560,"R") -> 0 | T65: =S65/$H65 -> 0 | U65: =K65+M65+O65+S65 -> 0 | V65: =U65/$H65 -> 0 | W65: High | X65: N | Y65: N
A66: Functional | B66: 50 | C66: Mortgagee | E66: Underwriting | F66: HO | G66: ALL | H66: 3 | I66: 2 | J66: ALL | K66: =COUNTIF(Mortgagee!$E$23:$E1561,"P") -> 0 | L66: =K66/$H66 -> 0 | M66: =COUNTIF(Mortgagee!$E$23:$E1561,"F") -> 0 | N66: =M66/$H66 -> 0 | O66: =COUNTIF(Mortgagee!$E$23:$E1561,"B") -> 0 | P66: =O66/H66 -> 0 | Q66: =COUNTIF(Mortgagee!$E$23:$E1561,"T") -> 0 | R66: =Q66/$H66 -> 0 | S66: =COUNTIF(Mortgagee!$E$23:$E1561,"R") -> 0 | T66: =S66/$H66 -> 0 | U66: =K66+M66+O66+S66 -> 0 | V66: =U66/$H66 -> 0 | W66: High | X66: N | Y66: N
A67: Functional | B67: 51 | C67: Cancellation Types | E67: Underwriting | F67: ALL | H67: 20 | I67: 5 | J67: ALL | K67: =COUNTIF('Cancellation Types'!$E$23:$E1701,"P") -> 0 | L67: =K67/$H67 -> 0 | M67: =COUNTIF('Cancellation Types'!$E$23:$E1697,"F") -> 0 | N67: =M67/$H67 -> 0 | O67: =COUNTIF('Cancellation Types'!$E$23:$E1697,"B") -> 0 | P67: =O67/H67 -> 0 | Q67: =COUNTIF('Cancellation Types'!$E$23:$E1697,"T") -> 0 | R67: =Q67/$H67 -> 0 | S67: =COUNTIF('Cancellation Types'!$E$23:$E1697,"R") -> 0 | T67: =S67/$H67 -> 0 | U67: =K67+M67+O67+S67 -> 0 | V67: =U67/$H67 -> 0 | W67: High | X67: N | Y67: N
A68: Integration | B68: 52 | C68: Sinkhole | E68: Integration | F68: HO | G68: FL | H68: 3 | I68: 1.5 | J68: ALL | K68: =COUNTIF(Sinkhole!$E$23:$E1549,"P") -> 0 | L68: =K68/$H68 -> 0 | M68: =COUNTIF(Sinkhole!$E$23:$E1549,"F") -> 0 | N68: =M68/$H68 -> 0 | O68: =COUNTIF(Sinkhole!$E$23:$E1549,"B") -> 0 | P68: =O68/H68 -> 0 | Q68: =COUNTIF(Sinkhole!$E$23:$E1549,"T") -> 0 | R68: =Q68/$H68 -> 0 | S68: =COUNTIF(Sinkhole!$E$23:$E1549,"R") -> 0 | T68: =S68/$H68 -> 0 | U68: =K68+M68+O68+S68 -> 0 | V68: =U68/$H68 -> 0 | W68: High | X68: N | Y68: N
A69: Integration | B69: 53 | C69: Storm Surge | E69: Integration | F69: HO | G69: FL | H69: 3 | I69: 1.5 | J69: ALL | K69: =COUNTIF('Storm Surge'!$E$23:$E1550,"P") -> 0 | L69: =K69/$H69 -> 0 | M69: =COUNTIF('Storm Surge'!$E$23:$E1550,"F") -> 0 | N69: =M69/$H69 -> 0 | O69: =COUNTIF('Storm Surge'!$E$23:$E1550,"B") -> 0 | P69: =O69/H69 -> 0 | Q69: =COUNTIF('Storm Surge'!$E$23:$E1550,"T") -> 0 | R69: =Q69/$H69 -> 0 | S69: =COUNTIF('Storm Surge'!$E$23:$E1550,"R") -> 0 | T69: =S69/$H69 -> 0 | U69: =K69+M69+O69+S69 -> 0 | V69: =U69/$H69 -> 0 | W69: High | X69: N | Y69: N
A70: Integration | B70: 54 | C70: Wind pool | E70: Integration | F70: HO | G70: FL, TX | H70: 2 | I70: 1.5 | J70: ALL | K70: =COUNTIF('Wind pool'!$E$23:$E1602,"P") -> 0 | L70: =K70/$H70 -> 0 | M70: =COUNTIF('Wind pool'!$E$23:$E1602,"F") -> 0 | N70: =M70/$H70 -> 0 | O70: =COUNTIF('Wind pool'!$E$23:$E1602,"B") -> 0 | P70: =O70/H70 -> 0 | Q70: =COUNTIF('Wind pool'!$E$23:$E1602,"T") -> 0 | R70: =Q70/$H70 -> 0 | S70: =COUNTIF('Wind pool'!$E$23:$E1602,"R") -> 0 | T70: =S70/$H70 -> 0 | U70: =K70+M70+O70+S70 -> 0 | V70: =U70/$H70 -> 0 | W70: High | X70: N | Y70: N
A71: Integration | B71: 55 | C71: Locations | E71: Integration | F71: ALL | H71: 2 | I71: 0.5 | J71: ALL | K71: =COUNTIF(Locations!$E$23:$E1567,"P") -> 0 | L71: =K71/$H71 -> 0 | M71: =COUNTIF(Locations!$E$23:$E1567,"F") -> 0 | N71: =M71/$H71 -> 0 | O71: =COUNTIF(Locations!$E$23:$E1567,"B") -> 0 | P71: =O71/H71 -> 0 | Q71: =COUNTIF(Locations!$E$23:$E1567,"T") -> 0 | R71: =Q71/$H71 -> 0 | S71: =COUNTIF(Locations!$E$23:$E1567,"R") -> 0 | T71: =S71/$H71 -> 0 | U71: =K71+M71+O71+S71 -> 0 | V71: =U71/$H71 -> 0 | W71: Medium | X71: N | Y71: N
A72: Functional | B72: 56 | C72: Underwriter Reassignement | E72: Underwriting | F72: ALL | H72: 18 | I72: 6 | J72: ALL | K72: =COUNTIF('Underwriter Reassignement'!$E$23:$E1558,"P") -> 0 | L72: =K72/$H72 -> 0 | M72: =COUNTIF('Underwriter Reassignement'!$E$23:$E1558,"F") -> 0 | N72: =M72/$H72 -> 0 | O72: =COUNTIF('Underwriter Reassignement'!$E$23:$E1558,"B") -> 0 | P72: =O72/H72 -> 0 | Q72: =COUNTIF('Underwriter Reassignement'!$E$23:$E1558,"T") -> 0 | R72: =Q72/$H72 -> 0 | S72: =COUNTIF('Underwriter Reassignement'!$E$23:$E1558,"R") -> 0 | T72: =S72/$H72 -> 0 | U72: =K72+M72+O72+S72 -> 0 | V72: =U72/$H72 -> 0 | W72: Medium | X72: N | Y72: N
A73: Functional | B73: 57 | C73: Manuscript endorsement | E73: Underwriting | F73: ALL | H73: 15 | I73: 8 | J73: ALL | K73: =COUNTIF('Manuscript endorsement'!$E$23:$E1313,"P") -> 0 | L73: =K73/$H73 -> 0 | M73: =COUNTIF('Manuscript endorsement'!$E$23:$E1313,"F") -> 0 | N73: =M73/$H73 -> 0 | O73: =COUNTIF('Manuscript endorsement'!$E$23:$E1313,"B") -> 0 | P73: =O73/H73 -> 0 | Q73: =COUNTIF('Manuscript endorsement'!$E$23:$E1313,"T") -> 0 | R73: =Q73/$H73 -> 0 | S73: =COUNTIF('Manuscript endorsement'!$E$23:$E1313,"R") -> 0 | T73: =S73/$H73 -> 0 | U73: =K73+M73+O73+S73 -> 0 | V73: =U73/$H73 -> 0 | W73: High | X73: N | Y73: N
A74: Integration | B74: 59 | C74: Flood | E74: Integration | F74: HS | G74: ALL | H74: 1 | I74: 0.5 | J74: ALL | K74: =COUNTIF(Flood!$E$23:$E1859,"P") -> 0 | L74: =K74/$H74 -> 0 | M74: =COUNTIF(Flood!$E$23:$E1859,"F") -> 0 | N74: =M74/$H74 -> 0 | O74: =COUNTIF(Flood!$E$23:$E1859,"B") -> 0 | P74: =O74/H74 -> 0 | Q74: =COUNTIF(Flood!$E$23:$E1859,"T") -> 0 | R74: =Q74/$H74 -> 0 | S74: =COUNTIF(Flood!$E$23:$E1859,"R") -> 0 | T74: =S74/$H74 -> 0 | U74: =K74+M74+O74+S74 -> 0 | V74: =U74/$H74 -> 0 | W74: High | X74: N | Y74: N
A75: Functional | B75: 58 | C75: Account referral | E75: Underwriting | F75: ALL | H75: 4 | I75: 2 | J75: ALL | K75: =COUNTIF('Account referral'!$E$23:$E1570,"P") -> 0 | L75: =K75/$H75 -> 0 | M75: =COUNTIF('Account referral'!$E$23:$E1570,"F") -> 0 | N75: =M75/$H75 -> 0 | O75: =COUNTIF('Account referral'!$E$23:$E1570,"B") -> 0 | P75: =O75/H75 -> 0 | Q75: =COUNTIF('Account referral'!$E$23:$E1570,"T") -> 0 | R75: =Q75/$H75 -> 0 | S75: =COUNTIF('Account referral'!$E$23:$E1570,"R") -> 0 | T75: =S75/$H75 -> 0 | U75: =K75+M75+O75+S75 -> 0 | V75: =U75/$H75 -> 0 | W75: High | X75: N | Y75: N
A76: Functional | B76: 60 | C76: Manually created tasks | E76: Underwriting | F76: ALL | G76: Not State Specific | H76: 21 | I76: 8 | J76: ALL | K76: =COUNTIF('Manually created tasks'!$E$23:$E1571,"P") -> 0 | L76: =K76/$H76 -> 0 | M76: =COUNTIF('Manually created tasks'!$E$23:$E1571,"F") -> 0 | N76: =M76/$H76 -> 0 | O76: =COUNTIF('Manually created tasks'!$E$23:$E1571,"B") -> 0 | P76: =O76/H76 -> 0 | Q76: =COUNTIF('Manually created tasks'!$E$23:$E1571,"T") -> 0 | R76: =Q76/$H76 -> 0 | S76: =COUNTIF('Manually created tasks'!$E$23:$E1571,"R") -> 0 | T76: =S76/$H76 -> 0 | U76: =K76+M76+O76+S76 -> 0 | V76: =U76/$H76 -> 0 | W76: High | X76: N | Y76: N
A77: Functional | B77: 61 | C77: Collections Large Schedule | E77: Underwriting | F77: CO | H77: 27 | I77: 8 | J77: ALL | K77: =COUNTIF('Collections Large Schedule'!$E$23:$E1554,"P") -> 0 | L77: =K77/$H77 -> 0 | M77: =COUNTIF('Collections Large Schedule'!$E$23:$E1554,"F") -> 0 | N77: =M77/$H77 -> 0 | O77: =COUNTIF('Collections Large Schedule'!$E$23:$E1554,"B") -> 0 | P77: =O77/H77 -> 0 | Q77: =COUNTIF('Collections Large Schedule'!$E$23:$E1554,"T") -> 0 | R77: =Q77/$H77 -> 0 | S77: =COUNTIF('Collections Large Schedule'!$E$23:$E1554,"R") -> 0 | T77: =S77/$H77 -> 0 | U77: =K77+M77+O77+S77 -> 0 | V77: =U77/$H77 -> 0 | W77: High | X77: N | Y77: N
A78: Functional | B78: 62 | C78: New User Creation | E78: Underwriting | F78: ALL | H78: 10 | I78: 1 | J78: ALL | K78: =COUNTIF('New User Creation'!$E$23:$E1573,"P") -> 0 | L78: =K78/$H78 -> 0 | M78: =COUNTIF('New User Creation'!$E$23:$E1573,"F") -> 0 | N78: =M78/$H78 -> 0 | O78: =COUNTIF('New User Creation'!$E$23:$E1573,"B") -> 0 | P78: =O78/H78 -> 0 | Q78: =COUNTIF('New User Creation'!$E$23:$E1573,"T") -> 0 | R78: =Q78/$H78 -> 0 | S78: =COUNTIF('New User Creation'!$E$23:$E1573,"R") -> 0 | T78: =S78/$H78 -> 0 | U78: =K78+M78+O78+S78 -> 0 | V78: =U78/$H78 -> 0 | W78: High | X78: N | Y78: N
A79: Functional | B79: 63 | C79: New Agency Creation | E79: Underwriting | F79: ALL | G79: ALL | H79: 20 | I79: 3 | J79: ALL | K79: =COUNTIF('New Agency Creation'!$E$23:$E1575,"P") -> 0 | L79: =K79/$H79 -> 0 | M79: =COUNTIF('New Agency Creation'!$E$23:$E1575,"F") -> 0 | N79: =M79/$H79 -> 0 | O79: =COUNTIF('New Agency Creation'!$E$23:$E1575,"B") -> 0 | P79: =O79/H79 -> 0 | Q79: =COUNTIF('New Agency Creation'!$E$23:$E1575,"T") -> 0 | R79: =Q79/$H79 -> 0 | S79: =COUNTIF('New Agency Creation'!$E$23:$E1575,"R") -> 0 | T79: =S79/$H79 -> 0 | U79: =K79+M79+O79+S79 -> 0 | V79: =U79/$H79 -> 0 | W79: High | X79: N | Y79: N
A80: Integration | B80: 64 | C80: Okta | E80: Integration | F80: ALL | G80: Not State Specific | H80: 4 | I80: 1 | J80: ALL | K80: =COUNTIF(OKTA!$E$23:$E1541,"P") -> 0 | L80: =K80/$H80 -> 0 | M80: =COUNTIF(OKTA!$E$23:$E1541,"F") -> 0 | N80: =M80/$H80 -> 0 | O80: =COUNTIF(OKTA!$E$23:$E1541,"B") -> 0 | P80: =O80/H80 -> 0 | Q80: =COUNTIF(OKTA!$E$23:$E1541,"T") -> 0 | R80: =Q80/$H80 -> 0 | S80: =COUNTIF(OKTA!$E$23:$E1541,"R") -> 0 | T80: =S80/$H80 -> 0 | U80: =K80+M80+O80+S80 -> 0 | V80: =U80/$H80 -> 0 | W80: High | X80: N | Y80: N
A81: Functional | B81: 65 | C81: Policy Navigation | E81: Underwriting | F81: ALL | H81: 6 | I81: 3 | J81: ALL | K81: =COUNTIF(PoliciesMainFlow!$E$23:$E1579,"P") -> 0 | L81: =K81/$H81 -> 0 | M81: =COUNTIF(PoliciesMainFlow!$E$23:$E1579,"F") -> 0 | N81: =M81/$H81 -> 0 | O81: =COUNTIF(PoliciesMainFlow!$E$23:$E1579,"B") -> 0 | P81: =O81/H81 -> 0 | Q81: =COUNTIF(PoliciesMainFlow!$E$23:$E1579,"T") -> 0 | R81: =Q81/$H81 -> 0 | S81: =COUNTIF(PoliciesMainFlow!$E$23:$E1579,"R") -> 0 | T81: =S81/$H81 -> 0 | U81: =K81+M81+O81+S81 -> 0 | V81: =U81/$H81 -> 0 | W81: High | Y81: N
A82: Functional | B82: 66 | C82: Customer Navigation | E82: Underwriting | F82: ALL | G82: Not State Specific | H82: 11 | I82: 2 | J82: ALL | K82: =COUNTIF(CustomersMainFlow!$E$23:$E1580,"P") -> 0 | L82: =K82/$H82 -> 0 | M82: =COUNTIF(CustomersMainFlow!$E$23:$E1580,"F") -> 0 | N82: =M82/$H82 -> 0 | O82: =COUNTIF(CustomersMainFlow!$E$23:$E1580,"B") -> 0 | P82: =O82/H82 -> 0 | Q82: =COUNTIF(CustomersMainFlow!$E$23:$E1580,"T") -> 0 | R82: =Q82/$H82 -> 0 | S82: =COUNTIF(CustomersMainFlow!$E$23:$E1580,"R") -> 0 | T82: =S82/$H82 -> 0 | U82: =K82+M82+O82+S82 -> 0 | V82: =U82/$H82 -> 0 | W82: High | X82: N | Y82: N
A83: Functional | B83: 67 | C83: Partner Navigation | E83: Underwriting | F83: ALL | H83: 8 | I83: 1 | J83: ALL | K83: =COUNTIF('Partner Navigation'!$E$23:$E1581,"P") -> 0 | L83: =K83/$H83 -> 0 | M83: =COUNTIF('Partner Navigation'!$E$23:$E1581,"F") -> 0 | N83: =M83/$H83 -> 0 | O83: =COUNTIF('Partner Navigation'!$E$23:$E1581,"B") -> 0 | P83: =O83/H83 -> 0 | Q83: =COUNTIF('Partner Navigation'!$E$23:$E1581,"T") -> 0 | R83: =Q83/$H83 -> 0 | S83: =COUNTIF('Partner Navigation'!$E$23:$E1581,"R") -> 0 | T83: =S83/$H83 -> 0 | U83: =K83+M83+O83+S83 -> 0 | V83: =U83/$H83 -> 0 | W83: High | X83: N | Y83: N
A84: Functional | B84: 68 | C84: Large HH | E84: Performance | F84: ALL | H84: 10 | I84: 5 | J84: ALL | K84: =COUNTIF('Large HH'!$E$23:$E1583,"P") -> 0 | L84: =K84/$H84 -> 0 | M84: =COUNTIF('Large HH'!$E$23:$E1583,"F") -> 0 | N84: =M84/$H84 -> 0 | O84: =COUNTIF('Large HH'!$E$23:$E1583,"B") -> 0 | P84: =O84/H84 -> 0 | Q84: =COUNTIF('Large HH'!$E$23:$E1583,"T") -> 0 | R84: =Q84/$H84 -> 0 | S84: =COUNTIF('Large HH'!$E$23:$E1583,"R") -> 0 | T84: =S84/$H84 -> 0 | U84: =K84+M84+O84+S84 -> 0 | V84: =U84/$H84 -> 0 | X84: N | Y84: N
A85: Functional | B85: 69 | C85: HH Documents Upload | E85: Underwriting | F85: ALL | G85: Not State Specific | H85: 14 | I85: 1 | J85: ALL | K85: =COUNTIF('HH Documents Upload'!$E$23:$E1584,"P") -> 0 | L85: =K85/$H85 -> 0 | M85: =COUNTIF('HH Documents Upload'!$E$23:$E1584,"F") -> 0 | N85: =M85/$H85 -> 0 | O85: =COUNTIF('HH Documents Upload'!$E$23:$E1584,"B") -> 0 | P85: =O85/H85 -> 0 | Q85: =COUNTIF('HH Documents Upload'!$E$23:$E1584,"T") -> 0 | R85: =Q85/$H85 -> 0 | S85: =COUNTIF('HH Documents Upload'!$E$23:$E1584,"R") -> 0 | T85: =S85/$H85 -> 0 | U85: =K85+M85+O85+S85 -> 0 | V85: =U85/$H85 -> 0 | W85: High | X85: N | Y85: N
A86: Functional | B86: 70 | C86: Transactions | E86: Underwriting | F86: ALL | H86: 6 | I86: 2 | J86: ALL | K86: =COUNTIF(TransactionTypes!$E$23:$E1581,"P") -> 0 | L86: =K86/$H86 -> 0 | M86: =COUNTIF(TransactionTypes!$E$23:$E1581,"F") -> 0 | N86: =M86/$H86 -> 0 | O86: =COUNTIF(TransactionTypes!$E$23:$E1581,"B") -> 0 | P86: =O86/H86 -> 0 | Q86: =COUNTIF(TransactionTypes!$E$23:$E1581,"T") -> 0 | R86: =Q86/$H86 -> 0 | S86: =COUNTIF(TransactionTypes!$E$23:$E1581,"R") -> 0 | T86: =S86/$H86 -> 0 | U86: =K86+M86+O86+S86 -> 0 | V86: =U86/$H86 -> 0 | W86: High | X86: N | Y86: N
A87: Functional | B87: 71 | C87: Renewals | E87: Underwriting | H87: 22 | I87: 10 | J87: ALL | K87: =COUNTIF(Renewals!$E$23:$E1587,"P") -> 0 | L87: =K87/$H87 -> 0 | M87: =COUNTIF(Renewals!$E$23:$E1587,"F") -> 0 | N87: =M87/$H87 -> 0 | O87: =COUNTIF(Renewals!$E$23:$E1587,"B") -> 0 | P87: =O87/H87 -> 0 | Q87: =COUNTIF(Renewals!$E$23:$E1587,"T") -> 0 | R87: =Q87/$H87 -> 0 | S87: =COUNTIF(Renewals!$E$23:$E1587,"R") -> 0 | T87: =S87/$H87 -> 0 | U87: =K87+M87+O87+S87 -> 0 | V87: =U87/$H87 -> 0 | W87: Critical | X87: N | Y87: N
A88: Functional | B88: 72 | C88: Links | E88: Underwriting | H88: 1 | I88: 2 | J88: ALL | K88: =COUNTIF(Links!$E$23:$E33,"P") -> 0 | L88: =K88/$H88 -> 0 | M88: =COUNTIF(Links!$E$23:$E33,"F") -> 0 | N88: =M88/$H88 -> 0 | O88: =COUNTIF(Links!$E$23:$E33,"B") -> 0 | P88: =O88/H88 -> 0 | Q88: =COUNTIF(Links!$E$23:$E33,"T") -> 0 | R88: =Q88/$H88 -> 0 | S88: =COUNTIF(Links!$E$23:$E33,"R") -> 0 | T88: =S88/$H88 -> 0 | U88: =K88+M88+O88+S88 -> 0 | V88: =U88/$H88 -> 0 | W88: Medium | X88: N | Y88: N
A89: Functional | B89: 73 | C89: Validation Messages | E89: Underwriting | F89: ALL | H89: 10 | I89: 2 | J89: ALL | K89: =COUNTIF('Validation messages'!$E$23:$E1592,"P") -> 0 | L89: =K89/$H89 -> 0 | M89: =COUNTIF('Validation messages'!$E$23:$E1592,"F") -> 0 | N89: =M89/$H89 -> 0 | O89: =COUNTIF('Validation messages'!$E$23:$E1592,"B") -> 0 | P89: =O89/H89 -> 0 | Q89: =COUNTIF('Validation messages'!$E$23:$E1592,"T") -> 0 | R89: =Q89/$H89 -> 0 | S89: =COUNTIF('Validation messages'!$E$23:$E1592,"R") -> 0 | T89: =S89/$H89 -> 0 | U89: =K89+M89+O89+S89 -> 0 | V89: =U89/$H89 -> 0 | W89: Medium | X89: N | Y89: N
A90: Functional | B90: 74 | C90: User Setup | E90: Underwriting | F90: ALL | H90: 17 | I90: 2 | J90: ALL | K90: =COUNTIF('User Setup'!$E$23:$E1593,"P") -> 0 | L90: =K90/$H90 -> 0 | M90: =COUNTIF('User Setup'!$E$23:$E1593,"F") -> 0 | N90: =M90/$H90 -> 0 | O90: =COUNTIF('User Setup'!$E$23:$E1593,"B") -> 0 | P90: =O90/H90 -> 0 | Q90: =COUNTIF('User Setup'!$E$23:$E1593,"T") -> 0 | R90: =Q90/$H90 -> 0 | S90: =COUNTIF('User Setup'!$E$23:$E1593,"R") -> 0 | T90: =S90/$H90 -> 0 | U90: =K90+M90+O90+S90 -> 0 | V90: =U90/$H90 -> 0 | W90: Medium | Y90: N
A91: Functional | B91: 75 | C91: LLC/Trust | E91: Underwriting | F91: ALL | H91: 16 | I91: 5 | J91: ALL | K91: =COUNTIF('LLC Trust'!$E$23:$E1431,"P") -> 0 | L91: =K91/$H91 -> 0 | M91: =COUNTIF('LLC Trust'!$E$23:$E1431,"F") -> 0 | N91: =M91/$H91 -> 0 | O91: =COUNTIF('LLC Trust'!$E$23:$E1431,"B") -> 0 | P91: =O91/H91 -> 0 | Q91: =COUNTIF('LLC Trust'!$E$23:$E1431,"T") -> 0 | R91: =Q91/$H91 -> 0 | S91: =COUNTIF('LLC Trust'!$E$23:$E1431,"R") -> 0 | T91: =S91/$H91 -> 0 | U91: =K91+M91+O91+S91 -> 0 | V91: =U91/$H91 -> 0 | W91: High | X91: N | Y91: N
A92: Functional | B92: 76 | C92: Existing Household navigation/updating | E92: Underwriting | G92: Not State Specific | H92: 7 | I92: 3 | J92: ALL | K92: =COUNTIF('Existing Household navigation'!$E$23:$E1596,"P") -> 0 | L92: =K92/$H92 -> 0 | M92: =COUNTIF('Existing Household navigation'!$E$23:$E1596,"F") -> 0 | N92: =M92/$H92 -> 0 | O92: =COUNTIF('Existing Household navigation'!$E$23:$E1596,"B") -> 0 | P92: =O92/H92 -> 0 | Q92: =COUNTIF('Existing Household navigation'!$E$23:$E1596,"T") -> 0 | R92: =Q92/$H92 -> 0 | S92: =COUNTIF('Existing Household navigation'!$E$23:$E1596,"R") -> 0 | T92: =S92/$H92 -> 0 | U92: =K92+M92+O92+S92 -> 0 | V92: =U92/$H92 -> 0 | W92: Critical | X92: N | Y92: N
A93: Functional | B93: 77 | C93: Transaction Behaviour - Adding/Deleting different number of objects (e.g.150 vehicles) | E93: Underwriting | F93: ALL | H93: 5 | I93: 14 | J93: ALL | K93: =COUNTIF('Transaction Behaviour'!$E$23:$E68,"P") -> 0 | L93: =K93/$H93 -> 0 | M93: =COUNTIF('Transaction Behaviour'!$E$23:$E68,"F") -> 0 | N93: =M93/$H93 -> 0 | O93: =COUNTIF('Transaction Behaviour'!$E$23:$E68,"B") -> 0 | P93: =O93/H93 -> 0 | Q93: =COUNTIF('Transaction Behaviour'!$E$23:$E68,"T") -> 0 | R93: =Q93/$H93 -> 0 | S93: =COUNTIF('Transaction Behaviour'!$E$23:$E68,"R") -> 0 | T93: =S93/$H93 -> 0 | U93: =K93+M93+O93+S93 -> 0 | V93: =U93/$H93 -> 0 | W93: High | X93: N | Y93: N
A94: Functional | B94: 78 | C94: Membership service | E94: Underwriting | F94: Admitted | G94: Not State Specific | H94: 10 | I94: 5 | J94: ALL | K94: =COUNTIF('Membership service'!$E$23:$E1605,"P") -> 0 | L94: =K94/$H94 -> 0 | M94: =COUNTIF('Membership service'!$E$23:$E1605,"F") -> 0 | N94: =M94/$H94 -> 0 | O94: =COUNTIF('Membership service'!$E$23:$E1605,"B") -> 0 | P94: =O94/H94 -> 0 | Q94: =COUNTIF('Membership service'!$E$23:$E1605,"T") -> 0 | R94: =Q94/$H94 -> 0 | S94: =COUNTIF('Membership service'!$E$23:$E1605,"R") -> 0 | T94: =S94/$H94 -> 0 | U94: =K94+M94+O94+S94 -> 0 | V94: =U94/$H94 -> 0 | W94: High | X94: N | Y94: N
A95: Functional | B95: 79 | C95: PSE Membership | E95: Underwriting | F95: Surplus | G95: Not State Specific | H95: 4 | I95: 2 | J95: ALL | K95: =COUNTIF('PSE Membership'!$E$23:$E1599,"P") -> 0 | L95: =K95/$H95 -> 0 | M95: =COUNTIF('PSE Membership'!$E$23:$E1599,"F") -> 0 | N95: =M95/$H95 -> 0 | O95: =COUNTIF('PSE Membership'!$E$23:$E1599,"B") -> 0 | P95: =O95/H95 -> 0 | Q95: =COUNTIF('PSE Membership'!$E$23:$E1599,"T") -> 0 | R95: =Q95/$H95 -> 0 | S95: =COUNTIF('PSE Membership'!$E$23:$E1599,"R") -> 0 | T95: =S95/$H95 -> 0 | U95: =K95+M95+O95+S95 -> 0 | V95: =U95/$H95 -> 0 | W95: Medium | X95: N | Y95: N
A96: Functional | B96: 80 | C96: Pop up window | E96: Underwriting | F96: ALL | G96: Not State Specific | H96: 4 | I96: 2 | J96: ALL | K96: =COUNTIF('Pop-up window'!$E$23:$E1600,"P") -> 0 | L96: =K96/$H96 -> 0 | M96: =COUNTIF('Pop-up window'!$E$23:$E1600,"F") -> 0 | N96: =M96/$H96 -> 0 | O96: =COUNTIF('Pop-up window'!$E$23:$E1600,"B") -> 0 | P96: =O96/H96 -> 0 | Q96: =COUNTIF('Pop-up window'!$E$23:$E1600,"T") -> 0 | R96: =Q96/$H96 -> 0 | S96: =COUNTIF('Pop-up window'!$E$23:$E1600,"R") -> 0 | T96: =S96/$H96 -> 0 | U96: =K96+M96+O96+S96 -> 0 | V96: =U96/$H96 -> 0 | W96: Medium | X96: N | Y96: N
A97: Functional | B97: 81 | C97: Additional Interests/Insured | E97: Underwriting | F97: ALL | H97: 45 | I97: 10 | J97: ALL | K97: =COUNTIF('Additional Interest-Insured'!$E$23:$E1599,"P") -> 0 | L97: =K97/$H97 -> 0 | M97: =COUNTIF('Additional Interest-Insured'!$E$33:$E1499,"F") -> 0 | N97: =M97/$H97 -> 0 | O97: =COUNTIF('Additional Interest-Insured'!$E$33:$E1499,"B") -> 0 | P97: =O97/H97 -> 0 | Q97: =COUNTIF('Additional Interest-Insured'!$E$33:$E1499,"T") -> 0 | R97: =Q97/$H97 -> 0 | S97: =COUNTIF('Additional Interest-Insured'!$E$33:$E1499,"R") -> 0 | T97: =S97/$H97 -> 0 | U97: =K97+M97+O97+S97 -> 0 | V97: =U97/$H97 -> 0 | W97: Medium | X97: N | Y97: N
A98: Functional | B98: 82 | C98: Incidents, mapping to other LOBs and YCD | E98: Product | H98: 8 | I98: 25 | J98: ALL | K98: =COUNTIF('Incidents, mapping to other LOB'!$E$23:$E1062,"P") -> 0 | L98: =K98/$H98 -> 0 | M98: =COUNTIF('Incidents, mapping to other LOB'!$E$23:$E1062,"F") -> 0 | N98: =M98/$H98 -> 0 | O98: =COUNTIF('Incidents, mapping to other LOB'!$E$23:$E1062,"B") -> 0 | P98: =O98/H98 -> 0 | Q98: =COUNTIF('Incidents, mapping to other LOB'!$E$23:$E1062,"T") -> 0 | R98: =Q98/$H98 -> 0 | S98: =COUNTIF('Incidents, mapping to other LOB'!$E$23:$E1062,"R") -> 0 | T98: =S98/$H98 -> 0 | U98: =K98+M98+O98+S98 -> 0 | V98: =U98/$H98 -> 0 | W98: Critical | X98: N | Y98: N
A99: Functional | B99: 83 | C99: Collections | E99: Product | H99: 17 | I99: 10 | J99: ALL | K99: =COUNTIF(Collections!$E$23:$E1551,"P") -> 0 | L99: =K99/$H99 -> 0 | M99: =COUNTIF(Collections!$E$23:$E1551,"F") -> 0 | N99: =M99/$H99 -> 0 | O99: =COUNTIF(Collections!$E$23:$E1551,"B") -> 0 | P99: =O99/H99 -> 0 | Q99: =COUNTIF(Collections!$E$23:$E1551,"T") -> 0 | R99: =Q99/$H99 -> 0 | S99: =COUNTIF(Collections!$E$23:$E1551,"R") -> 0 | T99: =S99/$H99 -> 0 | U99: =K99+M99+O99+S99 -> 0 | V99: =U99/$H99 -> 0 | W99: High | Y99: N
A100: Functional | B100: 84 | C100: Auto - (TCs: All Vehicle Types, All Operator Types) | E100: Product | F100: PA | H100: 8 | I100: 25 | J100: ALL | K100: =COUNTIF('Auto - TC with all inc and veh'!$E$23:$E119,"P") -> 0 | L100: =K100/$H100 -> 0 | M100: =COUNTIF('Auto - TC with all inc and veh'!$E$23:$E119,"F") -> 0 | N100: =M100/$H100 -> 0 | O100: =COUNTIF('Auto - TC with all inc and veh'!$E$23:$E119,"B") -> 0 | P100: =O100/H100 -> 0 | Q100: =COUNTIF('Auto - TC with all inc and veh'!$E$23:$E119,"T") -> 0 | R100: =Q100/$H100 -> 0 | S100: =COUNTIF('Auto - TC with all inc and veh'!$E$23:$E119,"R") -> 0 | T100: =S100/$H100 -> 0 | U100: =K100+M100+O100+S100 -> 0 | V100: =U100/$H100 -> 0 | W100: High | X100: N | Y100: N
A101: Functional | B101: 85 | C101: LOB Dependencies | E101: Product | H101: 13 | I101: 20 | J101: ALL | K101: =COUNTIF('LOB Dependencies'!$E$23:$E1526,"P") -> 0 | L101: =K101/$H101 -> 0 | M101: =COUNTIF('LOB Dependencies'!$E$23:$E1526,"F") -> 0 | N101: =M101/$H101 -> 0 | O101: =COUNTIF('LOB Dependencies'!$E$23:$E1526,"B") -> 0 | P101: =O101/H101 -> 0 | Q101: =COUNTIF('LOB Dependencies'!$E$23:$E1526,"T") -> 0 | R101: =Q101/$H101 -> 0 | S101: =COUNTIF('LOB Dependencies'!$E$23:$E1526,"R") -> 0 | T101: =S101/$H101 -> 0 | U101: =K101+M101+O101+S101 -> 0 | V101: =U101/$H101 -> 0 | W101: High | X101: N | Y101: N
A102: Functional | B102: 86 | C102: Out Of Sequence Transaction | E102: Product | F102: ALL | H102: 13 | I102: 10 | J102: ALL | K102: =COUNTIF('Out Of Sequence Transaction'!$E$23:$E1605,"P") -> 0 | L102: =K102/$H102 -> 0 | M102: =COUNTIF('Out Of Sequence Transaction'!$E$23:$E1605,"F") -> 0 | N102: =M102/$H102 -> 0 | O102: =COUNTIF('Out Of Sequence Transaction'!$E$23:$E1605,"B") -> 0 | P102: =O102/H102 -> 0 | Q102: =COUNTIF('Out Of Sequence Transaction'!$E$23:$E1605,"T") -> 0 | R102: =Q102/$H102 -> 0 | S102: =COUNTIF('Out Of Sequence Transaction'!$E$23:$E1605,"R") -> 0 | T102: =S102/$H102 -> 0 | U102: =K102+M102+O102+S102 -> 0 | V102: =U102/$H102 -> 0 | W102: Critical | X102: N | Y102: N
A103: Functional | B103: 87 | C103: Years Clean Discount | E103: Functional | F103: ALL | H103: 5 | I103: 10 | J103: ALL | K103: =COUNTIF('Years Clean Discount'!$E$23:$E1551,"P") -> 0 | L103: =K103/$H103 -> 0 | M103: =COUNTIF('Years Clean Discount'!$E$23:$E1551,"F") -> 0 | N103: =M103/$H103 -> 0 | O103: =COUNTIF('Years Clean Discount'!$E$23:$E1551,"B") -> 0 | P103: =O103/H103 -> 0 | Q103: =COUNTIF('Years Clean Discount'!$E$23:$E1551,"T") -> 0 | R103: =Q103/$H103 -> 0 | S103: =COUNTIF('Years Clean Discount'!$E$23:$E1551,"R") -> 0 | T103: =S103/$H103 -> 0 | U103: =K103+M103+O103+S103 -> 0 | V103: =U103/$H103 -> 0 | W103: High | X103: Y | Y103: N
...

Sheet Regression_ Test_Summary
A1: Regression Test Summary
A3: Objective: | B3: 1 | C3: Verify Policy workflow, Transactions creation and Integrations are working as expected on identified Scenarios
A4: Environment: STG1
A5: Data: | B5: 1 | C5: Date:
B6: 2 | C6: Environment URL
B7: 3 | C7: Login = Okta tile
A9: Status: | B9: N | C9: = Not executed by QA
B10: P | C10: = Passed by QA
B11: F | C11: = Failed by QA
B12: T | C12: = Testing in progress
B13: R | C13: = Rejected / Existing issue
B14: B | C14: = Blocked by QA
A16: Test | B16: SC# | C16: Regression Suites | D16: Automation Tags | E16: Area | F16: LOB | G16: Number of Test Cases (Per LOB) | H16: Number of LOBs impacted | I16: States Impacted | J16: Trx Impacted | K16: Aprox. Manual Execution Time (hrs) | L16: Environment | M16: N/A for Automation | N16: % N/A for Automation | O16: Automated | P16: % Automated | Q16: Partial Automated | R16: % Partial Automated | S16: Not Automated | T16: % Not Automated | U16: Scenario Priority | V16: Automated Y/P/N | W16: Status | X16: Comments
A17: Functional | B17: 1 | C17: Browser testing | E17: Underwriting | F17: ALL | G17: 15 | H17: 0 | I17: 0 | J17: N/A | K17: 5 | L17: ALL | M17: =COUNTIF('Browser testing'!$G23:$G1501,"N/A for Automation") -> 15 | N17: =M17/$G17 -> 1 | O17: =COUNTIF('Browser testing'!$G23:$G1501,"Automated") -> 0 | P17: =O17/$G17 -> 0 | Q17: =COUNTIF('Browser testing'!$G23:$G1501,"Partial Automated") -> 0 | R17: =Q17/G17 -> 0 | S17: =COUNTIF('Browser testing'!$G23:$G1501,"Not Automated") -> 0 | T17: =S17/$G17 -> 0 | U17: High | V17: N | W17: N
A18: Functional | B18: 2 | C18: BSE Broker Self Service Endorsement | D18: next/d | E18: Underwriting | F18: ALL | G18: 30 | K18: 15 | L18: ALL | M18: =COUNTIF(BSE!$G23:$G258,"N/A for Automation") -> 0 | N18: =M18/$G18 -> 0 | O18: =COUNTIF(BSE!$G23:$G258,"Automated") -> 1 | P18: =O18/$G18 -> 0.033333333 | Q18: =COUNTIF(BSE!$G23:$G258,"Partial Automated") -> 0 | R18: =Q18/G18 -> 0 | S18: =COUNTIF(BSE!$G23:$G258,"Not Automated") -> 29 | T18: =S18/$G18 -> 0.96666667 | U18: High | V18: P | W18: N | X18: Rally TC
A19: Functional | B19: 3 | C19: TASKS | E19: Underwriting | F19: ALL | G19: 6 | K19: 4 | L19: ALL | M19: =COUNTIF('Tasks & Emails'!$G23:$G1503,"N/A for Automation") -> 4 | N19: =M19/$G19 -> 0.66666667 | O19: =COUNTIF('Tasks & Emails'!$G23:$G1503,"Automated") -> 0 | P19: =O19/$G19 -> 0 | Q19: =COUNTIF('Tasks & Emails'!$G23:$G1503,"Partial Automated") -> 0 | R19: =Q19/G19 -> 0 | S19: =COUNTIF('Tasks & Emails'!$G23:$G1503,"Not Automated") -> 2 | T19: =S19/$G19 -> 0.33333333 | V19: P | W19: N
A20: Functional | B20: 4 | C20: BOR | E20: Underwriting | F20: ALL | G20: 13 | K20: 5 | L20: ALL | M20: =COUNTIF(BOR!$G$23:$G1478,"N/A for Automation") -> 13 | N20: =M20/$G20 -> 1 | O20: =COUNTIF(BOR!$G$23:$G1478,"Partial Automated") -> 0 | P20: =O20/$G20 -> 0 | Q20: =COUNTIF(BOR!$G$23:$G1478,"Partial Automated") -> 0 | R20: =Q20/G20 -> 0 | S20: =COUNTIF(BOR!$G$23:$G1478,"Not Automated") -> 0 | T20: =S20/$G20 -> 0 | U20: Critical | V20: N | W20: N
A21: Integration | B21: 5 | C21: OFAC | D21: - =@Integration, @OFAC, @CC, @HO, @PA, @EX, @ES, @PW, @HS, @CO, @NamedInsured, @LLC, @Trust @OtherEntity, @AdditionalInsured, @AdditionalInterests, @LossPayee | E21: Integration | F21: ALL | G21: 29 | H21: 8 | I21: 50 | J21: NB/END/RN | L21: ALL | M21: =COUNTIF(OFAC!$G$23:$G1664,"N/A for Automation") -> 0 | N21: =M21/$G21 -> 0 | O21: =COUNTIF(OFAC!$G$23:$G1664,"Automated") -> 29 | P21: =O21/$G21 -> 1 | Q21: =COUNTIF(OFAC!$G$23:$G1664,"Partial Automated") -> 0 | R21: =Q21/G21 -> 0 | S21: =COUNTIF(OFAC!$G$23:$G1664,"Not Automated") -> 0 | T21: =S21/$G21 -> 0 | U21: High | V21: Y | W21: N | X21: Rally TC
A22: Functional | B22: 6 | C22: Carrier Partners HS | D22: To check the scope of testing | E22: Underwriting | F22: HS, ES | G22: 22 | H22: 1 | K22: 3 | L22: ALL | M22: =COUNTIF('Carrier Partners HS'!$G$23:$G1458,"N/A for Automation") -> 0 | N22: =M22/$G22 -> 0 | O22: =COUNTIF('Carrier Partners HS'!$G$23:$G1458,"Automated") -> 2 | P22: =O22/$G22 -> 0.090909091 | Q22: =COUNTIF('Carrier Partners HS'!$G$23:$G1458,"Partial Automated") -> 0 | R22: =Q22/G22 -> 0 | S22: =COUNTIF('Carrier Partners HS'!$G$23:$G1458,"Not Automated") -> 20 | T22: =S22/$G22 -> 0.90909091 | U22: Medium | V22: P | W22: N
A23: Functional | B23: 7 | C23: Carrier Partners ES | D23: To check the scope of testing | E23: Underwriting | F23: ES | G23: 3 | H23: 1 | K23: 1 | L23: ALL | M23: =COUNTIF('Carrier Partners ES'!$G$23:$G1509,"N/A for Automation") -> 0 | N23: =M23/$G23 -> 0 | O23: =COUNTIF('Carrier Partners ES'!$G$23:$G1509,"Automated") -> 0 | P23: =O23/$G23 -> 0 | Q23: =COUNTIF('Carrier Partners ES'!$G$23:$G1509,"Partial Automated") -> 3 | R23: =Q23/G23 -> 1 | S23: =COUNTIF('Carrier Partners ES'!$G$23:$G1509,"Not Automated") -> 0 | T23: =S23/$G23 -> 0 | U23: Medium | V23: Y | W23: N
A24: Functional | B24: 8 | C24: Aggregation zone HS | E24: Underwriting | F24: HS | G24: 2 | K24: 1 | L24: ALL | M24: =COUNTIF('Aggregation zone HS'!$G$23:$G1510,"N/A for Automation") -> 2 | N24: =M24/$G24 -> 1 | O24: =COUNTIF('Aggregation zone HS'!$G$23:$G1510,"Automated") -> 0 | P24: =O24/$G24 -> 0 | Q24: =COUNTIF('Aggregation zone HS'!$G$23:$G1510,"Partial Automated") -> 0 | R24: =Q24/G24 -> 0 | S24: =COUNTIF('Aggregation zone HS'!$G$23:$G1510,"Not Automated") -> 0 | T24: =S24/$G24 -> 0 | U24: Medium | V24: N | W24: N
A25: Functional | B25: 9 | C25: TIV HS | E25: Underwriting | F25: HS | G25: 2 | K25: 1 | L25: ALL | M25: =COUNTIF('TIV HS'!$G$23:$G1511,"N/A for Automation") -> 0 | N25: =M25/$G25 -> 0 | O25: =COUNTIF('TIV HS'!$G$23:$G1511,"Automated") -> 0 | P25: =O25/$G25 -> 0 | Q25: =COUNTIF('TIV HS'!$G$23:$G1511,"Partial Automated") -> 0 | R25: =Q25/G25 -> 0 | S25: =COUNTIF('TIV HS'!$G$23:$G1511,"Not Automated") -> 2 | T25: =S25/$G25 -> 1 | U25: High | V25: Y | W25: N
A26: Integration | B26: 10 | C26: AIR HS FL | D26: - @Integration, @AIR, @HS, @HomeSurplus, @RMS, @OOS | E26: Integration | F26: HS | G26: 4 | H26: 1 | L26: ALL | M26: =COUNTIF('AIR HS FL'!$G$23:$G1545,"N/A for Automation") -> 0 | N26: =M26/$G26 -> 0 | O26: =COUNTIF('AIR HS FL'!$G$23:$G1545,"Automated") -> 4 | P26: =O26/$G26 -> 1 | Q26: =COUNTIF('AIR HS FL'!$G$23:$G1545,"Partial Automated") -> 0 | R26: =Q26/G26 -> 0 | S26: =COUNTIF('AIR HS FL'!$G$23:$G1545,"Not Automated") -> 0 | T26: =S26/$G26 -> 0 | U26: High | V26: Y | W26: N | X26: Rally TC
A27: Integration | B27: 11 | C27: RMS HS TX/HI | D27: @RMS, @Integration, @HS, @HomeSurplus, @Transactions, @END, @RN, @TX, @NB, @HI, @OOS | E27: Integration | F27: HS | G27: 6 | H27: 1 | L27: ALL | M27: =COUNTIF('RMS HS TX'!$G$23:$G1561,"N/A for Automation") -> 0 | N27: =M27/$G27 -> 0 | O27: =COUNTIF('RMS HS TX'!$G$23:$G1561,"Automated") -> 6 | P27: =O27/$G27 -> 1 | Q27: =COUNTIF('RMS HS TX'!$G$23:$G1561,"Partial Automated") -> 0 | R27: =Q27/G27 -> 0 | S27: =COUNTIF('RMS HS TX'!$G$23:$G1561,"Not Automated") -> 0 | T27: =S27/$G27 -> 0 | U27: High | V27: Y | W27: N | X27: Rally TC
A28: Integration | B28: 12 | C28: Elevation Certificate | D28: next/d | E28: Integration | F28: HO | G28: 20 | H28: 2 | K28: 3 | L28: ALL | M28: =COUNTIF('Elevation Certificate '!$G$23:$G1528,"N/A for Automation") -> 0 | N28: =M28/$G28 -> 0 | O28: =COUNTIF('Elevation Certificate '!$G$23:$G1528,"Automated") -> 20 | P28: =O28/$G28 -> 1 | Q28: =COUNTIF('Elevation Certificate '!$G$23:$G1528,"Partial Automated") -> 0 | R28: =Q28/G28 -> 0 | S28: =COUNTIF('Elevation Certificate '!$G$23:$G1528,"Not Automated") -> 0 | T28: =S28/$G28 -> 0 | U28: High | V28: Y | W28: N
A29: Integration | B29: 13 | C29: Earthquake report | D29: @Integration, @EQ, @Report, @Earthquake, @EarthquakeReport, @HO, @Homeowner, @NB, @NewBusiness, @END, @Endorsement, @OOS, @RN, @Renewal, @NBRewrite, @Rewrite, @HomeSurplus, @HS, @COC, @CourseOfConstruction, @Agent | E29: Integration | F29: HO | G29: 15 | H29: 2 | K29: 5 | L29: ALL | M29: =COUNTIF('Earthquake report'!$G$23:$G1602,"N/A for Automation") -> 0 | N29: =M29/$G29 -> 0 | O29: =COUNTIF('Earthquake report'!$G$23:$G1602,"Automated") -> 15 | P29: =O29/$G29 -> 1 | Q29: =COUNTIF('Earthquake report'!$G$23:$G1602,"Partial Automated") -> 0 | R29: =Q29/G29 -> 0 | S29: =COUNTIF('Earthquake report'!$G$23:$G1602,"Not Automated") -> 0 | T29: =S29/$G29 -> 0 | U29: High | V29: Y | W29: N | X29: Rally TC
A30: Integration | B30: 14 | C30: Wildfire Hazard reports | D30: next/d | E30: Integration | F30: HO | G30: 15 | H30: 2 | K30: 5 | L30: ALL | M30: =COUNTIF('Wildfire Hazard reports'!$G$23:$G1455,"N/A for Automation") -> 0 | N30: =M30/$G30 -> 0 | O30: =COUNTIF('Wildfire Hazard reports'!$G$23:$G1455,"Automated") -> 15 | P30: =O30/$G30 -> 1 | Q30: =COUNTIF('Wildfire Hazard reports'!$G$23:$G1455,"Partial Automated") -> 0 | R30: =Q30/G30 -> 0 | S30: =COUNTIF('Wildfire Hazard reports'!$G$23:$G1455,"Not Automated") -> 0 | T30: =S30/$G30 -> 0 | U30: High | V30: P | W30: N
A31: Functional | B31: 15 | C31: Moratorium | E31: Underwriting | F31: ALL | G31: 18 | K31: 7 | L31: ALL | M31: =COUNTIF(Moratorium!$G$23:$G1518,"N/A for Automation") -> 18 | N31: =M31/$G31 -> 1 | O31: =COUNTIF(Moratorium!$G$23:$G1518,"Automated") -> 0 | P31: =O31/$G31 -> 0 | Q31: =COUNTIF(Moratorium!$G$23:$G1518,"Partial Automated") -> 0 | R31: =Q31/G31 -> 0 | S31: =COUNTIF(Moratorium!$G$23:$G1518,"Not Automated") -> 0 | T31: =S31/$G31 -> 0 | U31: High | V31: N | W31: N
A32: Integration | B32: 16 | C32: Docusign | E32: Integration | F32: ALL | G32: 22 | H32: 6 | K32: 5 | L32: ALL | M32: =COUNTIF('Dragon-DocuSign'!$G$23:$G1519,"N/A for Automation") -> 14 | N32: =M32/$G32 -> 0.63636364 | O32: =COUNTIF('Dragon-DocuSign'!$G$23:$G1519,"Automated") -> 5 | P32: =O32/$G32 -> 0.22727273 | Q32: =COUNTIF('Dragon-DocuSign'!$G$23:$G1519,"Partial Automated") -> 3 | R32: =Q32/G32 -> 0.13636364 | S32: =COUNTIF('Dragon-DocuSign'!$G$23:$G1519,"Not Automated") -> 0 | T32: =S32/$G32 -> 0 | U32: High | V32: P | W32: N
A33: Functional | B33: 17 | C33: ITNR | E33: Underwriting | F33: ALL | G33: 10 | K33: 2 | L33: ALL | M33: =COUNTIF(ITNR!$G$23:$G1520,"N/A for Automation") -> 0 | N33: =M33/$G33 -> 0 | O33: =COUNTIF(ITNR!$G$23:$G1520,"Automated") -> 0 | P33: =O33/$G33 -> 0 | Q33: =COUNTIF(ITNR!$G$23:$G1520,"Partial Automated") -> 7 | R33: =Q33/G33 -> 0.7 | S33: =COUNTIF(ITNR!$G$23:$G1520,"Not Automated") -> 3 | T33: =S33/$G33 -> 0.3 | U33: Medium | V33: P | W33: N
A34: Functional | B34: 18 | C34: Agent Resource | E34: Underwriting | F34: NA | G34: 8 | K34: 1 | L34: ALL | M34: =COUNTIF('Agent Resource'!$G$23:$G1521,"N/A for Automation") -> 8 | N34: =M34/$G34 -> 1 | O34: =COUNTIF('Agent Resource'!$G$23:$G1521,"Automated") -> 0 | P34: =O34/$G34 -> 0 | Q34: =COUNTIF('Agent Resource'!$G$23:$G1521,"Partial Automated") -> 0 | R34: =Q34/G34 -> 0 | S34: =COUNTIF('Agent Resource'!$G$23:$G1521,"Not Automated") -> 0 | T34: =S34/$G34 -> 0 | U34: Low | V34: N/A | W34: N
A35: Integration | B35: 19 | C35: Predictive analytics - Home model - Appraisal | D35: @Integration, @PredictiveAnalysis, @A, @Homeowners, @Homeowner, @Grade, @Conversion, @Condo, @CondoCoop, @Tenants, @F, @OOS | E35: Integration | F35: HO | G35: 13 | H35: 1 | I35: 7 | L35: ALL | M35: =COUNTIF('Predictive analytics-Home model'!$G$23:$G1789,"N/A for Automation") -> 0 | N35: =M35/$G35 -> 0 | O35: =COUNTIF('Predictive analytics-Home model'!$G$23:$G1789,"Automated") -> 13 | P35: =O35/$G35 -> 1 | Q35: =COUNTIF('Predictive analytics-Home model'!$G$23:$G1789,"Partial Automated") -> 0 | R35: =Q35/G35 -> 0 | S35: =COUNTIF('Predictive analytics-Home model'!$G$23:$G1789,"Not Automated") -> 0 | T35: =S35/$G35 -> 0 | U35: High | V35: Y | W35: N | X35: Rally TC
A36: Integration | B36: 20 | C36: Predictive analytics - Auto model | D36: @Integration, @PredictiveAnalysis, @Auto, @PA, @Automobile, @A, @Grade, @F, @OOS, @Conversion, @AccountSummary, @Summary, @ | E36: Integration | F36: PA | G36: 6 | H36: 1 | I36: 50 | L36: ALL | M36: =COUNTIF('Predictive analytics-Auto model'!$G$23:$G1556,"N/A for Automation") -> 0 | N36: =M36/$G36 -> 0 | O36: =COUNTIF('Predictive analytics-Auto model'!$G$23:$G1556,"Automated") -> 6 | P36: =O36/$G36 -> 1 | Q36: =COUNTIF('Predictive analytics-Auto model'!$G$23:$G1556,"Partial Automated") -> 0 | R36: =Q36/G36 -> 0 | S36: =COUNTIF('Predictive analytics-Auto model'!$G$23:$G1556,"Not Automated") -> 0 | T36: =S36/$G36 -> 0 | U36: High | V36: Y | W36: N | X36: Rally TC
A37: Integration | B37: 21 | C37: Predictive analytics - Excess model | D37: @Integration, @PredictiveAnalysis, @Excess, @EX, @ExcessLiability, @A, @F, @Grade, @OOS | E37: Integration | F37: EX | G37: 5 | H37: 1 | I37: 50 | L37: ALL | M37: =COUNTIF('Predictive analytics-Excess mod'!$G$23:$G1554,"N/A for Automation") -> 0 | N37: =M37/$G37 -> 0 | O37: =COUNTIF('Predictive analytics-Excess mod'!$G$23:$G1554,"Automated") -> 5 | P37: =O37/$G37 -> 1 | Q37: =COUNTIF('Predictive analytics-Excess mod'!$G$23:$G1554,"Partial Automated") -> 0 | R37: =Q37/G37 -> 0 | S37: =COUNTIF('Predictive analytics-Excess mod'!$G$23:$G1554,"Not Automated") -> 0 | T37: =S37/$G37 -> 0 | U37: High | V37: Y | W37: N | X37: Rally TC
A38: Functional | B38: 22 | C38: Account Grade Summary | E38: Underwriting | F38: ALL | G38: 2 | K38: 1 | L38: ALL | M38: =COUNTIF('Account Grade Summary'!$G$23:$G1525,"N/A for Automation") -> 0 | N38: =M38/$G38 -> 0 | O38: =COUNTIF('Account Grade Summary'!$G$23:$G1525,"Automated") -> 0 | P38: =O38/$G38 -> 0 | Q38: =COUNTIF('Account Grade Summary'!$G$23:$G1525,"Partial Automated") -> 0 | R38: =Q38/G38 -> 0 | S38: =COUNTIF('Account Grade Summary'!$G$23:$G1525,"Not Automated") -> 2 | T38: =S38/$G38 -> 1 | U38: High | V38: Y | W38: N
A39: Functional | B39: 23 | C39: Roles/Authority - Sub Roles | D39: Alex | E39: Underwriting | F39: ALL | G39: 94 | K39: 35 | L39: ALL | M39: =COUNTIF('Roles Authority - Sub Roles'!$G$23:$G1525,"N/A for Automation") -> 0 | N39: =M39/$G39 -> 0 | O39: =COUNTIF('Roles Authority - Sub Roles'!$G$23:$G1525,"Automated") -> 0 | P39: =O39/$G39 -> 0 | Q39: =COUNTIF('Roles Authority - Sub Roles'!$G$23:$G1525,"Partial Automated") -> 0 | R39: =Q39/G39 -> 0 | S39: =COUNTIF('Roles Authority - Sub Roles'!$G$23:$G1525,"Not Automated") -> 94 | T39: =S39/$G39 -> 1 | U39: High | V39: N | W39: N
A40: Integration | B40: 24 | C40: Home CLUE | D40: @Integration, @HomeCLUE, @CLUE, @Homeowners, @HO, @Homeowner, @NoLosses, @Losses, @Override, @DifferentAddress, @Claims, @Agent, @COC, @HS, @HomeSurplus, @Document, @Upload | E40: Integration | F40: HO | G40: 12 | H40: 1 | K40: 4 | L40: ALL | M40: =COUNTIF('Dragon-LexisNexis HO CLUE'!$G$23:$G1561,"N/A for Automation") -> 0 | N40: =M40/$G40 -> 0 | O40: =COUNTIF('Dragon-LexisNexis HO CLUE'!$G$23:$G1561,"Automated") -> 12 | P40: =O40/$G40 -> 1 | Q40: =COUNTIF('Dragon-LexisNexis HO CLUE'!$G$23:$G1561,"Partial Automated") -> 0 | R40: =Q40/G40 -> 0 | S40: =COUNTIF('Dragon-LexisNexis HO CLUE'!$G$23:$G1561,"Not Automated") -> 0 | T40: =S40/$G40 -> 0 | U40: High | V40: Y | W40: N | X40: Rally TC
A41: Integration | B41: 25 | C41: Auto CLUE | D41: @Integration, @CLUE, @AutoCLUE, @Losses, @NoLosses, @Claims, @PA, @DifferentAddress, @Override, @Agent, @AutoPull, @NewDriver, @Endorsement, @ExcludedDriver, @Document, @Upload | E41: Integration | F41: PA | G41: 13 | H41: 1 | K41: 4 | L41: ALL | M41: =COUNTIF('Dragon-LexisNexis PA CLUE'!$G$23:$G1605,"N/A for Automation") -> 0 | N41: =M41/$G41 -> 0 | O41: =COUNTIF('Dragon-LexisNexis PA CLUE'!$G$23:$G1605,"Automated") -> 13 | P41: =O41/$G41 -> 1 | Q41: =COUNTIF('Dragon-LexisNexis PA CLUE'!$G$23:$G1605,"Partial Automated") -> 0 | R41: =Q41/G41 -> 0 | S41: =COUNTIF('Dragon-LexisNexis PA CLUE'!$G$23:$G1605,"Not Automated") -> 0 | T41: =S41/$G41 -> 0 | U41: High | V41: P | W41: N | X41: Rally TC
A42: Integration | B42: 26 | C42: Auto MVR | D42: @Integration, @MVR, @PA, @PersonalAuto, @Agent, @Hit, @ActivityFound, @No, @NoHit, @Override, @Endorsement, @AutoPull, @NewDriver, @ExcludedDriver, @NotInHousehold, @NoLosses, @NoAutoPull, @Document, @Upload | E42: Integration | F42: PA | G42: 13 | H42: 1 | I42: 50 | K42: 4 | L42: ALL | M42: =COUNTIF('Dragon-LexisNexis PA MVR'!$G$23:$G1593,"N/A for Automation") -> 0 | N42: =M42/$G42 -> 0 | O42: =COUNTIF('Dragon-LexisNexis PA MVR'!$G$23:$G1593,"Automated") -> 13 | P42: =O42/$G42 -> 1 | Q42: =COUNTIF('Dragon-LexisNexis PA MVR'!$G$23:$G1593,"Partial Automated") -> 0 | R42: =Q42/G42 -> 0 | S42: =COUNTIF('Dragon-LexisNexis PA MVR'!$G$23:$G1593,"Not Automated") -> 0 | T42: =S42/$G42 -> 0 | U42: High | V42: P | W42: N | X42: Rally TC
A43: Integration | B43: 27 | C43: Excess CLUE | D43: @CLUE, @ExcessClue, @ExcessCLUE, @Integration, @ExcessLiability, @ExcessSurplus, @EX, @Losses, @NoLosses, @DifferentAddress, @Override, @Endorsement, @NewDriver, @AutoPull, @ExcludedDriver, @Agent, @ES, @Document, @Upload, @Unassigned, | E43: Integration | F43: EX | G43: 16 | H43: 1 | K43: 3 | L43: ALL | M43: =COUNTIF('Dragon-LexisNexis EX CLUE'!$G$24:$G1666,"N/A for Automation") -> 0 | N43: =M43/$G43 -> 0 | O43: =COUNTIF('Dragon-LexisNexis EX CLUE'!$G$24:$G1666,"Automated") -> 16 | P43: =O43/$G43 -> 1 | Q43: =COUNTIF('Dragon-LexisNexis EX CLUE'!$G$24:$G1666,"Partial Automated") -> 0 | R43: =Q43/G43 -> 0 | S43: =COUNTIF('Dragon-LexisNexis EX CLUE'!$G$24:$G1666,"Not Automated") -> 0 | T43: =S43/$G43 -> 0 | U43: High | V43: P | W43: N | X43: Rally TC
A44: Integration | B44: 28 | C44: Excess MVR | D44: @MVR, @Integration, @ExcessLiability, @EX, @Hit, @Activity, @Found, @Agent, @No, @NoHit, @Override, @AutoPull, @Endorsement, @NewDriver, @ExcludedDriver, @NoLosses, @ES, @ActivityFound, @Document, @Upload | E44: Integration | F44: EX | G44: 14 | H44: 1 | K44: 1 | L44: ALL | M44: =COUNTIF('Dragon-LexisNexis EX MVR'!$G$24:$G1618,"N/A for Automation") -> 0 | N44: =M44/$G44 -> 0 | O44: =COUNTIF('Dragon-LexisNexis EX MVR'!$G$24:$G1618,"Automated") -> 14 | P44: =O44/$G44 -> 1 | Q44: =COUNTIF('Dragon-LexisNexis EX MVR'!$G$24:$G1618,"Partial Automated") -> 0 | R44: =Q44/G44 -> 0 | S44: =COUNTIF('Dragon-LexisNexis EX MVR'!$G$24:$G1618,"Not Automated") -> 0 | T44: =S44/$G44 -> 0 | U44: High | V44: P | W44: N | X44: Rally TC
A45: Integration | B45: 29 | C45: Home prefill | D45: @Home, @HO, @HomePrefill, @Integration, @Homeowners, @Homeowner, @CA, @Condo, @Coop, @Tenants, @END, @Endorsement, @OOS, @HomeSurplus, @HS, @RN, @Renewal, | E45: Integration | F45: HO | G45: 16 | H45: 2 | K45: 3 | L45: ALL | M45: =COUNTIF('Dragon-LexisNexis HO prefill'!$G$23:$G1731,"N/A for Automation") -> 0 | N45: =M45/$G45 -> 0 | O45: =COUNTIF('Dragon-LexisNexis HO prefill'!$G$23:$G1731,"Automated") -> 16 | P45: =O45/$G45 -> 1 | Q45: =COUNTIF('Dragon-LexisNexis HO prefill'!$G$23:$G1731,"Partial Automated") -> 0 | R45: =Q45/G45 -> 0 | S45: =COUNTIF('Dragon-LexisNexis HO prefill'!$G$23:$G1731,"Not Automated") -> 0 | T45: =S45/$G45 -> 0 | U45: High | V45: P | W45: N | X45: Rally TC
A46: Integration | B46: 30 | C46: Auto prefill | D46: @AutoPrefill, @Prefill, @Integration, @PersonalAuto, @PA, @ES | E46: Integration | F46: PA | G46: 5 | H46: 1 | K46: 1.5 | L46: ALL | M46: =COUNTIF('Dragon-LexisNexis PA prefill'!$G$23:$G1513,"N/A for Automation") -> 0 | N46: =M46/$G46 -> 0 | O46: =COUNTIF('Dragon-LexisNexis PA prefill'!$G$23:$G1513,"Automated") -> 5 | P46: =O46/$G46 -> 1 | Q46: =COUNTIF('Dragon-LexisNexis PA prefill'!$G$23:$G1513,"Partial Automated") -> 0 | R46: =Q46/G46 -> 0 | S46: =COUNTIF('Dragon-LexisNexis PA prefill'!$G$23:$G1513,"Not Automated") -> 0 | T46: =S46/$G46 -> 0 | U46: High | V46: P | W46: N | X46: Rally TC
A47: Integration | B47: 31 | C47: Auto NADA (Coll Symbol, OTC, PIP) | D47: Alex | E47: Integration | F47: PA | G47: 6 | H47: 1 | K47: 2 | L47: ALL | M47: =COUNTIF('Auto NADA(Coll Symbol,OTC,PIP)'!$G$23:$G1541,"N/A for Automation") -> 1 | N47: =M47/$G47 -> 0.16666667 | O47: =COUNTIF('Auto NADA(Coll Symbol,OTC,PIP)'!$G$23:$G1541,"Automated") -> 2 | P47: =O47/$G47 -> 0.33333333 | Q47: =COUNTIF('Auto NADA(Coll Symbol,OTC,PIP)'!$G$23:$G1541,"Partial Automated") -> 3 | R47: =Q47/G47 -> 0.5 | S47: =COUNTIF('Auto NADA(Coll Symbol,OTC,PIP)'!$G$23:$G1541,"Not Automated") -> 0 | T47: =S47/$G47 -> 0 | U47: High | V47: P | W47: N
A48: Integration | B48: 32 | C48: PW NADA | D48: @NADA, @PWNADA, @PW, @PrivateWatercraft, @Integration, @NewBusiness, @NB, @Prefill, @Endorsement, @END, @OOS, @Renewal, @RN, @ | E48: Integration | F48: PW | G48: 10 | H48: 1 | K48: 2 | L48: ALL | M48: =COUNTIF('PW NADA'!$G$23:$G1542,"N/A for Automation") -> 0 | N48: =M48/$G48 -> 0 | O48: =COUNTIF('PW NADA'!$G$23:$G1542,"Automated") -> 10 | P48: =O48/$G48 -> 1 | Q48: =COUNTIF('PW NADA'!$G$23:$G1542,"Partial Automated") -> 0 | R48: =Q48/G48 -> 0 | S48: =COUNTIF('PW NADA'!$G$23:$G1542,"Not Automated") -> 0 | T48: =S48/$G48 -> 0 | U48: High | V48: N | W48: N | X48: Rally TC
A49: Integration | B49: 33 | C49: Carfax | D49: Alex | E49: Integration | F49: PA | G49: 8 | H49: 1 | K49: 6 | L49: ALL | M49: =COUNTIF(Carfax!$G$23:$G1531,"N/A for Automation") -> 0 | N49: =M49/$G49 -> 0 | O49: =COUNTIF(Carfax!$G$23:$G1531,"Automated") -> 2 | P49: =O49/$G49 -> 0.25 | Q49: =COUNTIF(Carfax!$G$23:$G1531,"Partial Automated") -> 1 | R49: =Q49/G49 -> 0.125 | S49: =COUNTIF(Carfax!$G$23:$G1531,"Not Automated") -> 5 | T49: =S49/$G49 -> 0.625 | U49: High | V49: N | W49: N
A50: Functional | B50: 34 | C50: PURE Claims (Add template) | E50: Functional | F50: ALL | G50: 5 | K50: 3 | L50: ALL | M50: =COUNTIF('PURE Claims '!$G$23:$G1538,"N/A for Automation") -> 5 | N50: =M50/$G50 -> 1 | O50: =COUNTIF('PURE Claims '!$G$23:$G1538,"Automated") -> 0 | P50: =O50/$G50 -> 0 | Q50: =COUNTIF('PURE Claims '!$G$23:$G1538,"Partial Automated") -> 0 | R50: =Q50/G50 -> 0 | S50: =COUNTIF('PURE Claims '!$G$23:$G1538,"Not Automated") -> 0 | T50: =S50/$G50 -> 0 | U50: High | W50: N
A51: Functional | B51: 35 | C51: End submission | E51: Underwriting | F51: ALL | G51: 20 | K51: 5 | L51: ALL | M51: =COUNTIF('End submission'!$G$23:$G1544,"N/A for Automation") -> 20 | N51: =M51/$G51 -> 1 | O51: =COUNTIF('End submission'!$G$23:$G1544,"Automated") -> 0 | P51: =O51/$G51 -> 0 | Q51: =COUNTIF('End submission'!$G$23:$G1544,"Partial Automated") -> 0 | R51: =Q51/G51 -> 0 | S51: =COUNTIF('End submission'!$G$23:$G1544,"Not Automated") -> 0 | T51: =S51/$G51 -> 0 | U51: Medium | V51: N | W51: N
A52: Functional | B52: 36 | C52: Round Robbin | E52: Underwriting | F52: ALL | G52: 18 | K52: 4 | L52: ALL | M52: =COUNTIF('Round Robin'!$G$23:$G1548,"N/A for Automation") -> 18 | N52: =M52/$G52 -> 1 | O52: =COUNTIF('Round Robin'!$G$23:$G1548,"Automated") -> 0 | P52: =O52/$G52 -> 0 | Q52: =COUNTIF('Round Robin'!$G$23:$G1548,"Partial Automated") -> 0 | R52: =Q52/G52 -> 0 | S52: =COUNTIF('Round Robin'!$G$23:$G1548,"Not Automated") -> 0 | T52: =S52/$G52 -> 0 | U52: Medium | V52: N | W52: N
A53: Integration | B53: 37 | C53: Insurance score | E53: Integration | F53: ALL | G53: 25 | H53: 6 | K53: 25 | L53: ALL | M53: =COUNTIF('Insurance score'!$G$23:$G1505,"N/A for Automation") -> 8 | N53: =M53/$G53 -> 0.32 | O53: =COUNTIF('Insurance score'!$G$23:$G1505,"Automated") -> 2 | P53: =O53/$G53 -> 0.08 | Q53: =COUNTIF('Insurance score'!$G$23:$G1505,"Partial Automated") -> 0 | R53: =Q53/G53 -> 0 | S53: =COUNTIF('Insurance score'!$G$23:$G1505,"Not Automated") -> 15 | T53: =S53/$G53 -> 0.6 | U53: Critical | V53: N | W53: N
A54: Integration | B54: 38 | C54: ISO - PPC & BCEG | E54: Integration | F54: HO | G54: 5 | H54: 2 | K54: 10 | L54: ALL | M54: =COUNTIF('ISO, PPC & BCEG'!$G$23:$G1547,"N/A for Automation") -> 0 | N54: =M54/$G54 -> 0 | O54: =COUNTIF('ISO, PPC & BCEG'!$G$23:$G1547,"Automated") -> 1 | P54: =O54/$G54 -> 0.2 | Q54: =COUNTIF('ISO, PPC & BCEG'!$G$23:$G1547,"Partial Automated") -> 0 | R54: =Q54/G54 -> 0 | S54: =COUNTIF('ISO, PPC & BCEG'!$G$23:$G1547,"Not Automated") -> 4 | T54: =S54/$G54 -> 0.8 | U54: High | V54: N | W54: N
A55: Integration | B55: 39 | C55: Weather analytics | D55: @Integration, @Weather, @WeatherAnalytics, @HO, @Homeowner, @TX, @NB, @END, @OOS, @Renewal, @HS, @HomeSurplus, @Agent | E55: Integration | F55: HO | G55: 7 | L55: ALL | M55: =COUNTIF('Weather analytics'!$G$23:$G1629,"N/A for Automation") -> 0 | N55: =M55/$G55 -> 0 | O55: =COUNTIF('Weather analytics'!$G$23:$G1629,"Automated") -> 7 | P55: =O55/$G55 -> 1 | Q55: =COUNTIF('Weather analytics'!$G$23:$G1629,"Partial Automated") -> 0 | R55: =Q55/G55 -> 0 | S55: =COUNTIF('Weather analytics'!$G$23:$G1629,"Not Automated") -> 0 | T55: =S55/$G55 -> 0 | U55: High | V55: Y | W55: N | X55: Rally TC
A56: Integration | B56: 40 | C56: Verisk | E56: Integration | F56: HO | G56: 3 | I56: KY | K56: 7 | L56: ALL | M56: =COUNTIF(Verisk!$G$23:$G1549,"N/A for Automation") -> 3 | N56: =M56/$G56 -> 1 | O56: =COUNTIF(Verisk!$G$23:$G1549,"Automated") -> 0 | P56: =O56/$G56 -> 0 | Q56: =COUNTIF(Verisk!$G$23:$G1549,"Partial Automated") -> 0 | R56: =Q56/G56 -> 0 | S56: =COUNTIF(Verisk!$G$23:$G1549,"Not Automated") -> 0 | T56: =S56/$G56 -> 0 | U56: High | V56: N | W56: N | X56: N/A turned off
A57: Functional | B57: 41 | C57: Quote Not Taken up | E57: Underwriting | F57: ALL | G57: 8 | K57: 1 | L57: ALL | M57: =COUNTIF('Quote Not Taken up'!$G$23:$G1553,"N/A for Automation") -> 0 | N57: =M57/$G57 -> 0 | O57: =COUNTIF('Quote Not Taken up'!$G$23:$G1553,"Automated") -> 0 | P57: =O57/$G57 -> 0 | Q57: =COUNTIF('Quote Not Taken up'!$G$23:$G1553,"Partial Automated") -> 0 | R57: =Q57/G57 -> 0 | S57: =COUNTIF('Quote Not Taken up'!$G$23:$G1553,"Not Automated") -> 8 | T57: =S57/$G57 -> 1 | U57: Medium | V57: N | W57: N
A58: Functional | B58: 42 | C58: Forms | E58: Forms | F58: ALL | G58: 20 | K58: 8 | L58: ALL | M58: =COUNTIF(Forms!$G$23:$G1528,"N/A for Automation") -> 0 | N58: =M58/$G58 -> 0 | O58: =COUNTIF(Forms!$G$23:$G1528,"Automated") -> 1 | P58: =O58/$G58 -> 0.05 | Q58: =COUNTIF(Forms!$G$23:$G1528,"Partial Automated") -> 11 | R58: =Q58/G58 -> 0.55 | S58: =COUNTIF(Forms!$G$23:$G1528,"Not Automated") -> 8 | T58: =S58/$G58 -> 0.4 | U58: Medium | V58: P | W58: N
A59: Functional | B59: 43 | C59: Quote Proposals | D59: next/d | E59: Forms | F59: ALL | G59: 11 | K59: 1 | L59: ALL | M59: =COUNTIF('Quote Proposals'!$G$23:$G1574,"N/A for Automation") -> 1 | N59: =M59/$G59 -> 0.090909091 | O59: =COUNTIF('Quote Proposals'!$G$23:$G1574,"Automated") -> 10 | P59: =O59/$G59 -> 0.90909091 | Q59: =COUNTIF('Quote Proposals'!$G$23:$G1574,"Partial Automated") -> 0 | R59: =Q59/G59 -> 0 | S59: =COUNTIF('Quote Proposals'!$G$23:$G1574,"Not Automated") -> 0 | T59: =S59/$G59 -> 0 | U59: High | V59: P | W59: N
A60: Functional | B60: 44 | C60: Pre Bind Forms | E60: Forms | F60: ALL | G60: 74 | K60: 25 | L60: ALL | M60: =COUNTIF('Pre Bind Forms'!$G$23:$G1549,"N/A for Automation") -> 0 | N60: =M60/$G60 -> 0 | O60: =COUNTIF('Pre Bind Forms'!$G$23:$G1549,"Automated") -> 0 | P60: =O60/$G60 -> 0 | Q60: =COUNTIF('Pre Bind Forms'!$G$23:$G1549,"Partial Automated") -> 0 | R60: =Q60/G60 -> 0 | S60: =COUNTIF('Pre Bind Forms'!$G$23:$G1549,"Not Automated") -> 74 | T60: =S60/$G60 -> 1 | U60: Medium | V60: N | W60: N
A61: Integration | B61: 45 | C61: KY Municipality Taxes | D61: @KY, @Municipality, @Taxes, @MunicipalityTaxes, @Integration, @Homeowners, @HO, @Homeowner, @NB, @NewBusiness, @CondoCoop, @Condo, @END, @Endorsement, @Tenants, @RN, @Renewal, @PA, @PersonalAuto, @Auto, @EX, @ExcessLiability, @COC, @CC, @CourseOfConstruction | E61: Integration | F61: ALL | G61: 15 | I61: KY | K61: 3 | L61: ALL | M61: =COUNTIF('KY Municipality Taxes'!$G$23:$G1520,"N/A for Automation") -> 0 | N61: =M61/$G61 -> 0 | O61: =COUNTIF('KY Municipality Taxes'!$G$23:$G1520,"Automated") -> 15 | P61: =O61/$G61 -> 1 | Q61: =COUNTIF('KY Municipality Taxes'!$G$23:$G1520,"Partial Automated") -> 0 | R61: =Q61/G61 -> 0 | S61: =COUNTIF('KY Municipality Taxes'!$G$23:$G1520,"Not Automated") -> 0 | T61: =S61/$G61 -> 0 | U61: High | V61: P | W61: N | X61: Rally TC
A62: Integration | B62: 46 | C62: Census Tract | D62: @Integration, @MI, @PA, @Auto, @Census, @CensusTract, @NB, @NewBusiness, @END, @Endorsement, @OOS, @RN, @Renewal, @Override, @Agent | E62: Integration | F62: PA | G62: 6 | I62: KY | L62: ALL | M62: =COUNTIF('Census Tract'!$G$23:$G1569,"N/A for Automation") -> 0 | N62: =M62/$G62 -> 0 | O62: =COUNTIF('Census Tract'!$G$23:$G1569,"Automated") -> 6 | P62: =O62/$G62 -> 1 | Q62: =COUNTIF('Census Tract'!$G$23:$G1569,"Partial Automated") -> 0 | R62: =Q62/G62 -> 0 | S62: =COUNTIF('Census Tract'!$G$23:$G1569,"Not Automated") -> 0 | T62: =S62/$G62 -> 0 | U62: High | V62: Y | W62: N | X62: Rally TC
A63: Integration | B63: 47 | C63: Billing | E63: Integration | F63: ALL | G63: 8 | K63: 10 | L63: ALL | M63: =COUNTIF(Billing!$G$23:$G1551,"N/A for Automation") -> 0 | N63: =M63/$G63 -> 0 | O63: =COUNTIF(Billing!$G$23:$G1551,"Automated") -> 0 | P63: =O63/$G63 -> 0 | Q63: =COUNTIF(Billing!$G$23:$G1551,"Partial Automated") -> 0 | R63: =Q63/G63 -> 0 | S63: =COUNTIF(Billing!$G$23:$G1551,"Not Automated") -> 8 | T63: =S63/$G63 -> 1 | U63: Medium | V63: N | W63: N
A64: Functional | B64: 48 | C64: LA and UHNW indicators | E64: Underwriting | F64: Admitted | G64: 7 | K64: 2 | L64: ALL | M64: =COUNTIF('LA and UHNW indicators'!$G$23:$G1560,"N/A for Automation") -> 0 | N64: =M64/$G64 -> 0 | O64: =COUNTIF('LA and UHNW indicators'!$G$23:$G1560,"Automated") -> 0 | P64: =O64/$G64 -> 0 | Q64: =COUNTIF('LA and UHNW indicators'!$G$23:$G1560,"Partial Automated") -> 0 | R64: =Q64/G64 -> 0 | S64: =COUNTIF('LA and UHNW indicators'!$G$23:$G1560,"Not Automated") -> 7 | T64: =S64/$G64 -> 1 | U64: High | V64: N | W64: N
A65: Functional | B65: 49 | C65: Mortgagee | E65: Underwriting | F65: HO | G65: 3 | K65: 2 | L65: ALL | M65: =COUNTIF(Mortgagee!$G$23:$G1561,"N/A for Automation") -> 0 | N65: =M65/$G65 -> 0 | O65: =COUNTIF(Mortgagee!$G$23:$G1561,"Automated") -> 0 | P65: =O65/$G65 -> 0 | Q65: =COUNTIF(Mortgagee!$G$23:$G1561,"Partial Automated") -> 3 | R65: =Q65/G65 -> 1 | S65: =COUNTIF(Mortgagee!$G$23:$G1561,"Not Automated") -> 0 | T65: =S65/$G65 -> 0 | U65: High | V65: N | W65: N
A66: Functional | B66: 50 | C66: Cancellation Types | D66: next/d | E66: Underwriting | F66: ALL | G66: 29 | K66: 5 | L66: ALL | M66: =COUNTIF('Cancellation Types'!$G$23:$G1701,"N/A for Automation") -> 1 | N66: =M66/$G66 -> 0.034482759 | O66: =COUNTIF('Cancellation Types'!$G$23:$G1697,"Automated") -> 0 | P66: =O66/$G66 -> 0 | Q66: =COUNTIF('Cancellation Types'!$G$23:$G1697,"Partial Automated") -> 8 | R66: =Q66/G66 -> 0.27586207 | S66: =COUNTIF('Cancellation Types'!$G$23:$G1697,"Not Automated") -> 20 | T66: =S66/$G66 -> 0.68965517 | U66: High | V66: N | W66: N
A67: Integration | B67: 51 | C67: Sinkhole | D67: @Integration, @SinkHole, @Sinkhole, @HO, @Homeowner, @NB, @NewBusiness, @END, @Endorsement, @OOS, @RN, @Renewal, @HomeSurplus, @HS, @COC, @CourseOfConstruction, | E67: Integration | F67: HO | G67: 13 | I67: FL | K67: 1.5 | L67: ALL | M67: =COUNTIF(Sinkhole!$G$23:$G1549,"N/A for Automation") -> 0 | N67: =M67/$G67 -> 0 | O67: =COUNTIF(Sinkhole!$G$23:$G1549,"Automated") -> 13 | P67: =O67/$G67 -> 1 | Q67: =COUNTIF(Sinkhole!$G$23:$G1549,"Partial Automated") -> 0 | R67: =Q67/G67 -> 0 | S67: =COUNTIF(Sinkhole!$G$23:$G1549,"Not Automated") -> 0 | T67: =S67/$G67 -> 0 | U67: High | V67: N | W67: N | X67: Rally TC
A68: Integration | B68: 52 | C68: Storm Surge | D68: @Integration, @StormSurge, @HO, @Homeowner, @NB, @NewBusiness, @END, @Endorsement, @OOS, @RN, @Renewal, @HomeSurplus, @HS, @COC, @CourseOfConstruction, | E68: Integration | F68: HO | G68: 13 | I68: FL | K68: 1.5 | L68: ALL | M68: =COUNTIF('Storm Surge'!$G$23:$G1550,"N/A for Automation") -> 0 | N68: =M68/$G68 -> 0 | O68: =COUNTIF('Storm Surge'!$G$23:$G1550,"Automated") -> 13 | P68: =O68/$G68 -> 1 | Q68: =COUNTIF('Storm Surge'!$G$23:$G1550,"Partial Automated") -> 0 | R68: =Q68/G68 -> 0 | S68: =COUNTIF('Storm Surge'!$G$23:$G1550,"Not Automated") -> 0 | T68: =S68/$G68 -> 0 | U68: High | V68: N | W68: N | X68: COC Code is done. Waiting to implement it to turn it on. Rally TC
A69: Integration | B69: 53 | C69: Wind pool | D69: @Integration, @Wind, @WindPool, @HO, @Homeowner, @NB, @NewBusiness, @END, @Endorsement, @OOS, @RN, @Renewal, @HomeSurplus, @HS, @COC, @CourseOfConstruction, | E69: Integration | F69: HO | G69: 13 | I69: FL | K69: 1.5 | L69: ALL | M69: =COUNTIF('Wind pool'!$G$23:$G1602,"N/A for Automation") -> 0 | N69: =M69/$G69 -> 0 | O69: =COUNTIF('Wind pool'!$G$23:$G1602,"Automated") -> 13 | P69: =O69/$G69 -> 1 | Q69: =COUNTIF('Wind pool'!$G$23:$G1602,"Partial Automated") -> 0 | R69: =Q69/G69 -> 0 | S69: =COUNTIF('Wind pool'!$G$23:$G1602,"Not Automated") -> 0 | T69: =S69/$G69 -> 0 | U69: High | V69: N | W69: N | X69: Rally TC
A70: Integration | B70: 54 | C70: Locations | D70: next/d | E70: Integration | F70: ALL | G70: 2 | K70: 0.5 | L70: ALL | M70: =COUNTIF(Locations!$G$23:$G1567,"N/A for Automation") -> 0 | N70: =M70/$G70 -> 0 | O70: =COUNTIF(Locations!$G$23:$G1567,"Automated") -> 0 | P70: =O70/$G70 -> 0 | Q70: =COUNTIF(Locations!$G$23:$G1567,"Partial Automated") -> 0 | R70: =Q70/G70 -> 0 | S70: =COUNTIF(Locations!$G$23:$G1567,"Not Automated") -> 2 | T70: =S70/$G70 -> 1 | U70: Medium | V70: N | W70: N | X70: Rally TC
A71: Functional | B71: 55 | C71: Underwriter Reassignement | E71: Underwriting | F71: ALL | G71: 18 | K71: 6 | L71: ALL | M71: =COUNTIF('Underwriter Reassignement'!$G$23:$G1558,"N/A for Automation") -> 0 | N71: =M71/$G71 -> 0 | O71: =COUNTIF('Underwriter Reassignement'!$G$23:$G1558,"Automated") -> 0 | P71: =O71/$G71 -> 0 | Q71: =COUNTIF('Underwriter Reassignement'!$G$23:$G1558,"Partial Automated") -> 0 | R71: =Q71/G71 -> 0 | S71: =COUNTIF('Underwriter Reassignement'!$G$23:$G1558,"Not Automated") -> 18 | T71: =S71/$G71 -> 1 | U71: Medium | V71: N | W71: N
A72: Functional | B72: 56 | C72: Manuscript endorsement | E72: Underwriting | F72: ALL | G72: 15 | K72: 8 | L72: ALL | M72: =COUNTIF('Manuscript endorsement'!$G$23:$H1313,"N/A for Automation") -> 0 | N72: =M72/$G72 -> 0 | O72: =COUNTIF('Manuscript endorsement'!$G$23:$G1313,"Automated") -> 0 | P72: =O72/$G72 -> 0 | Q72: =COUNTIF('Manuscript endorsement'!$G$23:$G1313,"Partial Automated") -> 7 | R72: =Q72/G72 -> 0.46666667 | S72: =COUNTIF('Manuscript endorsement'!$G$23:$G1313,"Not Automated") -> 8 | T72: =S72/$G72 -> 0.53333333 | U72: High | V72: N | W72: N
A73: Integration | B73: 57 | C73: Flood | D73: @Integration, @Flood, @HO, @FL, @Homeowners, @Homeowner, @Condo, @Coop, @CA, @Tenants, @WA, @Endorsement, @OOS, @Renewal | E73: Integration | F73: HS | G73: 19 | L73: ALL | M73: =COUNTIF(Flood!$G$23:$G1859,"N/A for Automation") -> 0 | N73: =M73/$G73 -> 0 | O73: =COUNTIF(Flood!$G$23:$G1859,"Automated") -> 19 | P73: =O73/$G73 -> 1 | Q73: =COUNTIF(Flood!$G$23:$G1859,"Partial Automated") -> 0 | R73: =Q73/G73 -> 0 | S73: =COUNTIF(Flood!$G$23:$G1859,"Not Automated") -> 0 | T73: =S73/$G73 -> 0 | U73: High | V73: Y | W73: N | X73: Rally TC
A74: Functional | B74: 58 | C74: Account referral | E74: Underwriting | F74: ALL | G74: 4 | K74: 2 | L74: ALL | M74: =COUNTIF('Account referral'!$G$23:$G1570,"N/A for Automation") -> 3 | N74: =M74/$G74 -> 0.75 | O74: =COUNTIF('Account referral'!$G$23:$G1570,"Automated") -> 1 | P74: =O74/$G74 -> 0.25 | Q74: =COUNTIF('Account referral'!$G$23:$G1570,"Partial Automated") -> 0 | R74: =Q74/G74 -> 0 | S74: =COUNTIF('Account referral'!$G$23:$G1570,"Not Automated") -> 0 | T74: =S74/$G74 -> 0 | U74: High | V74: N | W74: N
A75: Functional | B75: 59 | C75: Manually created tasks | E75: Underwriting | F75: ALL | G75: 21 | K75: 8 | L75: ALL | M75: =COUNTIF('Manually created tasks'!$G$23:$G1571,"N/A for Automation") -> 20 | N75: =M75/$G75 -> 0.95238095 | O75: =COUNTIF('Manually created tasks'!$G$23:$G1571,"Automated") -> 0 | P75: =O75/$G75 -> 0 | Q75: =COUNTIF('Manually created tasks'!$G$23:$G1571,"Partial Automated") -> 0 | R75: =Q75/G75 -> 0 | S75: =COUNTIF('Manually created tasks'!$G$23:$G1571,"Not Automated") -> 1 | T75: =S75/$G75 -> 0.047619048 | U75: High | V75: N | W75: N
A76: Functional | B76: 60 | C76: Collections Large Schedule | E76: Underwriting | F76: CO | G76: 27 | K76: 8 | L76: ALL | M76: =COUNTIF('Collections Large Schedule'!$G$23:$G1554,"N/A for Automation") -> 1 | N76: =M76/$G76 -> 0.037037037 | O76: =COUNTIF('Collections Large Schedule'!$G$23:$G1554,"Automated") -> 16 | P76: =O76/$G76 -> 0.59259259 | Q76: =COUNTIF('Collections Large Schedule'!$G$23:$G1554,"Partial Automated") -> 7 | R76: =Q76/G76 -> 0.25925926 | S76: =COUNTIF('Collections Large Schedule'!$G$23:$G1554,"Not Automated") -> 3 | T76: =S76/$G76 -> 0.11111111 | U76: High | V76: N | W76: N
A77: Functional | B77: 61 | C77: New User Creation | E77: Underwriting | F77: ALL | G77: 10 | K77: 1 | L77: ALL | M77: =COUNTIF('New User Creation'!$G$23:$G1573,"N/A for Automation") -> 10 | N77: =M77/$G77 -> 1 | O77: =COUNTIF('New User Creation'!$G$23:$G1573,"Automated") -> 0 | P77: =O77/$G77 -> 0 | Q77: =COUNTIF('New User Creation'!$G$23:$G1573,"Partial Automated") -> 0 | R77: =Q77/G77 -> 0 | S77: =COUNTIF('New User Creation'!$G$23:$G1573,"Not Automated") -> 0 | T77: =S77/$G77 -> 0 | U77: High | V77: N | W77: N
A78: Functional | B78: 62 | C78: New Agency Creation | E78: Underwriting | F78: ALL | G78: 20 | K78: 3 | L78: ALL | M78: =COUNTIF('New Agency Creation'!$G$23:$G1575,"N/A for Automation") -> 20 | N78: =M78/$G78 -> 1 | O78: =COUNTIF('New Agency Creation'!$G$23:$G1575,"Automated") -> 0 | P78: =O78/$G78 -> 0 | Q78: =COUNTIF('New Agency Creation'!$G$23:$G1575,"Partial Automated") -> 0 | R78: =Q78/G78 -> 0 | S78: =COUNTIF('New Agency Creation'!$G$23:$G1575,"Not Automated") -> 0 | T78: =S78/$G78 -> 0 | U78: High | V78: N | W78: N
A79: Integration | B79: 63 | C79: Okta | E79: Integration | F79: ALL | G79: 4 | K79: 1 | L79: ALL | M79: =COUNTIF(OKTA!$G$23:$G1541,"N/A for Automation") -> 0 | N79: =M79/$G79 -> 0 | O79: =COUNTIF(OKTA!$G$23:$G1541,"Automated") -> 0 | P79: =O79/$G79 -> 0 | Q79: =COUNTIF(OKTA!$G$23:$G1541,"Partial Automated") -> 0 | R79: =Q79/G79 -> 0 | S79: =COUNTIF(OKTA!$G$23:$G1541,"Not Automated") -> 4 | T79: =S79/$G79 -> 1 | U79: High | V79: N | W79: N
A80: Functional | B80: 64 | C80: Policies Main Flow | E80: Underwriting | F80: ALL | G80: 6 | L80: ALL | M80: =COUNTIF(PoliciesMainFlow!$G$23:$G1579,"N/A for Automation") -> 0 | N80: =M80/$G80 -> 0 | O80: =COUNTIF(PoliciesMainFlow!$G$23:$G1579,"Automated") -> 6 | P80: =O80/$G80 -> 1 | Q80: =COUNTIF(PoliciesMainFlow!$G$23:$G1579,"Partial Automated") -> 0 | R80: =Q80/G80 -> 0 | S80: =COUNTIF(PoliciesMainFlow!$G$23:$G1579,"Not Automated") -> 0 | T80: =S80/$G80 -> 0 | U80: High | V80: Y | W80: N | X80: Rally TC
A81: Functional | B81: 65 | C81: Customer Navigation | E81: Underwriting | F81: ALL | G81: 11 | K81: 2 | L81: ALL | M81: =COUNTIF(CustomersMainFlow!$G$23:$G1580,"N/A for Automation") -> 0 | N81: =M81/$G81 -> 0 | O81: =COUNTIF(CustomersMainFlow!$G$23:$G1580,"Automated") -> 2 | P81: =O81/$G81 -> 0.18181818 | Q81: =COUNTIF(CustomersMainFlow!$G$23:$G1580,"Partial Automated") -> 0 | R81: =Q81/G81 -> 0 | S81: =COUNTIF(CustomersMainFlow!$G$23:$G1580,"Not Automated") -> 9 | T81: =S81/$G81 -> 0.81818182 | U81: High | V81: N | W81: N
A82: Functional | B82: 66 | C82: Partner Navigation | E82: Underwriting | F82: ALL | G82: 8 | K82: 1 | L82: ALL | M82: =COUNTIF('Partner Navigation'!$G$23:$G1581,"N/A for Automation") -> 0 | N82: =M82/$G82 -> 0 | O82: =COUNTIF('Partner Navigation'!$G$23:$G1581,"Automated") -> 0 | P82: =O82/$G82 -> 0 | Q82: =COUNTIF('Partner Navigation'!$G$23:$G1581,"Partial Automated") -> 0 | R82: =Q82/G82 -> 0 | S82: =COUNTIF('Partner Navigation'!$G$23:$G1581,"Not Automated") -> 8 | T82: =S82/$G82 -> 1 | U82: High | V82: N | W82: N
A83: Functional | B83: 67 | C83: Large HH | E83: Performance | F83: ALL | G83: 10 | K83: 5 | L83: ALL | M83: =COUNTIF('Large HH'!$G$23:$G1583,"N/A for Automation") -> 10 | N83: =M83/$G83 -> 1 | O83: =COUNTIF('Large HH'!$G$23:$G1583,"Automated") -> 0 | P83: =O83/$G83 -> 0 | Q83: =COUNTIF('Large HH'!$G$23:$G1583,"Partial Automated") -> 0 | R83: =Q83/G83 -> 0 | S83: =COUNTIF('Large HH'!$G$23:$G1583,"Not Automated") -> 0 | T83: =S83/$G83 -> 0 | V83: N | W83: N
A84: Functional | B84: 68 | C84: HH Documents Upload | E84: Underwriting | F84: ALL | G84: 14 | H84: 6 | K84: 1 | L84: ALL | M84: =COUNTIF('HH Documents Upload'!$G$23:$G1584,"N/A for Automation") -> 7 | N84: =M84/$G84 -> 0.5 | O84: =COUNTIF('HH Documents Upload'!$G$23:$G1584,"Automated") -> 5 | P84: =O84/$G84 -> 0.35714286 | Q84: =COUNTIF('HH Documents Upload'!$G$23:$G1584,"Partial Automated") -> 1 | R84: =Q84/G84 -> 0.071428571 | S84: =COUNTIF('HH Documents Upload'!$G$23:$G1584,"Not Automated") -> 1 | T84: =S84/$G84 -> 0.071428571 | U84: High | V84: N | W84: N
A85: Functional | B85: 69 | C85: Transaction Types | D85: @Functional, @Transactions, @TransactionTypes, @Cancellation, @Rewrite, @NewBusinessRewrite, @END, @Endorsement, @NPBE, @PBE, @OOS | E85: Underwriting | F85: ALL | G85: 6 | K85: 2 | L85: ALL | M85: =COUNTIF(TransactionTypes!$G$23:$G1581,"N/A for Automation") -> 1 | N85: =M85/$G85 -> 0.16666667 | O85: =COUNTIF(TransactionTypes!$G$23:$G1581,"Automated") -> 5 | P85: =O85/$G85 -> 0.83333333 | Q85: =COUNTIF(TransactionTypes!$G$23:$G1581,"Partial Automated") -> 0 | R85: =Q85/G85 -> 0 | S85: =COUNTIF(TransactionTypes!$G$23:$G1581,"Not Automated") -> 0 | T85: =S85/$G85 -> 0 | U85: High | V85: N | W85: N | X85: Rally TC
A86: Functional | B86: 70 | C86: Renewals | E86: Underwriting | G86: 22 | K86: 10 | L86: ALL | M86: =COUNTIF(Renewals!$G$23:$G1587,"N/A for Automation") -> 2 | N86: =M86/$G86 -> 0.090909091 | O86: =COUNTIF(Renewals!$G$23:$G1587,"Automated") -> 0 | P86: =O86/$G86 -> 0 | Q86: =COUNTIF(Renewals!$G$23:$G1587,"Partial Automated") -> 4 | R86: =Q86/G86 -> 0.18181818 | S86: =COUNTIF(Renewals!$G$23:$G1587,"Not Automated") -> 16 | T86: =S86/$G86 -> 0.72727273 | U86: Critical | V86: N | W86: N
A87: Functional | B87: 71 | C87: Links | E87: Underwriting | G87: 1 | K87: 2 | L87: ALL | M87: =COUNTIF(Links!$G$23:$G33,"N/A for Automation") -> 1 | N87: =M87/$G87 -> 1 | O87: =COUNTIF(Links!$G$23:$G33,"Automated") -> 0 | P87: =O87/$G87 -> 0 | Q87: =COUNTIF(Links!$G$23:$G33,"Partial Automated") -> 0 | R87: =Q87/G87 -> 0 | S87: =COUNTIF(Links!$G$23:$G33,"Not Automated") -> 0 | T87: =S87/$G87 -> 0 | U87: Medium | V87: N | W87: N
A88: Functional | B88: 72 | C88: Validation Messages | D88: next/d | E88: Underwriting | F88: ALL | G88: 10 | K88: 2 | L88: ALL | M88: =COUNTIF('Validation messages'!$G$23:$G1592,"N/A for Automation") -> 0 | N88: =M88/$G88 -> 0 | O88: =COUNTIF('Validation messages'!$G$23:$G1592,"Automated") -> 0 | P88: =O88/$G88 -> 0 | Q88: =COUNTIF('Validation messages'!$G$23:$G1592,"Partial Automated") -> 0 | R88: =Q88/G88 -> 0 | S88: =COUNTIF('Validation messages'!$G$23:$G1592,"Not Automated") -> 8 | T88: =S88/$G88 -> 0.8 | U88: Medium | V88: N | W88: N
A89: Functional | B89: 73 | C89: User Setup | E89: Underwriting | F89: ALL | G89: 17 | K89: 2 | L89: ALL | M89: =COUNTIF('User Setup'!$G$23:$G1593,"N/A for Automation") -> 17 | N89: =M89/$G89 -> 1 | O89: =COUNTIF('User Setup'!$G$23:$G1593,"Automated") -> 0 | P89: =O89/$G89 -> 0 | Q89: =COUNTIF('User Setup'!$G$23:$G1593,"Partial Automated") -> 0 | R89: =Q89/G89 -> 0 | S89: =COUNTIF('User Setup'!$G$23:$G1593,"Not Automated") -> 0 | T89: =S89/$G89 -> 0 | U89: Medium | W89: N
A90: Functional | B90: 74 | C90: LLC/Trust | D90: next/d | E90: Underwriting | F90: ALL | G90: 16 | K90: 5 | L90: ALL | M90: =COUNTIF('LLC Trust'!$G$23:$G1431,"N/A for Automation") -> 0 | N90: =M90/$G90 -> 0 | O90: =COUNTIF('LLC Trust'!$G$23:$G1431,"Automated") -> 0 | P90: =O90/$G90 -> 0 | Q90: =COUNTIF('LLC Trust'!$G$23:$G1431,"Partial Automated") -> 0 | R90: =Q90/G90 -> 0 | S90: =COUNTIF('LLC Trust'!$G$23:$G1431,"Not Automated") -> 16 | T90: =S90/$G90 -> 1 | U90: High | V90: N | W90: N
A91: Functional | B91: 75 | C91: Existing Household navigation/updating | E91: Underwriting | G91: 7 | K91: 3 | L91: ALL | M91: =COUNTIF('Existing Household navigation'!$G$23:$G1596,"N/A for Automation") -> 6 | N91: =M91/$G91 -> 0.85714286 | O91: =COUNTIF('Existing Household navigation'!$G$23:$G1596,"Automated") -> 1 | P91: =O91/$G91 -> 0.14285714 | Q91: =COUNTIF('Existing Household navigation'!$G$23:$G1596,"Partial Automated") -> 0 | R91: =Q91/G91 -> 0 | S91: =COUNTIF('Existing Household navigation'!$G$23:$G1596,"Not Automated") -> 0 | T91: =S91/$G91 -> 0 | U91: Critical | V91: N | W91: N
A92: Functional | B92: 76 | C92: Transaction Behaviour - Adding/Deleting different number of objects (e.g.150 vehicles) | E92: Underwriting | F92: ALL | G92: 5 | K92: 14 | L92: ALL | M92: =COUNTIF('Transaction Behaviour'!$G$23:$G68,"N/A for Automation") -> 5 | N92: =M92/$G92 -> 1 | O92: =COUNTIF('Transaction Behaviour'!$G$23:$G68,"Automated") -> 0 | P92: =O92/$G92 -> 0 | Q92: =COUNTIF('Transaction Behaviour'!$G$23:$G68,"Partial Automated") -> 0 | R92: =Q92/G92 -> 0 | S92: =COUNTIF('Transaction Behaviour'!$G$23:$G68,"Not Automated") -> 0 | T92: =S92/$G92 -> 0 | U92: High | V92: N | W92: N
A93: Functional | B93: 77 | C93: Membership service | E93: Underwriting | F93: Admitted | G93: 10 | K93: 5 | L93: ALL | M93: =COUNTIF('Membership service'!$G$23:$G1605,"N/A for Automation") -> 9 | N93: =M93/$G93 -> 0.9 | O93: =COUNTIF('Membership service'!$G$23:$G1605,"Automated") -> 0 | P93: =O93/$G93 -> 0 | Q93: =COUNTIF('Membership service'!$G$23:$G1605,"Partial Automated") -> 1 | R93: =Q93/G93 -> 0.1 | S93: =COUNTIF('Membership service'!$G$23:$G1605,"Not Automated") -> 0 | T93: =S93/$G93 -> 0 | U93: High | V93: N | W93: N
A94: Functional | B94: 78 | C94: PSE Membership | E94: Underwriting | F94: Surplus | G94: 4 | K94: 2 | L94: ALL | M94: =COUNTIF('PSE Membership'!$G$23:$G1599,"N/A for Automation") -> 0 | N94: =M94/$G94 -> 0 | O94: =COUNTIF('PSE Membership'!$G$23:$G1599,"Automated") -> 0 | P94: =O94/$G94 -> 0 | Q94: =COUNTIF('PSE Membership'!$G$23:$G1599,"Partial Automated") -> 1 | R94: =Q94/G94 -> 0.25 | S94: =COUNTIF('PSE Membership'!$G$23:$G1599,"Not Automated") -> 3 | T94: =S94/$G94 -> 0.75 | U94: Medium | V94: N | W94: N
A95: Functional | B95: 79 | C95: Pop up window | E95: Underwriting | F95: ALL | G95: 4 | K95: 2 | L95: ALL | M95: =COUNTIF('Pop-up window'!$G$23:$G1600,"N/A for Automation") -> 4 | N95: =M95/$G95 -> 1 | O95: =COUNTIF('Pop-up window'!$G$23:$G1600,"Automated") -> 0 | P95: =O95/$G95 -> 0 | Q95: =COUNTIF('Pop-up window'!$G$23:$G1600,"Partial Automated") -> 0 | R95: =Q95/G95 -> 0 | S95: =COUNTIF('Pop-up window'!$G$23:$G1600,"Not Automated") -> 0 | T95: =S95/$G95 -> 0 | U95: Medium | V95: N | W95: N
A96: Functional | B96: 80 | C96: Additional Interests/Insured - Forms - Additional Packages | D96: next/d | E96: Underwriting | F96: ALL | G96: 102 | K96: 10 | L96: ALL | M96: =COUNTIF('Additional Interest-Insured'!$G$23:$G1599,"N/A for Automation") -> 0 | N96: =M96/$G96 -> 0 | O96: =COUNTIF('Additional Interest-Insured'!$G$21:$G1499,"Automated") -> 99 | P96: =O96/$G96 -> 0.97058824 | Q96: =COUNTIF('Additional Interest-Insured'!$G$22:$G1499,"Partial Automated") -> 0 | R96: =Q96/G96 -> 0 | S96: =COUNTIF('Additional Interest-Insured'!$G$22:$G1499,"Not Automated") -> 3 | T96: =S96/$G96 -> 0.029411765 | U96: Medium | V96: N | W96: N
A97: Functional | B97: 81 | C97: Incidents, mapping to other LOBs and YCD | E97: Product | G97: 8 | K97: 25 | L97: ALL | M97: =COUNTIF('Incidents, mapping to other LOB'!$G$23:$G1062,"N/A for Automation") -> 4 | N97: =M97/$G97 -> 0.5 | O97: =COUNTIF('Incidents, mapping to other LOB'!$G$23:$G1062,"Automated") -> 0 | P97: =O97/$G97 -> 0 | Q97: =COUNTIF('Incidents, mapping to other LOB'!$G$23:$G1062,"Partial Automated") -> 0 | R97: =Q97/G97 -> 0 | S97: =COUNTIF('Incidents, mapping to other LOB'!$G$23:$G1062,"Not Automated") -> 4 | T97: =S97/$G97 -> 0.5 | U97: Critical | V97: N | W97: N
A98: Functional | B98: 82 | C98: Collections | E98: Product | G98: 17 | K98: 10 | L98: ALL | M98: =COUNTIF(Collections!$G$23:$G1551,"N/A for Automation") -> 4 | N98: =M98/$G98 -> 0.23529412 | O98: =COUNTIF(Collections!$G$23:$G1551,"Automated") -> 4 | P98: =O98/$G98 -> 0.23529412 | Q98: =COUNTIF(Collections!$G$23:$G1551,"Partial Automated") -> 3 | R98: =Q98/G98 -> 0.17647059 | S98: =COUNTIF(Collections!$G$23:$G1551,"Not Automated") -> 6 | T98: =S98/$G98 -> 0.35294118 | U98: High | W98: N
A99: Functional | B99: 83 | C99: Auto - (TCs: All Vehicle Types, All Operator Types) | D99: next/d | E99: Product | F99: PA | G99: 4 | K99: 25 | L99: ALL | M99: =COUNTIF('Auto - TC with all inc and veh'!$G$23:$G119,"N/A for Automation") -> 0 | N99: =M99/$G99 -> 0 | O99: =COUNTIF('Auto - TC with all inc and veh'!$G$23:$G119,"Automated") -> 1 | P99: =O99/$G99 -> 0.25 | Q99: =COUNTIF('Auto - TC with all inc and veh'!$G$23:$G119,"Partial Automated") -> 0 | R99: =Q99/G99 -> 0 | S99: =COUNTIF('Auto - TC with all inc and veh'!$G$23:$G119,"Not Automated") -> 3 | T99: =S99/$G99 -> 0.75 | U99: High | V99: N | W99: N | X99: Rally TC
A100: Functional | B100: 84 | C100: LOB Dependencies | E100: Product | G100: 13 | K100: 20 | L100: ALL | M100: =COUNTIF('LOB Dependencies'!$G$23:$G1526,"N/A for Automation") -> 8 | N100: =M100/$G100 -> 0.61538462 | O100: =COUNTIF('LOB Dependencies'!$G$23:$G1526,"Automated") -> 0 | P100: =O100/$G100 -> 0 | Q100: =COUNTIF('LOB Dependencies'!$G$23:$G1526,"Partial Automated") -> 0 | R100: =Q100/G100 -> 0 | S100: =COUNTIF('LOB Dependencies'!$G$23:$G1526,"Not Automated") -> 5 | T100: =S100/$G100 -> 0.38461538 | U100: High | V100: N | W100: N
A101: Functional | B101: 85 | C101: Out Of Sequence Transaction | E101: Product | F101: ALL | G101: 13 | K101: 10 | L101: ALL | M101: =COUNTIF('Out Of Sequence Transaction'!$G$23:$G1605,"N/A for Automation") -> 4 | N101: =M101/$G101 -> 0.30769231 | O101: =COUNTIF('Out Of Sequence Transaction'!$G$23:$G1605,"Automated") -> 0 | P101: =O101/$G101 -> 0 | Q101: =COUNTIF('Out Of Sequence Transaction'!$G$23:$G1605,"Partial Automated") -> 5 | R101: =Q101/G101 -> 0.38461538 | S101: =COUNTIF('Out Of Sequence Transaction'!$G$23:$G1605,"Not Automated") -> 4 | T101: =S101/$G101 -> 0.30769231 | U101: Critical | V101: N | W101: N
A102: Functional | B102: 86 | C102: Years Clean Discount | E102: Functional | F102: ALL | G102: 5 | K102: 10 | L102: ALL | M102: =COUNTIF('Years Clean Discount'!$G$23:$G1551,"N/A for Automation") -> 0 | N102: =M102/$G102 -> 0 | O102: =COUNTIF('Years Clean Discount'!$G$23:$G1551,"Automated") -> 0 | P102: =O102/$G102 -> 0 | Q102: =COUNTIF('Years Clean Discount'!$G$23:$G1551,"Partial Automated") -> 3 | R102: =Q102/G102 -> 0.6 | S102: =COUNTIF('Years Clean Discount'!$G$23:$G1551,"Not Automated") -> 2 | T102: =S102/$G102 -> 0.4 | U102: High | V102: Y | W102: N
A103: Integration | B103: 87 | C103: Loss control 360 | E103: Integration | F103: HO | G103: 15 | K103: 5 | L103: STG | M103: =COUNTIF('LC360'!$G$23:$G1552,"N/A for Automation") -> 0 | N103: =M103/$G103 -> 0 | O103: =COUNTIF('LC360'!$G$23:$G1552,"Automated") -> 1 | P103: =O103/$G103 -> 0.066666667 | Q103: =COUNTIF('LC360'!$G$23:$G1552,"Partial Automated") -> 0 | R103: =Q103/G103 -> 0 | S103: =COUNTIF('LC360'!$G$23:$G1552,"Not Automated") -> 14 | T103: =S103/$G103 -> 0.93333333 | U103: High | V103: N | W103: N
...

Sheet Aggregation zone HS
A1: Back to Summary
A2: Aggregation zone HS
A3: STG Environment
A4: Objective: | B4: 1 | C4: Validate Aggregation zone HS functionality.
A6: Data: | B6: 1 | C6: Role: Underwriter Agent Broker Number: User: Password:
B7: 2
B8: 3
A10: Preconditions: | B10: 1 | C10: Access to the application
B11: 2
B12: 3
B13: 4
A15: Status: | B15: N | C15: = Not executed by QA
B16: P | C16: = Passed by QA
B17: F | C17: = Failed by QA
B18: T | C18: = Testing in progress
B19: R | C19: = Rejected / Existing issue
B20: B | C20: = Blocked by QA
A22: Description | B22: # | C22: Steps | D22: Expected Results | E22: Status | F22: Automation status | G22: Comments | H22: Defect ID /Blocked reason
A24: Test Case # 1 Aggregation zone HS | B24: 1 | C24: Enter to Dragon as an underwriter. | D24: User login should be successful and able to navigate to the agg management page to perform the steps mentiond in the test case | E24: N | F24: N/A | G24: N/A for Automation
B25: 2 | C25: From the Home screen navigate to the Aggregate Management page
B26: 3 | C26: On the Aggregate Management page visit the block named - 'lob to open/close or edit'
B27: 4 | C27: From the cell 'Please Select LOB to block for selected counties' select HS/ES LOB, and from the cell 'Select coverage options' select coverage
B28: 5 | C28: Verify that the values for updated aggregation zones are editable by UW mngr.
A30: Test Case # 2 Open/Close Agg Zones | B30: 1 | C30: Enter to Dragon as an underwriter. | D30: User login should be successful and able to navigate to the agg management page to perform the steps mentiond in the test case | E30: N | F30: N/A | G30: N/A for Automation
B31: 2 | C31: From the Home screen navigate to the Aggregate Management page
B32: 3 | C32: On the Aggregate Management page visit the block named - 'lob to open/close or edit'
B33: 4 | C33: From the cell 'Please Select LOB to block for selected counties' select HS/ES LOB, and from the cell 'Select coverage options' select coverage
B34: 5 | C34: From the new block which will appear as 'counties to block or release' check the radio button for the Carrer/State/Zone which you want to open/close
B35: 6 | C35: To open a closed zone Click on 'open agg zone' button
B36: 7 | C36: To close an open zone Click on 'close agg zone' button
B37: 8 | C37: Verify that the updated aggregation zones are displaying under aggregation mngmt as per specs.

Sheet Browser testing
A1: Back to Summary
A2: Browser testing
A3: STG Environment
A4: Objective: | B4: 1 | C4: Validate Browser testing functionality.
A6: Data: | B6: 1 | C6: Role: Underwriter Agent Broker Number: User: Password:
B7: 2
B8: 3
A10: Preconditions: | B10: 1 | C10: Access to the external and internal users
B11: 2 | C11: Access to process the transaction
B12: 3
B13: 4
A15: Status: | B15: N | C15: = Not executed by QA
B16: P | C16: = Passed by QA
B17: F | C17: = Failed by QA
B18: T | C18: = Testing in progress
B19: R | C19: = Rejected / Existing issue
B20: B | C20: = Blocked by QA
A22: Description | B22: # | C22: Steps | D22: Expected Results | E22: Status | F22: Automation status | G22: Comments | H22: Defect ID /Blocked reason
A24: Test Case # 1 Verify that a user is not able to use duplicate feature in Chrome and have multiple tabs running the same User Session ID | B24: 1 | C24: Log into Dragon application in Chrome browser with one User Session | E24: N | F24: N/A | G24: N/A for Automation
B25: 2 | C25: In same Chrome browser open second tab with Dragon application with a new User Session
B26: 3 | C26: Navigate back to the first User Session and try to navigate through the User Interface | D26: User is not able to navigate - Session Expired
B27: 4 | C27: Compare User Session one and User Session two | D27: User Session IDs should be different
B28: 5 | C28: Verify that a user is not able to use duplicate feature in Chrome and have multiple tabs running the same User Session ID | D28: Verify that a user is not able to use duplicate feature in Chrome and have multiple tabs running the same User Session ID
A30: Test Case # 2 Verify that when a second Chrome tab of Dragon Environment is opened copy-pasting the link from the previous tab, an error message will be shown | B30: 1 | C30: Log into Dragon application in Chrome browser with one User Session | E30: N | F30: N/A | G30: N/A for Automation
B31: 2 | C31: In same Chrome browser open second tab with Dragon application with a new User Session
B32: 3 | C32: Navigate back to the first User Session and try to navigate through the User Interface | D32: User is not able to navigate - Session Expired
B33: 4 | C33: Verify that when a second Chrome tab of Dragon Environment is opened, old session will Time out | D33: Verify that when a second Chrome tab of Dragon Environment is opened, old session will Time out
A35: Test Case # 3 Verify that the user is not able to use "Back" button for navigating through Dragon Application | B35: 1 | C35: Log into Dragon application | E35: N | F35: N/A | G35: N/A for Automation
B36: 2 | C36: Navigate to Policies tab
B37: 3 | C37: Using Policy Hyperlink navigate to the Policy
B38: 4 | C38: Navigate to the Transactions/Endorsements tab
B39: 5 | C39: Open NB transaction
B40: 6 | C40: Click on "Back" button in Chrome if available | D40: "Back" Button should not be available -User is not able to navigate back using "Back" button
B41: 7 | C41: Verify that the user cannot use "Back" button for navigating through Dragon Application | D41: User is not able to use "Back" button for navigating through Dragon Application
A43: Test Case # 4 Verify exiting the environment when user is on any page different then Home page | B43: 1 | C43: Log into Dragon application | E43: N | F43: N/A | G43: N/A for Automation
B44: 2 | C44: Navigate to Policies tab
B45: 3 | C45: Exit the environment using "x" for closing the browser window
B46: 4 | C46: "Leave site?" message shown???/Window closed without messages??? | D46: Custom message showld be shown (waiting for expected result from PURE)
B47: 5
B48: 6
B49: 7
A51: Test Case # 5 Verify that Duplicate tab error will be shown to the user and page load will be aborted when the user uses Right-click, and 'Duplicate' option to launch a new tab | B51: 1 | C51: Launch the application window | E51: N | F51: N/A | G51: N/A for Automation
B52: 2 | C52: Right-click, and use the 'Duplicate' option to launch a new tab
B53: 3 | C53: Verify that a duplicate tab error is shown | D53: Duplicate tab error was shown to the user and page load was aborted.
A55: Test Case # 6 Verify that popup windows are rendering fine | B55: 1 | C55: Launch the application window | E55: N | F55: N/A | G55: N/A for Automation
B56: 2 | C56: Navigate to the pages that has popup window option
B57: 3 | C57: Open popup windows from different places
B58: 4 | C58: Verify that no errors are seen | D58: Popup windows rendered fine
A60: Test Case # 7 Verify that a user is able to open a new tab using Right-click on the Action hyperlink and selecting 'Open in New Tab', with the new session | B60: 1 | C60: Launch the application window | E60: N | F60: N/A | G60: N/A for Automation
B61: 2 | C61: Right-click on the Action hyperlink
B62: 3 | C62: Select 'Open in New Tab'
B63: 4 | C63: Verify that the new tab renders fine | D63: Application page was rendered in a new tab.
A65: Test Case # 8 Verify that the 'Leave Site?' javascript popup prompt is not displayed, and the timeout page is loaded and displayed when the timeout has expired. | B65: 1 | C65: Log into Dragon application | E65: N | F65: N/A | G65: N/A for Automation
B67: 2 | C67: Wait until the time-out message is diplayed
B69: 3 | C69: Wait until the remaining timeout has expired
B71: 4 | C71: Verify that the 'Leave Site?' javascript popup prompt is not displayed, and the timeout page is loaded and displayed when the timeout has expired. | D71: The 'Leave Site?' javascript popup prompt is not displayed, and the timeout page is loaded and displayed
A73: Test Case # 9 Verify that the popup message: 'You have unsaved changes on the page...' is displayed when the user clicks on the browser 'reload' button | B73: 1 | C73: Log into Dragon application | E73: N | F73: N/A | G73: N/A for Automation
B74: 2 | C74: Clicks on the browser 'reload' button
B75: 3 | C75: Verify that the popup message: 'You have unsaved changes on the page...' is displayed when the user clicks on the browser 'reload' button | D75: The popup message: 'You have unsaved changes on the page...' is displayed
A77: Test Case # 10 Verify that the popup message: 'You have unsaved changes on the page...' is displayed when the user is in quote creation process, before saving the quote form | B77: 1 | C77: Log into Dragon application | E77: N | F77: N/A | G77: N/A for Automation
B78: 2 | C78: Create a new quote
B79: 3 | C79: Clicks on the browser 'reload' button before saving the quote form
B80: 4 | C80: Verify that the popup message: 'You have unsaved changes on the page...' is displayed whenthe user is in quote creation process, before saving the quote form | D80: Verify that the popup message: 'You have unsaved changes on the page...' is displayed
A82: Test Case # 11 Verify that the popup message: 'You have unsaved changes on the page...' is not displayed when the timeout has expired and user clicks on the browser 'reload' button. | B82: 1 | C82: Log into Dragon application | E82: N | F82: N/A | G82: N/A for Automation
B83: 2 | C83: Wait until the time-out message is diplayed
B84: 3 | C84: Wait until the remaining timeout has expired
B85: 4 | C85: Click on the browser 'reload' button
B86: 5 | C86: Verify that the popup message: 'You have unsaved changes on the page...' is not displayed when the timeout has expired and user clicks on the browser 'reload' button. | D86: Verify that the popup message: 'You have unsaved changes on the page...' is not displayed
A88: Test Case # 12 Verify that user is able to open multiple environments at the same time, all with unique Session IDs | B88: 1 | C88: Log in to Okta | E88: N | F88: N/A | G88: N/A for Automation
B89: 2 | C89: Open multiple Dragon environment using a tile
B90: 3 | C90: Verify that multiple Dragon environments are opened with unique Session IDs | D90: Multiple Dragon environments are opened with unique Session IDs
A92: Test Case # 13 Verify that if the user closes one tab and opens another, again new session should be used - always a new session | B92: 1 | C92: Log in to Okta | E92: N | F92: N/A | G92: N/A for Automation
B93: 2 | C93: Open multiple Dragon environment using a tile
B94: 3 | C94: Close one tab
B95: 4 | C95: Open one more Dragon environment using a tile
B96: 5 | C96: Verify that if the user closes one tab and opens another, again new session should be used - always a new session | D96: If the user closes one tab and opens another, again new session should be used - always a new session
A98: Test Case # 14 Verify that when a tab is duplicated, a new tab is opened in a new session and those sessions cannot create same double transaction | B98: 1 | C98: Log in to Okta | E98: N | F98: N/A | G98: N/A for Automation
B99: 2 | C99: Open multiple Dragon environment using a tile
B100: 3 | C100: Verify that User session ID is unique for each tab
B101: 4 | C101: Open an existing Policy in both tabs
B102: 5 | C102: Create an Endorsement in both tabs, click Next and verify that double trx can not be created
A104: Test Case # 15 Verify that all above test cases are applicable to all other browsers except Chrome | B104: 1 | E104: N | F104: N/A | G104: N/A for Automation
B105: 2
B106: 3
B107: 4
B108: 5

Sheet BSE
A1: Back to Summary
A2: BSE Broker Self Service Endorsement
A3: STG Environment
A4: Objective: | B4: 1 | C4: Validate Dragon´s BSE functionality. Try different Lines of Bussines and different referrals
A6: Data: | B6: 1 | C6: Role: Underwriter Agent Broker Number: User: Password:
B7: 2
B8: 3
A10: Preconditions: | B10: 1 | C10: Access to the external and internal users
B11: 2 | C11: Access to process the transaction
B12: 3
B13: 4
A15: Status: | B15: N | C15: = Not executed by QA
B16: P | C16: = Passed by QA
B17: F | C17: = Failed by QA
B18: T | C18: = Testing in progress
B19: R | C19: = Rejected / Existing issue
B20: B | C20: = Blocked by QA
A22: Description | B22: # | C22: Steps | D22: Expected Results | E22: Status | F22: Automation status | G22: Comments | H22: Defect ID /Blocked reason
A24: Test Case # 1 Verify that Agent is able to Create and Process an Endorsement transaction with no referrals triggered | B24: 1 | C24: Log into Dragon as a broker | D24: Agent is able to Create and Process an Endorsement transaction with no referrals triggered | E24: N | F24: N | G24: Not Automated
B25: 2 | C25: Navigate to the existing HO policy
B26: 3 | C26: Create an Endorsement transaction
B27: 4 | C27: Do not change any data - Rate and Issue
B28: 5 | C28: Verify that Agent is able to Create and Process an Endorsement transaction with no referrals triggered
A30: Test Case # 2 Verify that Agent is able to create an OOS Endorsement transaction | B30: 1 | C30: Log into Dragon as a broker | E30: N | F30: N | G30: Not Automated
B31: 2 | C31: Navigate to the exiting PA policy
B32: 3 | C32: Create an OOS Endorsement transaction
B33: 4 | C33: Do not change any data
B34: 5 | C34: Rate the transaction | D34: An OOS referral is triggered
B35: 6 | C35: Verify that Agent is able to create an OOS Endorsement transaction | D35: Agent is able to create an OOS Endorsement transaction
A37: Test Case # 3 Verify that Agent is not able to process an OOS transaction | B37: 1 | C37: Log into Dragon as a broker | D37: Agent is not able to process an OOS transaction | E37: N | F37: N | G37: Not Automated
B38: 2 | C38: Navigate to the exiting PA policy
B39: 3 | C39: Create an OOS Endorsement transaction
B40: 4 | C40: Do not change any data
B41: 5 | C41: Rate the transaction
B42: 6 | C42: Verify that Agent is not able to process an OOS transaction
A44: Test Case # 4 Verify that Agent is not able to process an Endorsement transaction if one or more referrals are triggered | B44: 1 | C44: Log into Dragon as a broker | D44: Verify that Agent is not able to process an Endorsement transaction if one or more referrals are triggered | E44: N | F44: N | G44: Not Automated
B45: 2 | C45: Navigate to the exiting HO policy
B46: 3 | C46: Create an Endorsement transaction
B47: 4 | C47: Change the TIV value to over $50 milion
B48: 5 | C48: Rate the transaction
B49: 6 | C49: Verify that Agent is not able to process an Endorsement transaction if one or more referrals are triggered
A51: Test Case # 5 Verify that Agent is able to see Subjectivities page | B51: 1 | C51: Log into Dragon as a broker | D51: Advisory is triggered: The addition of scheduled fine art item(s) valued at more than $250K and non-fine art item(s) valued at more than $100K requires receipt of an appraisal or bill of sale. Please upload documentation on the Subjectivity page. Verify that broker is able to see the Subjectivity page containing following - Subjectivity document name: Bill of Sale/Appraisal – Collection | E51: N | F51: N | G51: Not Automated
B52: 2 | C52: Navigate to the exiting CO policy
B53: 3 | C53: Create an Endorsement transaction
B54: 4 | C54: Add a Fine Arts item with a value > $250.000
B55: 5 | C55: Click save changes/Navigate to any other page
B56: 6 | C56: Verify that Agent is able to see Subjectivities page
A58: Test Case # 6 Verify that Agent is able to sucessfully upload documents into Subjectivities page and associate them with Subjectivities triggered | B58: 1 | C58: Log into Dragon as a broker | E58: N | F58: N | G58: Not Automated
B59: 2 | C59: Navigate to the exiting CO policy
B60: 3 | C60: Create an Endorsement transaction
B61: 4 | C61: Add a Fine Arts item with a value > $250.000
B62: 5 | C62: Click save changes/Navigate to any other page | D62: Advisory triggered: The addition of scheduled fine art item(s) valued at more than $250K and non-fine art item(s) valued at more than $100K requires receipt of an appraisal or bill of sale. Please upload documentation on the Subjectivity page. Subjectivity page appeared containing following: Subjectivity document name: Bill of Sale/Appraisal – Collection
B63: 6 | C63: Navigate to the Subjectivity page
B64: 7 | C64: Upload the documents
B65: 8 | C65: Click save changes
B66: 9 | C66: Upload the documents
B67: 10 | C67: Verify that Agent is able to sucessfully upload documents into Subjectivities page and associate them with Subjectivities triggered | D67: Verify that Agent is able to sucessfully upload documents into Subjectivities page and associate them with Subjectivities triggered
A69: Test Case # 7 Verify that internal user is able to see Subjectivities page | B69: 1 | C69: Log into Dragon as an internal user | E69: N | F69: N | G69: Not Automated
B70: 2 | C70: Navigate to the exiting CO policy
B71: 3 | C71: Create an Endorsement transaction
B72: 4 | C72: Add a Fine Arts item with a value > $250.000
B73: 5 | C73: Click save changes/Navigate to any other page | D73: Advisory triggered: The addition of scheduled fine art item(s) valued at more than $250K and non-fine art item(s) valued at more than $100K requires receipt of an appraisal or bill of sale. Please upload documentation on the Subjectivity page. Subjectivity page appeared containing following: Subjectivity document name: Bill of Sale/Appraisal – Collection
B74: 6 | C74: Navigate to the Subjectivity page
B75: 7 | C75: Verify that internal user is able to see Subjectivities page | D75: Verify that internal user is able to see Subjectivities page
A77: Test Case # 8 Verify that inernal user is able to sucessfully upload documents into Subjectivities page and associate them with Subjectivities triggered | B77: 1 | C77: Log into Dragon as an internal user | E77: N | F77: N | G77: Not Automated
B78: 2 | C78: Navigate to the exiting CO policy
B79: 3 | C79: Create an Endorsement transaction
B80: 4 | C80: Add a Fine Arts item with a value > $250.000
B81: 5 | C81: Click save changes/Navigate to any other page | D81: Advisory triggered: The addition of scheduled fine art item(s) valued at more than $250K and non-fine art item(s) valued at more than $100K requires receipt of an appraisal or bill of sale. Please upload documentation on the Subjectivity page. Subjectivity page appeared containing following: Subjectivity document name: Bill of Sale/Appraisal – Collection
B82: 6 | C82: Navigate to the Subjectivity page
B83: 7 | C83: Upload the documents
B84: 8 | C84: Click save changes
B85: 9 | C85: Upload the documents
B86: 10 | C86: Verify that Internal user is able to sucessfully upload documents into Subjectivities page and associate them with Subjectivities triggered | D86: Verify that Internal user is able to sucessfully upload documents into Subjectivities page and associate them with Subjectivities triggered
A88: Test Case # 9 Verify that Subjectivity Page will be visible only when a Subjectivity has been triggered | B88: 1 | C88: Log into Dragon application | D88: Verify that Subjectivity Page will be visible only when a Subjectivity has been triggered | E88: N | F88: N | G88: Not Automated
B89: 2 | C89: Navigate to the existing PA policy
B90: 3 | C90: Create an Endorsement transaction
B91: 4 | C91: Increase the value of the vehicle for 50%
B92: 5 | C92: Click Save changes
B93: 6 | C93: Verify that Subjectivity Page will be visible only when a Subjectivity has been triggered
A95: Test Case # 10 Verify that a user is not able to process the Endorsement transaction if one or more Subjectivities are not satisfied | B95: 1 | C95: Log into Dragon application | D95: Verify that a user is not able to process the Endorsement transaction if one or more Subjectivities are not satisfied | E95: N | F95: Y | G95: Automated
B96: 2 | C96: Navigate to the existing PA policy
B97: 3 | C97: Create an Endorsement transaction
B98: 4 | C98: Increase the value of the vehicle for 50%
B99: 5 | C99: Rate the Endorsement without satisfying Subjectivity triggered
B100: 6 | C100: Verify that a user is not able to process the Endorsement transaction if one or more Subjectivities are not satisfied
A102: Test Case # 11 Verify that user will be able to process the Endorsement transaction if all of the Subjectivities triggered are satisfied | B102: 1 | C102: Log into Dragon application | D102: Verify that user will be able to process the Endorsement transaction if all of the Subjectivities triggered are satisfied | E102: N | F102: N | G102: Not Automated
B103: 2 | C103: Navigate to the existing PA policy
B104: 3 | C104: Create an Endorsement transaction
B105: 4 | C105: Increase the value of the vehicle for 50%
B106: 5 | C106: Navigate to the Subjectivities page
B107: 6 | C107: Satisfy Subjectivities triggered
B108: 7 | C108: Rate the Endorsement
B109: 8 | C109: Verify that user will be able to process the Endorsement transaction if all of the Subjectivities triggered are satisfied
A111: Test Case # 12 Verify that when Subjectivity page becomes visible, there will be Advisory message noting that the Subjectivity needs to be fullfilled based on the user's selection on the transaction | B111: 1 | C111: Log into Dragon application | E111: N | F111: N | G111: Not Automated
B112: 2 | C112: Navigate to the existing PA policy
B113: 3 | C113: Create an Endorsement transaction
B114: 4 | C114: Add a new vehicle with Agreed Value/Market value = $0
B115: 5 | C115: Click Save changes | D115: Verify that Advisory message is triggered: This change in value requires supporting documentation. Please upload bill of sale or appraisal to support the requested agreed value on the subjectivities page.
B116: 6 | C116: Navigate to the Subjectivity page
...

Sheet Tasks & Emails
A1: Back to Summary
A2: Tasks and Emails
A3: STG Environment
A4: Objective: | B4: 1 | C4: Validate Dragon´s tasks and emails. Try different tasks and emails
A6: Data: | B6: 1 | C6: Access to test Environment
B7: 2
B8: 3
A10: Preconditions: | B10: 1
B11: 2
B12: 3
B13: 4
A15: Status: | B15: N | C15: = Not executed by QA
B16: P | C16: = Passed by QA
B17: F | C17: = Failed by QA
B18: T | C18: = Testing in progress
B19: R | C19: = Rejected / Existing issue
B20: B | C20: = Blocked by QA
A22: Description | B22: # | C22: Steps | D22: Expected Results | E22: Status | F22: Automation status | G22: Comments | H22: Defect ID /Blocked reason
A24: Test Case # 1 Verify Renewal Review Required task is created and email sent to assigned user | B24: 1 | C24: Enter to Dragon as an underwriter. | D24: Tasks and emails should be generated. | E24: N | F24: N/A | G24: N/A for Automation
B25: 2 | C25: Create/Find a HO and CO policy (any state).
B26: 3 | C26: Create Auto Renewal
B27: 4 | C27: Verify that user is able to see renewal created with status Required Review.
B28: 5 | C28: Verify that task is generated and emails sent.
A30: Test Case # 2 Verify tasks and emails are getting created when referrals are fired | B30: 1 | C30: Login as an Agent | D30: Tasks and emails should be generated. | E30: N | F30: N/A | G30: N/A for Automation
B31: 2 | C31: Create/Find a HO and CO policy (any state).
B32: 3 | C32: Create an Endorsement.
B33: 4 | C33: Do any change not allowed for Agent. (e.g. Add an Additional Insured)
B34: 5 | C34: Navigate to the additional insured/interest page.
B35: 6 | C35: Add an "Additional Insured"
B36: 7 | C36: Do not make any other changes on the Endt.
B37: 8 | C37: Click on "review changes" button.
B38: 9 | C38: Review the changes that were just made.
B39: 10 | C39: Click on ">>>rate" button.
B40: 11 | C40: Review the premium on the modified premium page.
B41: 12 | C41: Verify that ">>> submit for review" button is enabled.
B42: 13 | C42: Click on ">>> submit for review" button.
... B65: 36 | C65: Verify that every time when user is clicking Submit button, new task and emails are generated.
A67: Test Case # 3 Verify that tasks and emails are getting created when referrals are triggered on all Post NB transaction | B67: 1 | C67: Navigate to the record from the Test Case 3. | E67: N | F67: N/A | G67: N/A for Automation
B68: 2 | C68: Create END and change the Named Insured fields and values and rate the transaction.
B69: 3 | C69: Navigate to the UW screen and verify that new referral has been triggered.
B70: 4 | C70: Verify that task and emails are getting creted and set to correct users.
B71: 5 | C71: Approve the referral triggered and issue END trx.
B72: 6 | C72: Create manual Renewal transaction.
B73: 7 | C73: Trigger the F grade and rate the Renewal.
B74: 8 | C74: Navigate to the UW screen and verify that new referral has been triggered.
B75: 9 | C75: Approve the referral triggered and issue Renewal trx.
B76: 10 | C76: Verify that task and emails are getting creted and sent to correct users. | D76: Tasks and emails should be generated and sent to users.
A78: Test Case # 4 Verify that referrals are not triggered on Cancellation trx and that email is set out to notify user that policy was cancelled | B78: 1 | C78: Navigate to existing HH and its policy. | E78: N | F78: N | G78: Not Automated
B79: 2 | C79: Navigate to Transaction list screen and click button New.
B80: 3 | C80: From the Transaction Type select value Cancellation.
B81: 4 | C81: Select requested by Company.
B82: 5 | C82: Click on button Next.
B83: 6 | C83: Verify that user do not have ability to see UW screen under Cancellation trs.
B84: 7 | C84: Issue Cancellation.
B85: 8 | C85: Verify that correct user have received the email that is system generated every time when policy is cancelled. | D85: Correct user is getting emails generated.
A87: Test Case # 5 Verify that referrals are not triggered on ITNR trx and not emails and tasks are generated | B87: 1 | C87: Navigate to existing HH and its policy. | E87: N | F87: N | G87: Not Automated
B88: 2 | C88: Navigate to Transaction list screen and click button New.
B89: 3 | C89: From the Transaction Type select value ITNR.
B90: 4 | C90: Populate all the mandatory fields and click on button Next.
B91: 5 | C91: Verify that ITNR trx will be processed and there will be no UW screen nor data for this type of trx.
B92: 6 | C92: Verify that after ITNR is issued, system is not generating task and emails | D92: No tasks and emails are generated.
A94: Test Case # 6 Verify that every time when policy expires, email and task are getting created | B94: 1 | C94: Navigate to the Policy tab and find the policy with EFF date that is almost 1year from today. | E94: N | F94: N/A | G94: N/A for Automation
B95: 2 | C95: Verify that on this policy all the transactions are issued and there has been no ITNR create.
B96: 3 | C96: Track the policy in question.
B97: 4 | C97: After the policy expires, system should generate task and email. | D97: Tasks and emails are generated.

Sheet BOR
A1: Back to Summary
A2: BOR
A3: STG Environment
A4: Objective: | B4: 1 | C4: Validate BOR Process
A6: Data: | B6: 1 | C6: Access to test Environment
B7: 2
B8: 3
A10: Preconditions: | B10: 1
B11: 2
B12: 3
B13: 4
A15: Status: | B15: N | C15: = Not executed by QA
B16: P | C16: = Passed by QA
B17: F | C17: = Failed by QA
B18: T | C18: = Testing in progress
B19: R | C19: = Rejected / Existing issue
B20: B | C20: = Blocked by QA
A22: Description | B22: # | C22: Steps | D22: Expected Results | E22: Status | F22: Automation status | G22: Comments | H22: Defect ID /Blocked reason
A24: Test Case # 1 Log in to Dragon as an Agent | B24: 1 | C24: Enter to Dragon as an agent. | D24: Agent is not able to see Partners page | E24: N | F24: N/A | G24: N/A for Automation
B25: 2 | C25: Agent doesn't have Partners Page and BOR is unaccessable for this user.
A27: Test Case # 2 Verify BOR is scheduled and processed successfully | B27: 1 | C27: Login as an UW | D27: BOR is scheduled and processed | E27: N | F27: N/A | G27: N/A for Automation
B28: 2 | C28: Create/Find a HO policy (any state).
B29: 3 | C29: Navigate to the Partners page
B30: 4 | C30: Click on "Broker Transfer"
B31: 5 | C31: On BOR Transfer page enter Customer ID in "Customer Search"
B32: 6 | C32: Select customer from the dropdown
B33: 7 | C33: In "New Broker Search" enter different Agency ID
B34: 8 | C34: Select Agency from the dropdown
B35: 9 | C35: Click on "Display Customer Details"
B36: 10 | C36: Select New Licensed Producer and New Advisor / Servicer
B37: 11 | C37: Click on "Schedule bor transfer" button
B38: 12 | C38: Verify BOR is scheduled sucessfully
B39: 13 | C39: Wait for the overnight job to be processed (or click the button ">>> Start BOR Batch" and navigate to the selected policy after few minutes)
... B41: 15 | C41: Verify that BOR is processed sucessfully and the Agency is changed to a new one on the account
A43: Test Case # 3 Verify BOR cannot be scheduled when there are unprocessed transactions on the policy | B43: 1 | C43: Login as an UW | D43: Wording is per request. | E43: N | F43: N/A | G43: N/A for Automation
B44: 2 | C44: Create/Find a HO policy (any state).
B45: 3 | C45: Create an Endorsement transaction and do not process
B46: 4 | C46: Navigate to the Partners page
B47: 5 | C47: Click on "Broker Transfer"
B48: 6 | C48: On BOR Transfer page enter Customer ID in "Customer Search"
B49: 7 | C49: Select customer from the dropdown
B50: 8 | C50: In "New Broker Search" enter different Agency ID
B51: 9 | C51: Select Agency from the dropdown
B52: 10 | C52: Click on "Display Customer Details"
B53: 11 | C53: Select New Licensed Producer and New Advisor / Servicer
B54: 12 | C54: Click on "Schedule bor transfer" button
B55: 13 | C55: Verify that message will appeare on top or the page telling user that there is unproccesed transaction on record.
B56: 14 | C56: Verify the wording of the message.
A58: Test Case # 4 Verify BOR is scheduled successfully | B58: 1 | C58: Login as an UW | D58: BOR is scheduled | E58: N | F58: N/A | G58: N/A for Automation
B59: 2 | C59: Create/Find a HO policy (any state).
B60: 3 | C60: Navigate to the Partners page
B61: 4 | C61: Click on "Broker Transfer"
B62: 5 | C62: On BOR Transfer page enter Customer ID in "Customer Search"
B63: 6 | C63: Select customer from the dropdown
B64: 7 | C64: In "New Broker Search" enter different Agency ID
B65: 8 | C65: Select Agency from the dropdown
B66: 9 | C66: Click on "Display Customer Details"
B67: 10 | C67: Select New Licensed Producer and New Advisor / Servicer
B68: 11 | C68: Click on "Schedule bor transfer" button
B69: 12 | C69: Verify BOR is scheduled sucessfully
A71: Test Case # 5 Verify that losing Agency cannot see transactions created after BOR transaction | B71: 1 | C71: Login as an UW | D71: Loosing agency is not able to see new trx afrter processing BOR | E71: N | F71: N/A | G71: N/A for Automation
B72: 2 | C72: Create/Find a HO policy (any state).
B73: 3 | C73: Navigate to the Partners page
B74: 4 | C74: Click on "Broker Transfer"
B75: 5 | C75: On BOR Transfer page enter Customer ID in "Customer Search"
B76: 6 | C76: Select customer from the dropdown
B77: 7 | C77: In "New Broker Search" enter different Agency ID
B78: 8 | C78: Select Agency from the dropdown
B79: 9 | C79: Click on "Display Customer Details"
B80: 10 | C80: Select New Licensed Producer and New Advisor / Servicer
B81: 11 | C81: Click on "Schedule bor transfer" button
B82: 12 | C82: Verify BOR is scheduled sucessfully
B83: 13 | C83: Wait for the overnight job to be processed
... B86: 16 | C86: Verify that loosing Agency cannot see any new transactions created.
A88: Test Case # 6 Verify that losing Agency cannot create new transactions after BOR | B88: 1 | C88: Login as an UW | D88: Loosing agency is not able to create new trx afrter processing BOR | E88: N | F88: N/A | G88: N/A for Automation
B89: 2 | C89: Create/Find a HO policy (any state).
B90: 3 | C90: Navigate to the Partners page
B91: 4 | C91: Click on "Broker Transfer"
B92: 5 | C92: On BOR Transfer page enter Customer ID in "Customer Search"
B93: 6 | C93: Select customer from the dropdown
B94: 7 | C94: In "New Broker Search" enter different Agency ID
B95: 8 | C95: Select Agency from the dropdown
B96: 9 | C96: Click on "Display Customer Details"
B97: 10 | C97: Select New Licensed Producer and New Advisor / Servicer
B98: 11 | C98: Click on "Schedule bor transfer" button
B99: 12 | C99: Verify BOR is scheduled sucessfully
B100: 13 | C100: Wait for the overnight job to be processed
... B103: 16 | C103: Verify that user from loosing Agency is not able to create new trx.
A105: Test Case # 7 Verify that winning Agency can create new transactions after BOR | B105: 1 | C105: Login as an UW | D105: Winning agency is able to create new trx afrter processing BOR | E105: N | F105: N/A | G105: N/A for Automation
B106: 2 | C106: Create/Find a HO policy (any state).
B107: 3 | C107: Navigate to the Partners page
B108: 4 | C108: Click on "Broker Transfer"
B109: 5 | C109: On BOR Transfer page enter Customer ID in "Customer Search"
B110: 6 | C110: Select customer from the dropdown
B111: 7 | C111: In "New Broker Search" enter different Agency ID
B112: 8 | C112: Select Agency from the dropdown
B113: 9 | C113: Click on "Display Customer Details"
B114: 10 | C114: Select New Licensed Producer and New Advisor / Servicer
B115: 11 | C115: Click on "Schedule bor transfer" button
B116: 12 | C116: Verify BOR is scheduled sucessfully
...

Sheet OFAC
A1: Back to Summary
A2: OFAC
A4: Objective: | B4: 1 | C4: Validate Ofac Integration Try different roles and permissions and how it triggers referrals
A6: Data: | B6: 1 | C6: Data to be Used for Testing: OFAC List - Individuals/Other Legal Entities
B7: 2
B8: 3
A10: Preconditions: | B10: 1 | C10: Access to UI
B11: 2
B12: 3
B13: 4
A15: Status: | B15: N | C15: = Not executed by QA
B16: P | C16: = Passed by QA
B17: F | C17: = Failed by QA
B18: T | C18: = Testing in progress
B19: R | C19: = Rejected / Existing issue
B20: B | C20: = Blocked by QA
A22: Description | B22: # | C22: Steps | D22: Expected Results | E22: Status | F22: Automation status | G22: Comments | H22: Defect ID /Blocked reason
A24: Test Case # 1 Verify that OFAC referral is triggered for Individuals from the List on Homeowners LOB, Named Insured Type: Individual (negative test for NB, END, RNW) | B24: 1 | C24: Login in the application using the Underwriter credentials | E24: N | F24: Y | G24: Automated
B25: 2 | C25: Create a Quote using a First/Last Name of a Person NOT on OFAC List, and populate mandatory fields
B26: 3 | C26: Verify that Named Insured Type = Individual
B27: 4 | C27: Complete the Quote and Rate
B28: 5 | C28: Visit UW Referrals page and verify that OFAC Referral is not triggered | D28: OFAC refferal NOT triggered on NB
B29: 6 | C29: Process NB transaction
B30: 7 | C30: Create an Endorsement trx
B31: 8 | C31: Rate Endorsement and visit UW Alerts page
B32: 9 | C32: Verify that OFAC Referral is not triggered | D32: OFAC refferal not triggered on Endorsement
B33: 10 | C33: Select More changes button and navigate to Cover page
B34: 11 | C34: Add additional Named Insured using data First/Last Name from OFAC List Vladimir Putin
B35: 12 | C35: Rate trx and visit UW Alerts page
B36: 13 | C36: Verify that OFAC Referral is triggered | D36: OFAC refferal triggered on Endorsement
B37: 14 | C37: Process Endorsement
B38: 15 | C38: Create Renewal, click Review changes button, then Renewed Premium
B39: 16 | C39: Navigate to UW Alerts page and verify OFAC refferal for Vladmir Putin | D39: OFAC refferal triggered on Renewal
A41: Test Case # 2 Verify that OFAC referral is triggered for Individuals from the List on Homeowners LOB, Named Insured Type: Individual (positive test for NB, END, RNW) | B41: 1 | C41: Login in the application using the Underwriter credentials | E41: N | F41: Y | G41: Automated
B42: 2 | C42: Create a Quote using a First/Last Name Marko Milosevic, and populate mandatory fields
B43: 3 | C43: Verify that Named Insured Type = Individual
B44: 4 | C44: Complete the Quote and Rate
B45: 5 | C45: Visit UW Referrals page and verify that OFAC Referral is triggered | D45: OFAC refferal triggered on NB
B46: 6 | C46: Process NB transaction
B47: 7 | C47: Create an Endorsement trx
B48: 8 | C48: Rate Endorsement and visit UW Alerts page
B49: 9 | C49: Verify that OFAC Referral is not triggered | D49: OFAC refferal not triggered on Endorsement
B50: 10 | C50: Select More changes button and navigate to Cover page
B51: 11 | C51: Add additional Named Insured using data First/Last Name from OFAC List Vladimir Putin
B52: 12 | C52: Rate trx and visit UW Alerts page
B53: 13 | C53: Verify that OFAC Referral is triggered | D53: OFAC refferal triggered on Endorsement
B54: 14 | C54: Process Endorsement
B55: 15 | C55: Create Renewal, click Review changes button, then Renewed Premium
B56: 16 | C56: Navigate to UW Alerts page and verify OFAC refferals | D56: OFAC refferal triggered on Renewal
A58: Test Case # 3 Verify that OFAC referral is triggered for Individuals/Legal Entities from the List on Homeowners LOB, Named Insured Type: Other Legal Entity (NB, END, RNW) | B58: 1 | C58: Login in the application using the Underwriter credentials | E58: N | F58: Y | G58: Automated
B59: 2 | C59: Create a Quote using a Company Name not from OFAC List, and populate mandatory fields
B60: 3 | C60: Verify that Named Insured Type = Other Legal Entity
B61: 4 | C61: Complete all mandatory fields the Quote and Rate
B62: 5 | C62: Visit UW Referrals page and verify that OFAC Referral is not triggered | D62: OFAC refferal is NOT triggered on NB
B63: 6 | C63: Navigate back to Questionnaire and replace Entity name with Company name from OFAC List
B64: 7 | C64: Add Beneficial Owner - First/Last Name from OFAC List
B65: 8 | C65: Visit UW Referrals page and verify that OFAC Referral is triggered twice | D65: OFAC refferal is triggered on NB
B66: 9 | C66: Process NB transaction
B67: 10 | C67: Create an Endorsement trx
B68: 11 | C68: Rate Endorsement and visit UW Alerts page
B69: 12 | C69: Verify that OFAC Referral is not triggered | D69: OFAC refferal not triggered on Endorsement
B70: 13 | C70: Navigate back to Questionnaire and add another Legal Entity name with Company name from OFAC List
B71: 14 | C71: Rate trx and visit UW Alerts page
B72: 15 | C72: Verify that OFAC Referral is triggered | D72: OFAC refferal triggered on Endorsement
B73: 16 | C73: Process Endorsement
B74: 17 | C74: Create Renewal, click Review changes button, then Renewed Premium
B75: 18 | C75: Navigate to UW Alerts page and verify OFAC refferals | D75: OFAC refferal triggered on Renewal
A77: Test Case # 4 Verify that OFAC referral is triggered for Individuals/Legal Entities from the List on Homeowners LOB, Named Insured Type: LLC (NB, END, RNW) | B77: 1 | C77: Login in the application using the Underwriter credentials | E77: N | F77: Y | G77: Automated
B78: 2 | C78: Create a Quote using a Company Name not from OFAC List, and populate mandatory fields
B79: 3 | C79: Verify that Named Insured Type = LLC
B80: 4 | C80: Complete all mandatory fields the Quote and Rate
B81: 5 | C81: Visit UW Referrals page and verify that OFAC Referral is not triggered | D81: OFAC refferal is NOT triggered on NB
B82: 6 | C82: Navigate back to Questionnaire and replace Entity name with Company name from OFAC List
B83: 7 | C83: Visit UW Referrals page and verify that OFAC Referral is triggered twice
B84: 8 | C84: Add Beneficial Owner - First/Last Name from OFAC List
B85: 9 | C85: Process NB transaction
B86: 10 | C86: Create an Endorsement trx
B87: 11 | C87: Rate Endorsement and visit UW Alerts page
B88: 12 | C88: Verify that OFAC Referral is not triggered | D88: OFAC refferal not triggered on Endorsement
B89: 13 | C89: Navigate back to Questionnaire and add another Legal Entity name with Company name from OFAC List
B90: 14 | C90: Rate trx and visit UW Alerts page
B91: 15 | C91: Verify that OFAC Referral is triggered | D91: OFAC refferal triggered on Endorsement
B92: 16 | C92: Process Endorsement
B93: 17 | C93: Create Renewal, click Review changes button, then Renewed Premium
B94: 18 | C94: Navigate to UW Alerts page and verify OFAC refferals | D94: OFAC refferal triggered on Renewal
A96: Test Case # 5 Verify that OFAC referral is triggered for Homeowners LOB, Additional Interest (NB, END, RNW) | B96: 1 | C96: Login in the application using the Underwriter credentials | E96: N | F96: Y | G96: Automated
B97: 2 | C97: Create a Quote using a First/Last Name not on OFAC List, and populate mandatory fields
B98: 3 | C98: Add Additional Interest First/Last Name from OFAC List
B99: 4 | C99: Complete the Quote and Rate
B100: 5 | C100: Visit UW Referrals page and verify that OFAC Referral is triggered | D100: OFAC refferal triggered on NB
B101: 6 | C101: Process NB transaction
B102: 7 | C102: Create an Endorsement trx
B103: 8 | C103: Rate Endorsement and visit UW Alerts page
B104: 9 | C104: Verify that OFAC Referral is not triggered | D104: OFAC refferal not triggered on Endorsement
B105: 10 | C105: Select More changes button and navigate to Additional Interest page
B106: 11 | C106: Add Additional Interest First/Last Name from OFAC List
B107: 12 | C107: Rate trx and visit UW Alerts page
B108: 13 | C108: Verify that OFAC Referral is triggered | D108: OFAC refferal triggered on Endorsement
B109: 14 | C109: Process Endorsement
B110: 15 | C110: Create Renewal, click Review changes button, then Renewed Premium
...

Sheet Carrier Partners ES
A1: Back to Summary
A2: Carrier Partners ES
A3: STG Environment
A4: Objective: | B4: 1 | C4: Validate Carrier Partners ES functionality.
A6: Data: | B6: 1 | C6: Role: Underwriter Agent Broker Number: User: Password:
B7: 2
B8: 3
A10: Preconditions: | B10: 1 | C10: Access to the application
B11: 2
B12: 3
B13: 4
A15: Status: | B15: N | C15: = Not executed by QA
B16: P | C16: = Passed by QA
B17: F | C17: = Failed by QA
B18: T | C18: = Testing in progress
B19: R | C19: = Rejected / Existing issue
B20: B | C20: = Blocked by QA
A22: Description | B22: # | C22: Steps | D22: Expected Results | E22: Status | F22: Automation status | G22: Comments | H22: Defect ID /Blocked reason
A24: Test Case # 1 ES ALL states Carrier Partner = PURE Specialty Exchange | B24: 1 | C24: Enter to Dragon as an underwriter. | D24: PURE Specialty Exchange | E24: N | F24: Y | G24: Partial Automated
B25: 2 | C25: Create a new ES quote with eff. date 05/01/2023
B26: 3 | C26: Verify that the new Underwriting Company PURE Specialty Exchange is automaticaly assigned
B27: 4 | C27: Enter all mandatory fields and continue with quoting
B28: 5
B29: 6 | C29: Total States include AL, CA, CT, FL, GA, LA, MA, MS, NC, NJ, NY, SC, TX
B30: 7 | C30: Existing States - CA, CT, FL, MA, NY, TX
B31: 8 | C31: New States - AL, GA, LA, MS, NC, NJ, SC
A33: Test Case # 2 ES ALL states Carrier Partner = Safety Specialty Ins. | B33: 1 | C33: Enter to Dragon as an underwriter. | D33: Safety Specialty Ins. | E33: N | F33: Y | G33: Partial Automated
B34: 2 | C34: Create a new ES quote with eff. date before 05/01/2023
B35: 3 | C35: Verify that the Underwriting Company Safety Specialty Ins. is automaticaly assigned
B36: 4 | C36: Enter all mandatory fields and continue with quoting
B37: 5
B38: 6 | C38: Total States include AL, CA, CT, FL, GA, LA, MA, MS, NC, NJ, NY, SC, TX
B39: 7 | C39: Existing States - CA, CT, FL, MA, NY, TX
B40: 8 | C40: New States - AL, GA, LA, MS, NC, NJ, SC
A42: Test Case # 3 Excess Surplus State Expansion | B42: 1 | C42: Enter to Dragon as an underwriter. | D42: NOTE: Before 5/1/23: New Business Quotes for Excess Surplus with an effective date of 4/30 and prior should have Safety Specialty as the Carrier Partner. -This should include the new Excess Surplus states that will be available in the system starting 1/27 (AL, GA, LA, MS, NC, NJ, SC) -All Renewal Policies for Excess Surplus states written with an effective date before 4/30 should have Safety Specialty as the Carrier Partner 5/1/23 or later: -All Excess Surplus Renewals with an effective date of 5/1 or later should have PSE as the Carrier Partner -This should include the new Excess Surplus states that will be available in the system starting 1/27 (AL, GA, LA, MS, NC, NJ, SC) -All Excess Surplus Quotes/New Business with an effective date of 5/1 or later should have PSE as the Carrier Partner -This should include the new Excess Surplus states that will be available in the system starting 1/27 (AL, GA, LA, MS, NC, NJ, SC) | E42: N | F42: Y | G42: Partial Automated
B43: 2 | C43: Create a new ES quote with eff. date 01/27/2023
B44: 3 | C44: Verify that the new states are available
B45: 4 | C45: Enter all mandatory fields and continue with quoting
B46: 5
B47: 6 | C47: Total States include AL, CA, CT, FL, GA, LA, MA, MS, NC, NJ, NY, SC, TX
B48: 7 | C48: Existing States - CA, CT, FL, MA, NY, TX
B49: 8 | C49: New States - AL, GA, LA, MS, NC, NJ, SC
B50: 9
B51: 10
B52: 11
B53: 12
B54: 13
B55: 14
B56: 15
B57: 16
B58: 17

Sheet Carrier Partners HS
A1: Back to Summary
A2: Carrier Partners HS
A3: STG Environment
A4: Objective: | B4: 1 | C4: Validate Carrier Partners HS/ES functionality.
A6: Data: | B6: 1 | C6: Role: Underwriter Agent Broker Number: User: Password:
B7: 2
B8: 3
A10: Preconditions: | B10: 1 | C10: Access to the application
B11: 2
B12: 3
B13: 4
A15: Status: | B15: N | C15: = Not executed by QA
B16: P | C16: = Passed by QA
B17: F | C17: = Failed by QA
B18: T | C18: = Testing in progress
B19: R | C19: = Rejected / Existing issue
B20: B | C20: = Blocked by QA
A22: Description | B22: # | C22: Steps | D22: Expected Results | E22: Status | F22: Automation status | G22: Comments | H22: Defect ID /Blocked reason
A24: Test Case # 1 HS FL Carrier Partner = Accredited Specialty Insurance Company | B24: 1 | C24: Enter to Dragon as an underwriter. | D24: Accredited Specialty Insurance Company | E24: N | F24: Y | G24: Automated
B25: 2 | C25: Create a new HS FL quote with the address: 1215 NW 7th Ave, Florida City, 33034
B26: 3 | C26: Set Year built > 2015
B27: 4 | C27: Set Replacement cost = $3.000.000
B28: 5 | C28: Set Hurricane deductible = 5%
B29: 6 | C29: Distance to Coast override = '< 1000 ft'
B30: 7 | C30: Set Opening Protection = Impact Glass Rated for Large Missiles
B31: 8 | C31: Verify that the system automaticaly assigned Accredited Specialty Insurance Company as a Underwriter Company for FL state, Home Surplus Line
A33: Test Case # 2 HS FL Carrier Partner = National Fire & Marine Insurance Company | B33: 1 | C33: Enter to Dragon as an underwriter. | D33: National Fire & Marine Insurance Company | E33: N | F33: Y | G33: Automated
B34: 2 | C34: Create a new HS FL quote with the address: 1215 NW 7th Ave, Florida City, 33034
B35: 3 | C35: Set Year built > 2015
B36: 4 | C36: Set Replacement cost = $1.000.000
B37: 5 | C37: Set Hurricane deductible = 5%
B38: 6 | C38: Distance to Coast override = '< 1000 ft'
B39: 7 | C39: Set Opening Protection = Impact Glass Rated for Large Missiles
B40: 8 | C40: Verify that the system automaticaly assigned National Fire & Marine Insurance Company as a Underwriter Company for FL state, Home Surplus Line
A42: Test Case # 3 HS TX state Carrier Partner = Safety Specialty | B42: 1 | C42: Enter to Dragon as an underwriter | D42: The system automaticaly assigned Safety Specialty as a Underwriter Company NOTE: depending on certain rules (e.g. eff date of the policy) and assignment criteria for each of the Underwriting Company, under which the Companies write the policy, Companies may vary from state to state | E42: N | F42: Y | G42: Not Automated
B43: 2 | C43: Create a new HS quote in TX
B44: 3 | C44: Use any available address ()
B45: 4 | C45: Populate all mandatory fields on the quote
B46: 5 | C46: Navigate back to the coverage page
B47: 6 | C47: Verify that the system automaticaly assigned Safety Specialty as a Underwriter Company for TX state, Home Surplus Line
B48: 7 | C48: All Underwriting Companies (Carrier Partners) can be checked on the UI/Home page/Aggregate management page, under open/close carrier partner block
A50: Test Case # 4 HS NY state Carrier Partner = Safety Specialty | B50: 1 | C50: Enter to Dragon as an underwriter | D50: The system automaticaly assigned Safety Specialty as a Underwriter Company NOTE: depending on certain rules (e.g. eff date of the policy) and assignment criteria for each of the Underwriting Company, under which the Companies write the policy, Companies may vary from state to state | E50: N | F50: Y | G50: Not Automated
B51: 2 | C51: Create a new HS quote in NY
B52: 3 | C52: Use any available address ()
B53: 4 | C53: Populate all mandatory fields on the quote
B54: 5 | C54: Navigate back to the coverage page
B55: 6 | C55: Verify that the system automaticaly assigned Safety Specialty as a Underwriter Company for TX state, Home Surplus Line
B56: 7 | C56: All Underwriting Companies (Carrier Partners) can be checked on the UI/Home page/Aggregate management page, under open/close carrier partner block
A58: Test Case # 5 HS CA state Carrier Partner = PURE Specialty Exchange | B58: 1 | C58: Enter to Dragon as an underwriter | D58: The system automaticaly assigned PURE Specialty Exchange as a Underwriter Company NOTE: depending on certain rules (e.g. eff date of the policy) and assignment criteria for each of the Underwriting Company, under which the Companies write the policy, Companies may vary from state to state | E58: N | F58: Y | G58: Not Automated
B59: 2 | C59: Create a new HS quote in CA state
B60: 3 | C60: Use any available address (503 Avery Sheep Ranch Rd, Avery, CA 95224)
B61: 4 | C61: Populate all mandatory fields on the quote
B62: 5 | C62: Navigate back to the coverage page
B63: 6 | C63: Verify that the system automaticaly assigned PURE Specialty Exchange as a Underwriter Company for CA state, Home Surplus Line
B64: 7 | C64: All Underwriting Companies (Carrier Partners) can be checked on the UI/Home page/Aggregate management page, under open/close carrier partner block
A66: Test Case # 6 HS MA state Carrier Partner = PURE Specialty Exchange | B66: 1 | C66: Enter to Dragon as an underwriter | D66: The system automaticaly assigned PURE Specialty Exchange as a Underwriter Company NOTE: depending on certain rules (e.g. eff date of the policy) and assignment criteria for each of the Underwriting Company, under which the Companies write the policy, Companies may vary from state to state | E66: N | F66: Y | G66: Not Automated
B67: 2 | C67: Create a new HS quote in MA state
B68: 3 | C68: Use any available address (382 Bedford St, Lakeville, MA 02347)
B69: 4 | C69: Populate all mandatory fields on the quote
B70: 5 | C70: Navigate back to the coverage page
B71: 6 | C71: Verify that the system automaticaly assigned PURE Specialty Exchange as a Underwriter Company for MA state, Home Surplus Line
B72: 7 | C72: All Underwriting Companies (Carrier Partners) can be checked on the UI/Home page/Aggregate management page, under open/close carrier partner block
A74: Test Case # 7 HS MS state Carrier Partner = PURE Specialty Exchange | B74: 1 | C74: Enter to Dragon as an underwriter | D74: The system automaticaly assigned PURE Specialty Exchange as a Underwriter Company NOTE: depending on certain rules (e.g. eff date of the policy) and assignment criteria for each of the Underwriting Company, under which the Companies write the policy, Companies may vary from state to state | E74: N | F74: Y | G74: Not Automated
B75: 2 | C75: Create a new HS quote in MS state
B76: 3 | C76: Use any available address (1224 Highway 2, Corinth, MS 38834)
B77: 4 | C77: Populate all mandatory fields on the quote
B78: 5 | C78: Navigate back to the coverage page
B79: 6 | C79: Verify that the system automaticaly assigned PURE Specialty Exchange as a Underwriter Company for MS state, Home Surplus Line
B80: 7 | C80: All Underwriting Companies (Carrier Partners) can be checked on the UI/Home page/Aggregate management page, under open/close carrier partner block
A82: Test Case # 8 HS NC state Carrier Partner = PURE Specialty Exchange | B82: 1 | C82: Enter to Dragon as an underwriter | D82: The system automaticaly assigned PURE Specialty Exchange as a Underwriter Company NOTE: depending on certain rules (e.g. eff date of the policy) and assignment criteria for each of the Underwriting Company, under which the Companies write the policy, Companies may vary from state to state | E82: N | F82: Y | G82: Not Automated
B83: 2 | C83: Create a new HS quote in NC state
B84: 3 | C84: Use any available address (409 S Dogwood Ave, Siler City, NC 27344)
B85: 4 | C85: Populate all mandatory fields on the quote
B86: 5 | C86: Navigate back to the coverage page
B87: 6 | C87: Verify that the system automaticaly assigned PURE Specialty Exchange as a Underwriter Company for NC state, Home Surplus Line
B88: 7 | C88: All Underwriting Companies (Carrier Partners) can be checked on the UI/Home page/Aggregate management page, under open/close carrier partner block
A90: Test Case # 9 HS SC state Carrier Partner = PURE Specialty Exchange | B90: 1 | C90: Enter to Dragon as an underwriter | D90: The system automaticaly assigned PURE Specialty Exchange as a Underwriter Company NOTE: depending on certain rules (e.g. eff date of the policy) and assignment criteria for each of the Underwriting Company, under which the Companies write the policy, Companies may vary from state to state | E90: N | F90: Y | G90: Not Automated
B91: 2 | C91: Create a new HS quote in SC
B92: 3 | C92: Use any available address (125 Patton Street, Fountain Inn, SC 29644)
B93: 4 | C93: Populate all mandatory fields on the quote
B94: 5 | C94: Navigate back to the coverage page
B95: 6 | C95: Verify that the system automaticaly assigned PURE Specialty Exchange as a Underwriter Company for SC state, Home Surplus Line
B96: 7 | C96: All Underwriting Companies (Carrier Partners) can be checked on the UI/Home page/Aggregate management page, under open/close carrier partner block
A98: Test Case # 10 HS NJ state Carrier Partner = PURE Specialty Exchange | B98: 1 | C98: Enter to Dragon as an underwriter | D98: The system automaticaly assigned PURE Specialty Exchange as a Underwriter Company NOTE: depending on certain rules (e.g. eff date of the policy) and assignment criteria for each of the Underwriting Company, under which the Companies write the policy, Companies may vary from state to state | E98: N | F98: Y | G98: Not Automated
B99: 2 | C99: Create a new HS quote in NJ
B100: 3 | C100: Use any available address (51 Aberdeen Road, Matawan, NJ 07747)
B101: 4 | C101: Populate all mandatory fields on the quote
B102: 5 | C102: Navigate back to the coverage page
B103: 6 | C103: Verify that the system automaticaly assigned PURE Specialty Exchange as a Underwriter Company for NJ state, Home Surplus Line
B104: 7 | C104: All Underwriting Companies (Carrier Partners) can be checked on the UI/Home page/Aggregate management page, under open/close carrier partner block
A106: Test Case # 11 HS GA state Carrier Partner = PURE Specialty Exchange | B106: 1 | C106: Enter to Dragon as an underwriter | D106: The system automaticaly assigned PURE Specialty Exchange as a Underwriter Company NOTE: depending on certain rules (e.g. eff date of the policy) and assignment criteria for each of the Underwriting Company, under which the Companies write the policy, Companies may vary from state to state | E106: N | F106: Y | G106: Not Automated
B107: 2 | C107: Create a new HS quote in GA
B108: 3 | C108: Use any available address (10040 Lake Forest Way, Roswell, GA 30076)
B109: 4 | C109: Populate all mandatory fields on the quote
B110: 5 | C110: Navigate back to the coverage page
B111: 6 | C111: Verify that the system automaticaly assigned PURE Specialty Exchange as a Underwriter Company for GA state, Home Surplus Line
B112: 7 | C112: All Underwriting Companies (Carrier Partners) can be checked on the UI/Home page/Aggregate management page, under open/close carrier partner block
A114: Test Case # 12 HS LA state Carrier Partner = PURE Specialty Exchange | B114: 1 | C114: Enter to Dragon as an underwriter | D114: The system automaticaly assigned PURE Specialty Exchange as a Underwriter Company NOTE: depending on certain rules (e.g. eff date of the policy) and assignment criteria for each of the Underwriting Company, under which the Companies write the policy, Companies may vary from state to state | E114: N | F114: Y | G114: Not Automated
B115: 2 | C115: Create a new HS quote in LA
B116: 3 | C116: Use any available address (204 Shadow Springs Dr, Lafayette, LA 70508)
...

Sheet TIV HS
A1: Back to Summary
A2: TIV HS
A3: STG Environment
A4: Objective: | B4: 1 | C4: Validate TIV HS functionality.
A6: Data: | B6: 1 | C6: Role: Underwriter Agent Broker Number: User: Password:
B7: 2
B8: 3
A10: Preconditions: | B10: 1 | C10: Access to the application
B11: 2
B12: 3
B13: 4
A15: Status: | B15: N | C15: = Not executed by QA
B16: P | C16: = Passed by QA
B17: F | C17: = Failed by QA
B18: T | C18: = Testing in progress
B19: R | C19: = Rejected / Existing issue
B20: B | C20: = Blocked by QA
A22: Description | B22: # | C22: Steps | D22: Expected Results | E22: Status | F22: Automation status | G22: Comments | H22: Defect ID /Blocked reason
A24: Test Case # 1 Verify TIV underwriting threshold colors | B24: 1 | C24: Enter to Dragon as an underwriter. | D24: On the Premium summary - underwriting threshold colors should be displayed for available capacity for the zone. | E24: N | F24: N | G24: Not Automated
B25: 2 | C25: Create and rate HS quote adding if available excess flood/earthquage coverages.
B26: 3 | C26: Navigate to the Primium Summary page
B27: 4 | C27: Verify the underwriting threshold colors for available capacity for the zone. (location, flood and earthquage coverages.)
B28: 5 | C28: Verify for - Normal capacity - color should be green.
B29: 6 | C29: Modify TIV capacity for the same zone and Verify the UW threshold for -Over limit - Color should be Red.
B30: 7 | C30: Follow the same process for other thresolds type.
A32: Test Case # 2 Verify TIV/ROL values | B32: 1 | C32: Enter to Dragon as an underwriter. | D32: TIV/ROL values should show correctly | E32: N | F32: N | G32: Not Automated
B33: 2 | C33: Create and rate HS quote, adding if available excess flood/earthquage coverages.
B34: 3 | C34: Navigate to the Primium Summary page
B35: 4 | C35: Verify TIV values for location, excess flood and earthquage coverages.
B36: 5 | C36: Verify ROL values for location, excess flood and earthquage coverages for New Business and Renewals.

Sheet AIR HS FL
A1: Back to Summary
A2: AIR/RMS HS FL
A3: STG Environment
A4: Objective: | B4: 1 | C4: Validate AIR/RMS HS FL functionality.
A6: Data: | B6: 1 | C6: Role: Underwriter Agent Broker Number: User: Password:
B7: 2
B8: 3
A10: Preconditions: | B10: 1 | C10: Access to the application
B11: 2
B12: 3
B13: 4
A15: Status: | B15: N | C15: = Not executed by QA
B16: P | C16: = Passed by QA
B17: F | C17: = Failed by QA
B18: T | C18: = Testing in progress
B19: R | C19: = Rejected / Existing issue
B20: B | C20: = Blocked by QA
A22: Description | B22: # | C22: Steps | D22: Expected Results | E22: Status | F22: Automation status | G22: Comments | H22: Defect ID /Blocked reason
A24: Test Case # 1 Verify that AIR reports are sucessfully ordered for FL state, Home Surplus Line NB/END/REN | B24: 1 | C24: Enter to Dragon as an underwriter. | E24: N | F24: Y | G24: Automated
B25: 2 | C25: Create a new HS FL quote with the address: 1215 NW 7th Ave, Florida City, 33034
B26: 3 | C26: Set Year built > 2015
B27: 4 | C27: Set Replacement cost = $1.000.000
B28: 5 | C28: Set Hurricane deductible = 5%
B29: 6 | C29: Distance to Coast override = '< 1000 ft'
B30: 7 | C30: Set Opening Protection = Impact Glass Rated for Large Missiles
B31: 8 | C31: Navigate to the Risk Model information
B32: 9 | C32: Verify that AIR reports are sucessfully ordered for FL state, Home Surplus Line | D32: AIR reports are sucessfully ordered for FL state, Home Surplus Line
B33: 10 | C33: Populate all the mandatory fields and bind the quote into a policy
B34: 11 | C34: Create an Endorsement Transaction
B35: 12 | C35: Verify that AIR reports are not reordered for FL state, Home Surplus Line | D35: AIR reports are not reordered for FL state, Home Surplus Line
B36: 13 | C36: Issue the Endorsement transaction
B37: 14 | C37: Create Renewal transaction
B38: 15 | C38: Verify that AIR reports are sucessfully ordered for FL state, Home Surplus Line | D38: AIR reports are sucessfully ordered for FL state, Home Surplus Line
B39: 16 | C39: Issue the Renewal transaction
A41: Test Case # 2 Verify that AIR reports are sucessfully ordered for FL state, Home Surplus Line NB/OOS END/REN | B41: 1 | C41: Enter to Dragon as an underwriter. | E41: N | F41: Y | G41: Automated
B42: 2 | C42: Create a new HS FL quote with the address: 1215 NW 7th Ave, Florida City, 33034
B43: 3 | C43: Set Year built > 2015
B44: 4 | C44: Set Replacement cost = $1.000.000
B45: 5 | C45: Set Hurricane deductible = 5%
B46: 6 | C46: Distance to Coast override = '< 1000 ft'
B47: 7 | C47: Set Opening Protection = Impact Glass Rated for Large Missiles
B48: 8 | C48: Navigate to the Risk Model information
B49: 9 | C49: Verify that AIR reports are sucessfully ordered for FL state, Home Surplus Line | D49: AIR reports are sucessfully ordered for FL state, Home Surplus Line
B50: 10 | C50: Populate all the mandatory fields and bind the quote into a policy
B51: 11 | C51: Create and issue the Renewal transaction
B52: 12 | C52: Create an OOS Endorsement Transaction
B53: 13 | C53: Verify that AIR reports are not reordered for FL state, Home Surplus Line | D53: AIR reports are not reordered for FL state, Home Surplus Line
B54: 14 | C54: Issue the Endorsement transaction
B55: 15 | C55: After the rollforward navigate back to the homeowners risk model information page
B56: 16 | C56: Verify that AIR reports are sucessfully ordered for FL state, Home Surplus Line | D56: AIR reports are sucessfully ordered for FL state, Home Surplus Line
A58: Test Case # 3 Verify that RMS reports are sucessfully ordered for FL state, Home Surplus Line NB/END/REN | B58: 1 | C58: Enter to Dragon as an underwriter. | E58: N | F58: Y | G58: Automated
B59: 2 | C59: Create a new HS FL quote with the address: 1215 NW 7th Ave, Florida City, 33034
B60: 3 | C60: Set Year built > 2015
B61: 4 | C61: Set Replacement cost = $3.000.000
B62: 5 | C62: Set Hurricane deductible = 5%
B63: 6 | C63: Distance to Coast override = '< 1000 ft'
B64: 7 | C64: Set Opening Protection = Impact Glass Rated for Large Missiles
B65: 8 | C65: Navigate to the Risk Model information
B66: 9 | C66: Verify that RMS reports are sucessfully ordered for FL state, Home Surplus Line | D66: RMS reports are sucessfully ordered for FL state, Home Surplus Line.
B67: 10 | C67: Populate all the mandatory fields and bind the quote into a policy
B68: 11 | C68: Create an Endorsement Transaction
B69: 12 | C69: Verify that RMS reports are not reordered for FL state, Home Surplus Line | D69: RMS reports are not reordered for FL state, Home Surplus Line
B70: 13 | C70: Issue the Endorsement transaction
B71: 14 | C71: Create Renewal transaction
B72: 15 | C72: Verify that RMS reports are sucessfully ordered for FL state, Home Surplus Line | D72: RMS reports are sucessfully ordered for FL state, Home Surplus Line.
B73: 16 | C73: Issue the Renewal transaction
A75: Test Case # 4 Verify that RMS reports are sucessfully ordered for FL state, Home Surplus Line NB/END/REN | B75: 1 | C75: Enter to Dragon as an underwriter. | E75: N | F75: Y | G75: Automated
B76: 2 | C76: Create a new HS FL quote with the address: 1215 NW 7th Ave, Florida City, 33034
B77: 3 | C77: Set Year built > 2015
B78: 4 | C78: Set Replacement cost = $3.000.000
B79: 5 | C79: Set Hurricane deductible = 5%
B80: 6 | C80: Distance to Coast override = '< 1000 ft'
B81: 7 | C81: Set Opening Protection = Impact Glass Rated for Large Missiles
B82: 8 | C82: Navigate to the Risk Model information
B83: 9 | C83: Verify that RMS reports are sucessfully ordered for FL state, Home Surplus Line | D83: RMS reports are sucessfully ordered for FL state, Home Surplus Line.
B84: 10 | C84: Populate all the mandatory fields and bind the quote into a policy
B85: 11 | C85: Create and issue the Renewal transaction
B86: 12 | C86: Create an OOS Endorsement Transaction
B87: 13 | C87: Verify that RMS reports are not reordered for FL state, Home Surplus Line | D87: RMS reports are not reordered for FL state, Home Surplus Line
B88: 14 | C88: Issue the Endorsement transaction
B89: 15 | C89: After the rollforward navigate back to the homeowners risk model information page
B90: 16 | C90: Verify that RMS reports are sucessfully ordered for FL state, Home Surplus Line | D90: RMS reports are sucessfully ordered for FL state, Home Surplus Line.

Sheet RMS HS TX
A1: Back to Summary
A2: RMS HS TX/HI
A3: STG Environment
A4: Objective: | B4: 1 | C4: Validate RMS HS TX functionality.
A6: Data: | B6: 1 | C6: Role: Underwriter Agent Broker Number: User: Password:
B7: 2
B8: 3
A10: Preconditions: | B10: 1 | C10: Access to the application
B11: 2
B12: 3
B13: 4
A15: Status: | B15: N | C15: = Not executed by QA
B16: P | C16: = Passed by QA
B17: F | C17: = Failed by QA
B18: T | C18: = Testing in progress
B19: R | C19: = Rejected / Existing issue
B20: B | C20: = Blocked by QA
A22: Description | B22: # | C22: Steps | D22: Expected Results | E22: Status | F22: Automation status | G22: Comments | H22: Defect ID /Blocked reason
A24: Test Case # 1 Verify that RMS reports are sucessfully ordered for TX state, Home Surplus Line NB | B24: 1 | C24: Enter to Dragon as an underwriter. | E24: N | F24: Y | G24: Automated
B25: 2 | C25: Create a new HS TX quote with the address: 18026 Shaman Road, Galveston, TX 77554
B26: 3 | C26: Set Year built = 2010
B27: 4 | C27: Set Replacement cost = $6.000.000
B28: 5 | C28: Set Hurricane deductible = 10%
B29: 6 | C29: Navigate to the Risk Model information page
B30: 7 | C30: Verify that RMS reports are sucessfully ordered for TX state, Home Surplus Line | D30: RMS reports are sucessfully ordered for TX state, Home Surplus Line.
A32: Test Case # 2 Verify that RMS reports are sucessfully ordered for TX state, Home Surplus Line on END and REN | B32: 1 | C32: Enter to Dragon as an underwriter. | E32: N | F32: Y | G32: Automated
B33: 2 | C33: Create a new HS TX quote with the address: 18026 Shaman Road, Galveston, TX 77554
B34: 3 | C34: Set Year built = 2010
B35: 4 | C35: Set Replacement cost = $6.000.000
B36: 5 | C36: Set Hurricane deductible = 10%
B37: 6 | C37: Navigate to the Risk Model information page
B38: 7 | C38: Verify that RMS reports are sucessfully ordered for TX state, Home Surplus Line | D38: RMS reports are sucessfully ordered for TX state, Home Surplus Line.
B39: 8 | C39: Populate all the mandatory fields and bind the quote into a policy
B40: 9 | C40: Create an Endorsement Transaction
B41: 10 | C41: Verify that RMS reports are not reordered for TX state, Home Surplus Line | D41: RMS reports are not reordered for TX state, Home Surplus Line.
B42: 11 | C42: Issue the Endorsement transaction
B43: 12 | C43: Create Renewal transaction
B44: 13 | C44: Verify that RMS reports are sucessfully ordered for TX state, Home Surplus Line | D44: RMS reports are sucessfully Repulled for TX state, Home Surplus Line.
B45: 14 | C45: Issue the Renewal transaction
A47: Test Case # 3 Verify that RMS reports are sucessfully ordered for TX state, Home Surplus Line on OOS END and REN | B47: 1 | C47: Enter to Dragon as an underwriter. | E47: N | F47: Y | G47: Automated | H47: HS248830901
B48: 2 | C48: Create a new HS TX quote with the address: 18026 Shaman Road, Galveston, TX 77554
B49: 3 | C49: Set Year built = 2010
B50: 4 | C50: Set Replacement cost = $6.000.000
B51: 5 | C51: Set Hurricane deductible = 10%
B52: 6 | C52: Navigate to the Risk Model information page
B53: 7 | C53: Verify that RMS reports are sucessfully ordered for TX state, Home Surplus Line | D53: RMS reports are sucessfully ordered for TX state, Home Surplus Line.
B54: 8 | C54: Populate all the mandatory fields and bind the quote into a policy
B55: 9 | C55: Create and issue the Renewal transaction
B56: 10 | C56: Create an OOS Endorsement Transaction
B57: 11 | C57: Verify that RMS reports are not reordered for TX state, Home Surplus Line | D57: RMS reports are not reordered for TX state, Home Surplus Line.
B58: 12 | C58: Issue the Endorsement transaction
B59: 13 | C59: After the rollforward navigate back to the homeowners risk model information page
B60: 14 | C60: Verify that RMS reports are sucessfully ordered for TX state, Home Surplus Line | D60: RMS reports are sucessfully Repulled for TX state, Home Surplus Line.
A62: Test Case # 4 Verify that RMS reports are sucessfully ordered for HI state, Home Surplus Line NB | B62: 1 | C62: Enter to Dragon as an underwriter. | E62: N | F62: Y | G62: Automated
B63: 2 | C63: Create a new HI TX quote with the address: 7000 Hawaii Kai Dr, Honolulu, HI 96825
B64: 3 | C64: Set Year built = 2010
B65: 4 | C65: Set Replacement cost = $6.000.000
B66: 5 | C66: Set Hurricane deductible = 10%
B67: 6 | C67: Navigate to the Risk Model information page
B68: 7 | C68: Verify that RMS reports are sucessfully ordered for HI state, Home Surplus Line | D68: RMS reports are sucessfully ordered for HI state, Home Surplus Line.
A70: Test Case # 5 Verify that RMS reports are sucessfully ordered for HI state, Home Surplus Line on END and REN | B70: 1 | C70: Enter to Dragon as an underwriter. | E70: N | F70: Y | G70: Automated
B71: 2 | C71: Create a new HS TX quote with the address: 7000 Hawaii Kai Dr, Honolulu, HI 96825
B72: 3 | C72: Set Year built = 2010
B73: 4 | C73: Set Replacement cost = $6.000.000
B74: 5 | C74: Set Hurricane deductible = 10%
B75: 6 | C75: Navigate to the Risk Model information page
B76: 7 | C76: Verify that RMS reports are sucessfully ordered for HI state, Home Surplus Line | D76: RMS reports are sucessfully ordered for HI state, Home Surplus Line.
B77: 8 | C77: Populate all the mandatory fields and bind the quote into a policy
B78: 9 | C78: Create an Endorsement Transaction
B79: 10 | C79: Verify that RMS reports are sucessfully ordered for HI state, Home Surplus Line | D79: RMS reports are sucessfully ordered for HI state, Home Surplus Line.
B80: 11 | C80: Issue the Endorsement transaction
B81: 12 | C81: Create Renewal transaction
B82: 13 | C82: Verify that RMS reports are sucessfully ordered for HI state, Home Surplus Line | D82: RMS reports are sucessfully ordered for HI state, Home Surplus Line.
B83: 14 | C83: Issue the Renewal transaction
A85: Test Case # 6 Verify that RMS reports are sucessfully ordered for HI state, Home Surplus Line on OOS END and REN | B85: 1 | C85: Enter to Dragon as an underwriter. | E85: N | F85: Y | G85: Automated
B86: 2 | C86: Create a new HS TX quote with the address: 7000 Hawaii Kai Dr, Honolulu, HI 96825
B87: 3 | C87: Set Year built = 2010
B88: 4 | C88: Set Replacement cost = $6.000.000
B89: 5 | C89: Set Hurricane deductible = 10%
B90: 6 | C90: Navigate to the Risk Model information page
B91: 7 | C91: Verify that RMS reports are sucessfully ordered for HI state, Home Surplus Line | D91: RMS reports are sucessfully ordered for HI state, Home Surplus Line.
B92: 8 | C92: Populate all the mandatory fields and bind the quote into a policy
B93: 9 | C93: Create and issue the Renewal transaction
B94: 10 | C94: Create an OOS Endorsement Transaction
B95: 11 | C95: Verify that RMS reports are sucessfully ordered for HI state, Home Surplus Line | D95: RMS reports are sucessfully ordered for HI state, Home Surplus Line.
B96: 12 | C96: Issue the Endorsement transaction
B97: 13 | C97: After the rollforward navigate back to the homeowners risk model information page
B98: 14 | C98: Verify that RMS reports are sucessfully ordered for HI state, Home Surplus Line | D98: RMS reports are sucessfully Repulled for HI state, Home Surplus Line.

Sheet Elevation Certificate 
A1: Back to Summary
A2: Elevation Certificate
A3: STG Environment
A4: Objective: | B4: 1 | C4: Validate Elevation Certificate functionality.
A6: Data: | B6: 1 | C6: Role: Underwriter Agent Broker Number: User: Password:
B7: 2
B8: 3
A10: Preconditions: | B10: 1 | C10: Access to the application
B11: 2
B12: 3
B13: 4
A15: Status: | B15: N | C15: = Not executed by QA
B16: P | C16: = Passed by QA
B17: F | C17: = Failed by QA
B18: T | C18: = Testing in progress
B19: R | C19: = Rejected / Existing issue
B20: B | C20: = Blocked by QA
A22: Description | B22: # | C22: Steps | D22: Expected Results | E22: Status | F22: Automation status | G22: Comments | H22: Defect ID /Blocked reason
A24: Test Case # 1 Verify that Flood information is pulled on NB HO LOB | B24: 1 | C24: Enter to Dragon as an underwriter. | E24: N | F24: Y | G24: Automated
B25: 2 | C25: Create a HO quote
B26: 3 | C26: Navigate to Location coverage page
B27: 4 | C27: On the Flood information block verify that RiskMeter Flood Zone is pulled | D27: RiskMeter Flood Zone is pulled
B28: 5 | C28: Verify that Panel Number is pulled | D28: Panel Number is pulled
B29: 6 | C29: Verify that Soil Type is pulled | D29: Soil Type is pulled
B30: 7 | C30: Verify that Flood ID is pulled | D30: Flood ID is pulled
B31: 8 | C31: Populate all the mandatory fields
B32: 9 | C32: Bind the quote into a policy
A34: Test Case # 2 Verify that the Flood information is pulled on Endorsement for new Risk location HO LOB | B34: 1 | C34: Enter to Dragon as an underwriter. | E34: N | F34: Y | G34: Automated
B35: 2 | C35: Create a HO quote
B36: 3 | C36: Navigate to Location coverage page
B37: 4 | C37: On the Flood information block verify that RiskMeter Flood Zone is pulled | D37: RiskMeter Flood Zone is pulled
B38: 5 | C38: Verify that Panel Number is pulled | D38: Panel Number is pulled
B39: 6 | C39: Verify that Soil Type is pulled | D39: Soil Type is pulled
B40: 7 | C40: Verify that Flood ID is pulled | D40: Flood ID is pulled
B41: 8 | C41: Populate all the mandatory fields
B42: 9 | C42: Bind the quote into a policy
B43: 10 | C43: Create an Endorsement transaction
B44: 11 | C44: Navigate to the homeowners coverage page
B45: 12 | C45: Add Additional location
B46: 13 | C46: Navigate to Location coverage page of the new location
B47: 14 | C47: On the Flood information block verify that RiskMeter Flood Zone is pulled | D47: RiskMeter Flood Zone is pulled
B48: 15 | C48: Verify that Panel Number is pulled | D48: Panel Number is pulled
B49: 16 | C49: Verify that Soil Type is pulled | D49: Soil Type is pulled
B50: 17 | C50: Verify that Flood ID is pulled | D50: Flood ID is pulled
B51: 18 | C51: Populate all the mandatory fields
B52: 19 | C52: Issue the Endorsement transaction
A54: Test Case # 3 Verify that the Flood information is pulled on OOS Endorsement for new Risk location HO LOB | B54: 1 | C54: Enter to Dragon as an underwriter. | E54: N | F54: Y | G54: Automated
B55: 2 | C55: Create a HO quote
B56: 3 | C56: Navigate to Location coverage page
B57: 4 | C57: On the Flood information block verify that RiskMeter Flood Zone is pulled | D57: RiskMeter Flood Zone is pulled
B58: 5 | C58: Verify that Panel Number is pulled | D58: Panel Number is pulled
B59: 6 | C59: Verify that Soil Type is pulled | D59: Soil Type is pulled
B60: 7 | C60: Verify that Flood ID is pulled | D60: Flood ID is pulled
B61: 8 | C61: Populate all the mandatory fields
B62: 9 | C62: Bind the quote into a policy
B63: 10 | C63: Create and issue a Renwal transaction
B64: 11 | C64: Create a OOS Endorsement transaction
B65: 12 | C65: Navigate to the homeowners coverage page
B66: 13 | C66: Add Additional location
B67: 14 | C67: Navigate to Location coverage page of the new location
B68: 15 | C68: On the Flood information block verify that RiskMeter Flood Zone is pulled | D68: RiskMeter Flood Zone is pulled
B69: 16 | C69: Verify that Panel Number is pulled | D69: Panel Number is pulled
B70: 17 | C70: Verify that Soil Type is pulled | D70: Soil Type is pulled
B71: 18 | C71: Verify that Flood ID is pulled | D71: Flood ID is pulled
B72: 19 | C72: Populate all the mandatory fields
B73: 20 | C73: Issue the OOS Endorsement transaction
B74: 21 | C74: After the rollforward navigate back to the Flood information page
B75: 22 | C75: On the Flood information block verify that RiskMeter Flood Zone is pulled | D75: RiskMeter Flood Zone is pulled
B76: 23 | C76: Verify that Panel Number is pulled | D76: Panel Number is pulled
B77: 24 | C77: Verify that Soil Type is pulled | D77: Soil Type is pulled
B78: 25 | C78: Verify that Flood ID is pulled | D78: Flood ID is pulled
A80: Test Case # 4 Verify that the Flood information is pulled on Renewal HO LOB | B80: 1 | C80: Enter to Dragon as an underwriter. | E80: N | F80: Y | G80: Automated
B81: 2 | C81: Create a HO quote
B82: 3 | C82: Navigate to Location coverage page
B83: 4 | C83: On the Flood information block verify that RiskMeter Flood Zone is pulled | D83: RiskMeter Flood Zone is pulled
B84: 5 | C84: Verify that Panel Number is pulled | D84: Panel Number is pulled
B85: 6 | C85: Verify that Soil Type is pulled | D85: Soil Type is pulled
B86: 7 | C86: Verify that Flood ID is pulled | D86: Flood ID is pulled
B87: 8 | C87: Populate all the mandatory fields
B88: 9 | C88: Bind the quote into a policy
B89: 10 | C89: Create a Renewal transaction
B90: 11 | C90: Navigate to the homeowners coverage page
B91: 12 | C91: Add Additional location
B92: 13 | C92: Navigate to Location coverage page of the new location
B93: 14 | C93: On the Flood information block verify that RiskMeter Flood Zone is pulled | D93: RiskMeter Flood Zone is pulled
B94: 15 | C94: Verify that Panel Number is pulled | D94: Panel Number is pulled
B95: 16 | C95: Verify that Soil Type is pulled | D95: Soil Type is pulled
B96: 17 | C96: Verify that Flood ID is pulled | D96: Flood ID is pulled
B97: 18 | C97: Populate all the mandatory fields
B98: 19 | C98: Process the Renewal transaction
A100: Test Case # 5 Verify that the Flood information is pulled on NB Rewrite HO LOB | B100: 1 | C100: Enter to Dragon as an underwriter. | E100: N | F100: Y | G100: Automated
B101: 2 | C101: Create a HO quote
B102: 3 | C102: Navigate to Location coverage page
B103: 4 | C103: On the Flood information block verify that RiskMeter Flood Zone is pulled | D103: RiskMeter Flood Zone is pulled
B104: 5 | C104: Verify that Panel Number is pulled | D104: Panel Number is pulled
B105: 6 | C105: Verify that Soil Type is pulled | D105: Soil Type is pulled
B106: 7 | C106: Verify that Flood ID is pulled | D106: Flood ID is pulled
B107: 8 | C107: Populate all the mandatory fields
B108: 9 | C108: Bind the quote into a policy
B109: 10 | C109: Create Cancellation transaction
...

Sheet Earthquake report
A1: Back to Summary
A2: Earthquake report
A3: STG Environment
A4: Objective: | B4: 1 | C4: Validate Earthquake report functionality.
A6: Data: | B6: 1 | C6: Role: Underwriter Agent Broker Number: User: Password:
B7: 2
B8: 3
A10: Preconditions: | B10: 1 | C10: Access to the Dragon application
B11: 2
B12: 3
B13: 4
A15: Status: | B15: N | C15: = Not executed by QA
B16: P | C16: = Passed by QA
B17: F | C17: = Failed by QA
B18: T | C18: = Testing in progress
B19: R | C19: = Rejected / Existing issue
B20: B | C20: = Blocked by QA
A22: Description | B22: # | C22: Steps | D22: Expected Results | E22: Status | F22: Automation status | G22: Comments | H22: Defect ID /Blocked reason
A24: Test Case # 1 Verify that when an Underwriter creates Admitted Homeowners Quote - Earthquake reports are pulled | B24: 1 | C24: Enter to Dragon as an underwriter. | E24: N | F24: Y | G24: Automated
B25: 2 | C25: Create a HO quote in any of the following states: CA, OR, ID, WA
B26: 3 | C26: Navigate to Earthquake page
B27: 4 | C27: On the Earthquake reports block verify that MMI Reports are pulled | D27: MMI Reports are pulled
B28: 5 | C28: Verify that Soil Grade is pulled | D28: Soil Grade is pulled
B29: 6 | C29: Verify that Soil Type is pulled | D29: Soil Type is pulled
B30: 7 | C30: Populate all the mandatory fields
B31: 8 | C31: Bind the quote into a policy
A33: Test Case # 2 Verify that the Earthquake Report is pulled on Endorsement for new Risk location | B33: 1 | C33: Enter to Dragon as an underwriter. | E33: N | F33: Y | G33: Automated
B34: 2 | C34: Create a HO quote in any of the following states: CA, OR, ID, WA
B35: 3 | C35: Navigate to Earthquake page
B36: 4 | C36: On the Earthquake reports block verify that MMI Reports are pulled | D36: MMI Reports are pulled
B37: 5 | C37: Verify that Soil Grade is pulled | D37: Soil Grade is pulled
B38: 6 | C38: Verify that Soil Type is pulled | D38: Soil Type is pulled
B39: 7 | C39: Populate all the mandatory fields
B40: 8 | C40: Bind the quote into a policy
B41: 9 | C41: Create an Endorsement transaction
B42: 10 | C42: Navigate to the homeowners coverage page
B43: 11 | C43: Add Additional location
B44: 12 | C44: Navigate to Earthquake page of the new location
B45: 13 | C45: On the Earthquake reports block verify that MMI Reports are pulled | D45: MMI Reports are pulled
B46: 14 | C46: Verify that Soil Grade is pulled | D46: Soil Grade is pulled
B47: 15 | C47: Verify that Soil Type is pulled | D47: Soil Type is pulled
B48: 16 | C48: Populate all the mandatory fields
B49: 17 | C49: Issue the Endorsement transaction
A51: Test Case # 3 Verify that the Earthquake Report is pulled on OOS Endorsement for new Risk location | B51: 1 | C51: Enter to Dragon as an underwriter. | E51: N | F51: Y | G51: Automated
B52: 2 | C52: Create a HO quote in any of the following states: CA, OR, ID, WA
B53: 3 | C53: Navigate to Earthquake page
B54: 4 | C54: On the Earthquake reports block verify that MMI Reports are pulled | D54: MMI Reports are pulled
B55: 5 | C55: Verify that Soil Grade is pulled | D55: Soil Grade is pulled
B56: 6 | C56: Verify that Soil Type is pulled | D56: Soil Type is pulled
B57: 7 | C57: Populate all the mandatory fields
B58: 8 | C58: Bind the quote into a policy
B59: 9 | C59: Create and issue a Renwal transaction
B60: 10 | C60: Create a OOS Endorsement transaction
B61: 11 | C61: Navigate to the homeowners coverage page
B62: 12 | C62: Add Additional location
B63: 13 | C63: Navigate to Earthquake page of the new location
B64: 14 | C64: On the Earthquake reports block verify that MMI Reports are pulled | D64: MMI Reports are pulled
B65: 15 | C65: Verify that Soil Grade is pulled | D65: Soil Grade is pulled
B66: 16 | C66: Verify that Soil Type is pulled | D66: Soil Type is pulled
B67: 17 | C67: Populate all the mandatory fields
B68: 18 | C68: Issue the OOS Endorsement transaction
B69: 19 | C69: After the rollforward navigate back to the Earthquake reports page
B70: 20 | C70: On the Earthquake reports block verify that MMI Reports are pulled | D70: MMI Reports are pulled
B71: 21 | C71: Verify that Soil Grade is pulled | D71: Soil Grade is pulled
B72: 22 | C72: Verify that Soil Type is pulled | D72: Soil Type is pulled
A74: Test Case # 4 Verify that the Earthquake Report is pulled on Renewal | B74: 1 | C74: Enter to Dragon as an underwriter. | E74: N | F74: Y | G74: Automated
B75: 2 | C75: Create a HO quote in any of the following states: CA, OR, ID, WA
B76: 3 | C76: Navigate to Earthquake page
B77: 4 | C77: On the Earthquake reports block verify that MMI Reports are pulled | D77: MMI Reports are pulled
B78: 5 | C78: Verify that Soil Grade is pulled | D78: Soil Grade is pulled
B79: 6 | C79: Verify that Soil Type is pulled | D79: Soil Type is pulled
B80: 7 | C80: Populate all the mandatory fields
B81: 8 | C81: Bind the quote into a policy
B82: 9 | C82: Create a Renewal transaction
B83: 10 | C83: Navigate to the homeowners coverage page
B84: 11 | C84: Add Additional location
B85: 12 | C85: Navigate to Earthquake page of the new location
B86: 13 | C86: On the Earthquake reports block verify that MMI Reports are pulled | D86: MMI Reports are pulled
B87: 14 | C87: Verify that Soil Grade is pulled | D87: Soil Grade is pulled
B88: 15 | C88: Verify that Soil Type is pulled | D88: Soil Type is pulled
B89: 16 | C89: Populate all the mandatory fields
B90: 17 | C90: Process the Renewal transaction
A92: Test Case # 5 Verify that the Earthquake Report is pulled on NB Rewrite | B92: 1 | C92: Enter to Dragon as an underwriter. | E92: N | F92: Y | G92: Automated
B93: 2 | C93: Create a HO quote in any of the following states: CA, OR, ID, WA
B94: 3 | C94: Navigate to Earthquake page
B95: 4 | C95: On the Earthquake reports block verify that MMI Reports are pulled | D95: MMI Reports are pulled
B96: 5 | C96: Verify that Soil Grade is pulled | D96: Soil Grade is pulled
B97: 6 | C97: Verify that Soil Type is pulled | D97: Soil Type is pulled
B98: 7 | C98: Populate all the mandatory fields
B99: 8 | C99: Bind the quote into a policy
B100: 9 | C100: Create Cancellation transaction
B101: 10 | C101: Set Cancellation Eff. Date = New Business
B102: 11 | C102: Cancellation Reason select = Cancel Rewrite
B103: 12 | C103: Process The Cancellation
B104: 13 | C104: Create New Business Rewrite transaction
B105: 14 | C105: Navigate to the homeowners coverage page
B106: 15 | C106: Add Additional location
B107: 16 | C107: Navigate to Earthquake page of the new location
B108: 17 | C108: On the Earthquake reports block verify that MMI Reports are pulled | D108: MMI Reports are pulled
B109: 18 | C109: Verify that Soil Grade is pulled | D109: Soil Grade is pulled
...

Sheet Wildfire Hazard reports
A1: Back to Summary
A2: Wildfire Hazard reports
A3: STG Environment
A4: Objective: | B4: 1 | C4: Validate Wildfire Hazard reports functionality.
A6: Data: | B6: 1 | C6: Role: Underwriter Agent Broker Number: User: Password:
B7: 2
B8: 3
A10: Preconditions: | B10: 1 | C10: Access to the application
B11: 2
B12: 3
B13: 4
A15: Status: | B15: N | C15: = Not executed by QA
B16: P | C16: = Passed by QA
B17: F | C17: = Failed by QA
B18: T | C18: = Testing in progress
B19: R | C19: = Rejected / Existing issue
B20: B | C20: = Blocked by QA
A22: Description | B22: # | C22: Steps | D22: Expected Results | E22: Status | F22: Automation status | G22: Comments | H22: Defect ID /Blocked reason
A24: Test Case # 1 Verify that when an Underwriter creates Admitted Homeowners Quote - Wildfire reports are pulled | B24: 1 | C24: Enter to Dragon as an underwriter. | E24: N | F24: Y | G24: Automated
B25: 2 | C25: Create a HO quote in any of the following states: CA, OR, ID, WA, TX
B26: 3 | C26: Navigate to Wildfire page
B27: 4 | C27: On the Wildfire reports block verify that Wildfire Hazard Severity is pulled | D27: Wildfire Hazard Severity is pulled
B28: 5 | C28: Verify that Wildfire Risk Factor is pulled | D28: Wildfire Risk Factor is pulled
B29: 6 | C29: Verify that Wildfire Risk Score is pulled | D29: Wildfire Risk Score is pulled
B30: 7 | C30: Populate all the mandatory fields
B31: 8 | C31: Bind the quote into a policy
A33: Test Case # 2 Verify that the Wildfire Report is pulled on Endorsement for new Risk location | B33: 1 | C33: Enter to Dragon as an underwriter. | E33: N | F33: Y | G33: Automated
B34: 2 | C34: Create a HO quote in any of the following states: CA, OR, ID, WA, TX
B35: 3 | C35: Navigate to Wildfire page
B36: 4 | C36: On the Wildfire reports block verify that Wildfire Hazard Severity is pulled | D36: Wildfire Hazard Severity is pulled
B37: 5 | C37: Verify that Wildfire Risk Factor is pulled | D37: Wildfire Risk Factor is pulled
B38: 6 | C38: Verify that Wildfire Risk Score is pulled | D38: Wildfire Risk Score is pulled
B39: 7 | C39: Populate all the mandatory fields
B40: 8 | C40: Bind the quote into a policy
B41: 9 | C41: Create an Endorsement transaction
B42: 10 | C42: Navigate to the homeowners coverage page
B43: 11 | C43: Add Additional location
B44: 12 | C44: Navigate to Wildfire page of the new location
B45: 13 | C45: On the Wildfire reports block verify that Wildfire Hazard Severity is pulled | D45: Wildfire Hazard Severity is pulled
B46: 14 | C46: Verify that Wildfire Risk Factor is pulled | D46: Wildfire Risk Factor is pulled
B47: 15 | C47: Verify that Wildfire Risk Score is pulled | D47: Wildfire Risk Score is pulled
B48: 16 | C48: Populate all the mandatory fields
B49: 17 | C49: Issue the Endorsement transaction
A51: Test Case # 3 Verify that the Wildfire Report is pulled on OOS Endorsement for new Risk location | B51: 1 | C51: Enter to Dragon as an underwriter. | E51: N | F51: Y | G51: Automated
B52: 2 | C52: Create a HO quote in any of the following states: CA, OR, ID, WA, TX
B53: 3 | C53: Navigate to Wildfire page
B54: 4 | C54: On the Wildfire reports block verify that Wildfire Hazard Severity is pulled | D54: Wildfire Hazard Severity is pulled
B55: 5 | C55: Verify that Wildfire Risk Factor is pulled | D55: Wildfire Risk Factor is pulled
B56: 6 | C56: Verify that Wildfire Risk Score is pulled | D56: Wildfire Risk Score is pulled
B57: 7 | C57: Populate all the mandatory fields
B58: 8 | C58: Bind the quote into a policy
B59: 9 | C59: Create and issue a Renwal transaction
B60: 10 | C60: Create a OOS Endorsement transaction
B61: 11 | C61: Navigate to the homeowners coverage page
B62: 12 | C62: Add Additional location
B63: 13 | C63: Navigate to Wildfire page of the new location
B64: 14 | C64: On the Wildfire reports block verify that Wildfire Hazard Severity is pulled | D64: Wildfire Hazard Severity is pulled
B65: 15 | C65: Verify that Wildfire Risk Factor is pulled | D65: Wildfire Risk Factor is pulled
B66: 16 | C66: Verify that Wildfire Risk Score is pulled | D66: Wildfire Risk Score is pulled
B67: 17 | C67: Populate all the mandatory fields
B68: 18 | C68: Issue the OOS Endorsement transaction
B69: 19 | C69: After the rollforward navigate back to the Wildfire reports page
B70: 20 | C70: On the Wildfire reports block verify that Wildfire Hazard Severity is pulled | D70: Wildfire Hazard Severity is pulled
B71: 21 | C71: Verify that Wildfire Risk Factor is pulled | D71: Wildfire Risk Factor is pulled
B72: 22 | C72: Verify that Wildfire Risk Score is pulled | D72: Wildfire Risk Score is pulled
A74: Test Case # 4 Verify that the Wildfire Report is pulled on Renewal | B74: 1 | C74: Enter to Dragon as an underwriter. | E74: N | F74: Y | G74: Automated
B75: 2 | C75: Create a HO quote in any of the following states: CA, OR, ID, WA, TX
B76: 3 | C76: Navigate to Wildfire page
B77: 4 | C77: On the Wildfire reports block verify that Wildfire Hazard Severity is pulled | D77: Wildfire Hazard Severity is pulled
B78: 5 | C78: Verify that Wildfire Risk Factor is pulled | D78: Wildfire Risk Factor is pulled
B79: 6 | C79: Verify that Wildfire Risk Score is pulled | D79: Wildfire Risk Score is pulled
B80: 7 | C80: Populate all the mandatory fields
B81: 8 | C81: Bind the quote into a policy
B82: 9 | C82: Create a Renewal transaction
B83: 10 | C83: Navigate to the homeowners coverage page
B84: 11 | C84: Add Additional location
B85: 12 | C85: Navigate to Wildfire page of the new location
B86: 13 | C86: On the Wildfire reports block verify that Wildfire Hazard Severity is pulled | D86: Wildfire Hazard Severity is pulled
B87: 14 | C87: Verify that Wildfire Risk Factor is pulled | D87: Wildfire Risk Factor is pulled
B88: 15 | C88: Verify that Wildfire Risk Score is pulled | D88: Wildfire Risk Score is pulled
B89: 16 | C89: Populate all the mandatory fields
B90: 17 | C90: Process the Renewal transaction
A92: Test Case # 5 Verify that the Wildfire Report is pulled on NB Rewrite | B92: 1 | C92: Enter to Dragon as an underwriter. | E92: N | F92: Y | G92: Automated
B93: 2 | C93: Create a HO quote in any of the following states: CA, OR, ID, WA, TX
B94: 3 | C94: Navigate to Wildfire page
B95: 4 | C95: On the Wildfire reports block verify that Wildfire Hazard Severity is pulled | D95: Wildfire Hazard Severity is pulled
B96: 5 | C96: Verify that Wildfire Risk Factor is pulled | D96: Wildfire Risk Factor is pulled
B97: 6 | C97: Verify that Wildfire Risk Score is pulled | D97: Wildfire Risk Score is pulled
B98: 7 | C98: Populate all the mandatory fields
B99: 8 | C99: Bind the quote into a policy
B100: 9 | C100: Create Cancellation transaction
B101: 10 | C101: Set Cancellation Eff. Date = New Business
B102: 11 | C102: Cancellation Reason select = Cancel Rewrite
B103: 12 | C103: Process The Cancellation
B104: 13 | C104: Create New Business Rewrite transaction
B105: 14 | C105: Navigate to the homeowners coverage page
B106: 15 | C106: Add Additional location
B107: 16 | C107: Navigate to Wildfire page of the new location
B108: 17 | C108: On the Wildfire reports block verify that Wildfire Hazard Severity is pulled | D108: Wildfire Hazard Severity is pulled
B109: 18 | C109: Verify that Wildfire Risk Factor is pulled | D109: Wildfire Risk Factor is pulled
...

Sheet Moratorium
A1: Back to Summary
A2: Moratorium
A3: STG Environment
A4: Objective: | B4: 1 | C4: Validate Moratorium functionality.
A6: Data: | B6: 1 | C6: Role: Underwriter Agent Broker Number: User: Password:
B7: 2
B8: 3
A10: Preconditions: | B10: 1 | C10: Access to the application
B11: 2 | C11: Senior UW Manager role
B12: 3
B13: 4
A15: Status: | B15: N | C15: = Not executed by QA
B16: P | C16: = Passed by QA
B17: F | C17: = Failed by QA
B18: T | C18: = Testing in progress
B19: R | C19: = Rejected / Existing issue
B20: B | C20: = Blocked by QA
A22: Description | B22: # | C22: Steps | D22: Expected Results | E22: Status | F22: Automation status | G22: Comments | H22: Defect ID /Blocked reason
A24: Test Case # 1 Verify that only Senior UW Manager role is able to see Moratorium page | B24: 1 | C24: Log into Dragon as Senior UW Manager role. | D24: Verify that only Senior UW Manager role is able to see Moratorium page | E24: N | F24: N/A | G24: N/A for Automation
B25: 2 | C25: Verify that only Senior UW Manager role is able to see Moratorium page
A30: Test Case # 2 Verify that Agent is not able to see moratorium page | B30: 1 | C30: Log into Dragon as External user - Agent | E30: N | F30: N/A | G30: N/A for Automation
B31: 2 | C31: Verify that Agent is not able to see moratorium page
A37: Test Case # 3 Verify that roles other then Senior UW Manager are not able to see Moratorium page | B37: 1 | C37: Log into Dragon as UW Manager | E37: N | F37: N/A | G37: N/A for Automation
B38: 2 | C38: Verify that UW Manager cannot see Moratorium page
B39: 3 | C39: Change the role to an Underwriter
B40: 4 | C40: Verify that Underwriter cannot see Moratorium page
B41: 5 | C41: Change the role to Senior UW Technician
B42: 6 | C42: Verify that Senior UW Technician cannot see Moratorium page
B43: 7 | C43: Change the role to UW Technician
B44: 8 | C44: Verify that UW Technician cannot see Moratorium page
B45: 9 | C45: Change the role to Inquery Only
B46: 10 | C46: Verify that Inquery Only cannot see Moratorium page
B47: 11 | C47: Change the role to Agency Marketing Manager
B48: 12 | C48: Verify that Agency Marketing Manager cannot see Moratorium page
B49: 13 | C49: Change the role to Agency Marketing Director
B50: 14 | C50: Verify that Agency Marketing Director cannot see Moratorium page
A52: Test Case # 4 Verify that a user that has "PURE Programs user only?" checkbox checked, will be able to see only Surplus Lines on Moratorium page | B52: 1 | C52: Log into Dragon application as Senior UW Manager | E52: N | F52: N/A | G52: N/A for Automation
B53: 2 | C53: Navigate to the User Setup page
B54: 3 | C54: Navigate to a specific user for testing
B55: 4 | C55: Check the "PURE Programs user only?" checkbox
B56: 5 | C56: Navigate back to the Dragon Home page
B57: 6 | C57: Navigate to the Moratorium page
